Workbook

Sheet 00_README_METHODOLOGY
A1: Fresh Thyme YTD SLA Reporting Package — Methodology & QA Notes
A3: Scope & Source
A4: • Source file: Fresh_Thyme_Year_to_Date_08_01_2025.xlsx — one sheet, 569 ticket records, 227 source columns, covering closed dates Aug 1, 2025 through Aug 11, 2026.
A5: • This is NCR field-service ticket data for Meijer Inc. (Account Name), reported under the Fresh Thyme banner (69 store locations across 10 states). Service Request Type is predominantly 'MNT' (maintenance, 414 tickets) and 'CHGC' (149 tickets), with 6 'CHGF'.
A6: • 01_RAW_DATA is a verbatim, unedited copy of the source for audit and reconciliation. All analysis is built on 02_CLEAN_DATA, a derived layer that never modifies the original values.
A8: SLA Methodology — the core logic
A9: • This dataset carries two SLA layers for ticket resolution: a raw/gross determination made at ticket close, and a mitigation-adjusted determination applied afterward through a vendor exception-review process. Both are preserved and reported separately, as requested.
A10: • RAW SLA: uses 'Service Level Agreement Resolve Met Indicator' (source column DZ) — the ticket-level pass/fail against its Resolve Limit Duration, before any mitigation review. Reported on 08_RESOLUTION_ANALYSIS and as a comparison figure; overall raw attainment among SLA-eligible tickets is 342/435 = 78.6%.
A11: • SLA ELIGIBILITY / OPPORTUNITY: uses 'Service Level Agreement Resolve Opportunity Indicator' (source column EB) exactly as instructed. EB = 1 means the ticket counts toward the SLA population after mitigation review (435 of 569 tickets); EB = 0 means it is excluded from the opportunity population entirely (134 tickets) — this happens both for tickets that are structurally out of SLA scope and for tickets where an approved mitigation removed them from consideration.
A12: • FINAL / ADJUSTED SLA MET (what this report calls 'Adjusted / Opportunity SLA'): for every ticket where Opportunity = 1, we take the 'Mitigated Service Level Agreement Resolve Met Indicator' (source column CE) when it has been populated (i.e., a mitigation was fully processed — 'Mitigated Indicator' = 2), and fall back to the 'Service Level Agreement Resolve Met Net Indicator' (source column EA) when no mitigation outcome was recorded for that ticket. This is computed as a live formula in 02_CLEAN_DATA column V ('Final SLA Met') and labeled in column W ('Final SLA Result': Met / Missed / Not Eligible).
A13: • This logic was validated by grouping the full dataset on every combination of Mitigated Indicator, Mitigation Reason, the four SLA indicator fields (DZ/EA/EB/CE), Reviewed Indicator, Exclude flag and ticket status — 16 distinct combinations covering all 569 rows — and confirming the Final SLA Met formula reproduces a fully reconciled 337 Met / 98 Missed / 134 Not Eligible split (337+98+134 = 569).
A14: • YTD Adjusted/Opportunity SLA % = 337 ÷ 435 = 77.5%. This is the headline SLA metric used on the dashboard and throughout the PowerPoint.
... A42: • All PowerPoint figures are pulled from this recalculated workbook — no independently recomputed numbers.

Sheet 03_EXECUTIVE_DASHBOARD
A1: FRESH THYME — YTD OPERATIONS / SLA PERFORMANCE REPORT
A3: Field Service SLA Analysis | Period: Aug 2025 – Aug 2026 | Vendor: NCR | Account: Meijer Inc. (Fresh Thyme banner)
A5: TOTAL TICKETS | C5: CLOSED TICKETS | E5: OPEN TICKETS | G5: CANCELED TICKETS | I5: SLA ELIGIBLE TICKETS
A6: =COUNTA('02_CLEAN_DATA'!$A$2:$A$570) -> 569 | C6: =COUNTIF('02_CLEAN_DATA'!$M$2:$M$570,"closed") -> 561 | E6: =COUNTIF('02_CLEAN_DATA'!$M$2:$M$570,"open") -> 1 | G6: =COUNTIF('02_CLEAN_DATA'!$M$2:$M$570,"canceled*") -> 7 | I6: =COUNTIF('02_CLEAN_DATA'!$R$2:$R$570,1) -> 435
A10: SLA MET | C10: SLA MISSED | E10: YTD SLA % (ADJUSTED) | G10: SLA TARGET (INPUT) | I10: VARIANCE TO TARGET (PP)
A11: =COUNTIF('02_CLEAN_DATA'!$W$2:$W$570,"Met") -> 337 | C11: =COUNTIF('02_CLEAN_DATA'!$W$2:$W$570,"Missed") -> 98 | E11: =COUNTIF('02_CLEAN_DATA'!$W$2:$W$570,"Met")/COUNTIF('02_CLEAN_DATA'!$R$2:$R$570,1) -> 0.77471264 | G11: =IF(ISBLANK('04_SLA_TREND'!$B$1),"Not Set",'04_SLA_TREND'!$B$1) -> Not Set | I11: =IF(ISBLANK('04_SLA_TREND'!$B$1),"Enter target",E11-'04_SLA_TREND'!$B$1) -> Enter target
A15: EXCEPTIONS (CCR) | C15: EXCEPTION RATE | E15: AVG RESOLUTION TIME (HRS) | G15: MEDIAN RESOLUTION (HRS) | I15: EXCLUDED FROM OPPORTUNITY
A16: =COUNTIF('02_CLEAN_DATA'!$S$2:$S$570,"Customer Contracted Reasons") -> 353 | C16: =COUNTIF('02_CLEAN_DATA'!$S$2:$S$570,"Customer Contracted Reasons")/COUNTA('02_CLEAN_DATA'!$A$2:$A$570) -> 0.62038664 | E16: =AVERAGE('02_CLEAN_DATA'!$O$2:$O$570) -> 30.227606 | G16: {=MEDIAN('02_CLEAN_DATA'!$O$2:$O$570)} -> 14.04 | I16: =COUNTIF('02_CLEAN_DATA'!$R$2:$R$570,0) -> 134
A21: Color reference bands used throughout this workbook: | D21: ≥ 90% SLA | F21: 80–90% SLA | H21: < 80% SLA
A22: These are common field-service reporting bands, not a Fresh Thyme/Meijer contracted figure — no target % is present in the source data. Enter an actual contracted target in the SLA Target card above (linked to 04_SLA_TREND!B1) to activate variance-to-target reporting workbook-wide.
A25: YTD Monthly SLA % Trend (Adjusted / Opportunity Basis) | H25: Ticket Mix
A47: Methodology: SLA % = Final SLA Met ÷ SLA Eligible tickets (Service Level Agreement Resolve Opportunity Indicator = 1), where Final SLA Met uses the Mitigated SLA Resolve Met Indicator when a mitigation has been fully processed, otherwise the Net SLA Resolve Met Indicator. Full methodology, data-quality notes and assumptions are documented in 00_README_METHODOLOGY.

Sheet 04_SLA_TREND
A1: Contracted SLA Target % | C1: << Input cell: enter Fresh Thyme / Meijer's contracted SLA target here (e.g. 0.90) to activate variance-to-target reporting. No target % is present in the source workbook, so it is intentionally left blank rather than assumed.
A2: Month | B2: Total Tickets | C2: SLA Eligible | D2: SLA Met | E2: SLA Missed | F2: SLA % | G2: Variance to Target (pp) | H2: Exceptions (CCR) | I2: Exception Rate | J2: Avg Resolution (Hrs) | K2: Median Resolution (Hrs)
A3: 2025-08 | B3: =COUNTIF('02_CLEAN_DATA'!$L$2:$L$570,A3) -> 39 | C3: =COUNTIFS('02_CLEAN_DATA'!$L$2:$L$570,A3,'02_CLEAN_DATA'!$R$2:$R$570,1) -> 19 | D3: =COUNTIFS('02_CLEAN_DATA'!$L$2:$L$570,A3,'02_CLEAN_DATA'!$W$2:$W$570,"Met") -> 15 | E3: =COUNTIFS('02_CLEAN_DATA'!$L$2:$L$570,A3,'02_CLEAN_DATA'!$W$2:$W$570,"Missed") -> 4 | F3: =IF(C3=0,"",D3/C3) -> 0.78947368 | G3: =IF(OR($B$1="",F3=""),"",F3-$B$1) | H3: =COUNTIFS('02_CLEAN_DATA'!$L$2:$L$570,A3,'02_CLEAN_DATA'!$S$2:$S$570,"Customer Contracted Reasons") -> 3 | I3: =IF(B3=0,"",H3/B3) -> 0.076923077 | J3: =IFERROR(AVERAGEIF('02_CLEAN_DATA'!$L$2:$L$570,A3,'02_CLEAN_DATA'!$O$2:$O$570),"") -> 32.271282 | K3: {=IFERROR(MEDIAN(IF('02_CLEAN_DATA'!$L$2:$L$570=A3,'02_CLEAN_DATA'!$O$2:$O$570)),"")} -> 21.25
A4: 2025-09 | B4: =COUNTIF('02_CLEAN_DATA'!$L$2:$L$570,A4) -> 57 | C4: =COUNTIFS('02_CLEAN_DATA'!$L$2:$L$570,A4,'02_CLEAN_DATA'!$R$2:$R$570,1) -> 44 | D4: =COUNTIFS('02_CLEAN_DATA'!$L$2:$L$570,A4,'02_CLEAN_DATA'!$W$2:$W$570,"Met") -> 31 | E4: =COUNTIFS('02_CLEAN_DATA'!$L$2:$L$570,A4,'02_CLEAN_DATA'!$W$2:$W$570,"Missed") -> 13 | F4: =IF(C4=0,"",D4/C4) -> 0.70454545 | G4: =IF(OR($B$1="",F4=""),"",F4-$B$1) | H4: =COUNTIFS('02_CLEAN_DATA'!$L$2:$L$570,A4,'02_CLEAN_DATA'!$S$2:$S$570,"Customer Contracted Reasons") -> 11 | I4: =IF(B4=0,"",H4/B4) -> 0.19298246 | J4: =IFERROR(AVERAGEIF('02_CLEAN_DATA'!$L$2:$L$570,A4,'02_CLEAN_DATA'!$O$2:$O$570),"") -> 42.746316 | K4: {=IFERROR(MEDIAN(IF('02_CLEAN_DATA'!$L$2:$L$570=A4,'02_CLEAN_DATA'!$O$2:$O$570)),"")} -> 14.85
A5: 2025-10 | B5: =COUNTIF('02_CLEAN_DATA'!$L$2:$L$570,A5) -> 56 | C5: =COUNTIFS('02_CLEAN_DATA'!$L$2:$L$570,A5,'02_CLEAN_DATA'!$R$2:$R$570,1) -> 37 | D5: =COUNTIFS('02_CLEAN_DATA'!$L$2:$L$570,A5,'02_CLEAN_DATA'!$W$2:$W$570,"Met") -> 23 | E5: =COUNTIFS('02_CLEAN_DATA'!$L$2:$L$570,A5,'02_CLEAN_DATA'!$W$2:$W$570,"Missed") -> 14 | F5: =IF(C5=0,"",D5/C5) -> 0.62162162 | G5: =IF(OR($B$1="",F5=""),"",F5-$B$1) | H5: =COUNTIFS('02_CLEAN_DATA'!$L$2:$L$570,A5,'02_CLEAN_DATA'!$S$2:$S$570,"Customer Contracted Reasons") -> 7 | I5: =IF(B5=0,"",H5/B5) -> 0.125 | J5: =IFERROR(AVERAGEIF('02_CLEAN_DATA'!$L$2:$L$570,A5,'02_CLEAN_DATA'!$O$2:$O$570),"") -> 41.202321 | K5: {=IFERROR(MEDIAN(IF('02_CLEAN_DATA'!$L$2:$L$570=A5,'02_CLEAN_DATA'!$O$2:$O$570)),"")} -> 20.875
A6: 2025-11 | B6: =COUNTIF('02_CLEAN_DATA'!$L$2:$L$570,A6) -> 44 | C6: =COUNTIFS('02_CLEAN_DATA'!$L$2:$L$570,A6,'02_CLEAN_DATA'!$R$2:$R$570,1) -> 28 | D6: =COUNTIFS('02_CLEAN_DATA'!$L$2:$L$570,A6,'02_CLEAN_DATA'!$W$2:$W$570,"Met") -> 11 | E6: =COUNTIFS('02_CLEAN_DATA'!$L$2:$L$570,A6,'02_CLEAN_DATA'!$W$2:$W$570,"Missed") -> 17 | F6: =IF(C6=0,"",D6/C6) -> 0.39285714 | G6: =IF(OR($B$1="",F6=""),"",F6-$B$1) | H6: =COUNTIFS('02_CLEAN_DATA'!$L$2:$L$570,A6,'02_CLEAN_DATA'!$S$2:$S$570,"Customer Contracted Reasons") -> 5 | I6: =IF(B6=0,"",H6/B6) -> 0.11363636 | J6: =IFERROR(AVERAGEIF('02_CLEAN_DATA'!$L$2:$L$570,A6,'02_CLEAN_DATA'!$O$2:$O$570),"") -> 59.275227 | K6: {=IFERROR(MEDIAN(IF('02_CLEAN_DATA'!$L$2:$L$570=A6,'02_CLEAN_DATA'!$O$2:$O$570)),"")} -> 15.5
A7: 2025-12 | B7: =COUNTIF('02_CLEAN_DATA'!$L$2:$L$570,A7) -> 50 | C7: =COUNTIFS('02_CLEAN_DATA'!$L$2:$L$570,A7,'02_CLEAN_DATA'!$R$2:$R$570,1) -> 39 | D7: =COUNTIFS('02_CLEAN_DATA'!$L$2:$L$570,A7,'02_CLEAN_DATA'!$W$2:$W$570,"Met") -> 32 | E7: =COUNTIFS('02_CLEAN_DATA'!$L$2:$L$570,A7,'02_CLEAN_DATA'!$W$2:$W$570,"Missed") -> 7 | F7: =IF(C7=0,"",D7/C7) -> 0.82051282 | G7: =IF(OR($B$1="",F7=""),"",F7-$B$1) | H7: =COUNTIFS('02_CLEAN_DATA'!$L$2:$L$570,A7,'02_CLEAN_DATA'!$S$2:$S$570,"Customer Contracted Reasons") -> 8 | I7: =IF(B7=0,"",H7/B7) -> 0.16 | J7: =IFERROR(AVERAGEIF('02_CLEAN_DATA'!$L$2:$L$570,A7,'02_CLEAN_DATA'!$O$2:$O$570),"") -> 23.1098 | K7: {=IFERROR(MEDIAN(IF('02_CLEAN_DATA'!$L$2:$L$570=A7,'02_CLEAN_DATA'!$O$2:$O$570)),"")} -> 12.67
A8: 2026-01 | B8: =COUNTIF('02_CLEAN_DATA'!$L$2:$L$570,A8) -> 57 | C8: =COUNTIFS('02_CLEAN_DATA'!$L$2:$L$570,A8,'02_CLEAN_DATA'!$R$2:$R$570,1) -> 38 | D8: =COUNTIFS('02_CLEAN_DATA'!$L$2:$L$570,A8,'02_CLEAN_DATA'!$W$2:$W$570,"Met") -> 28 | E8: =COUNTIFS('02_CLEAN_DATA'!$L$2:$L$570,A8,'02_CLEAN_DATA'!$W$2:$W$570,"Missed") -> 10 | F8: =IF(C8=0,"",D8/C8) -> 0.73684211 | G8: =IF(OR($B$1="",F8=""),"",F8-$B$1) | H8: =COUNTIFS('02_CLEAN_DATA'!$L$2:$L$570,A8,'02_CLEAN_DATA'!$S$2:$S$570,"Customer Contracted Reasons") -> 57 | I8: =IF(B8=0,"",H8/B8) -> 1 | J8: =IFERROR(AVERAGEIF('02_CLEAN_DATA'!$L$2:$L$570,A8,'02_CLEAN_DATA'!$O$2:$O$570),"") -> 22.958246 | K8: {=IFERROR(MEDIAN(IF('02_CLEAN_DATA'!$L$2:$L$570=A8,'02_CLEAN_DATA'!$O$2:$O$570)),"")} -> 4.13
A9: 2026-02 | B9: =COUNTIF('02_CLEAN_DATA'!$L$2:$L$570,A9) -> 41 | C9: =COUNTIFS('02_CLEAN_DATA'!$L$2:$L$570,A9,'02_CLEAN_DATA'!$R$2:$R$570,1) -> 40 | D9: =COUNTIFS('02_CLEAN_DATA'!$L$2:$L$570,A9,'02_CLEAN_DATA'!$W$2:$W$570,"Met") -> 40 | E9: =COUNTIFS('02_CLEAN_DATA'!$L$2:$L$570,A9,'02_CLEAN_DATA'!$W$2:$W$570,"Missed") -> 0 | F9: =IF(C9=0,"",D9/C9) -> 1 | G9: =IF(OR($B$1="",F9=""),"",F9-$B$1) | H9: =COUNTIFS('02_CLEAN_DATA'!$L$2:$L$570,A9,'02_CLEAN_DATA'!$S$2:$S$570,"Customer Contracted Reasons") -> 41 | I9: =IF(B9=0,"",H9/B9) -> 1 | J9: =IFERROR(AVERAGEIF('02_CLEAN_DATA'!$L$2:$L$570,A9,'02_CLEAN_DATA'!$O$2:$O$570),"") -> 11.812439 | K9: {=IFERROR(MEDIAN(IF('02_CLEAN_DATA'!$L$2:$L$570=A9,'02_CLEAN_DATA'!$O$2:$O$570)),"")} -> 3.48
A10: 2026-03 | B10: =COUNTIF('02_CLEAN_DATA'!$L$2:$L$570,A10) -> 45 | C10: =COUNTIFS('02_CLEAN_DATA'!$L$2:$L$570,A10,'02_CLEAN_DATA'!$R$2:$R$570,1) -> 45 | D10: =COUNTIFS('02_CLEAN_DATA'!$L$2:$L$570,A10,'02_CLEAN_DATA'!$W$2:$W$570,"Met") -> 40 | E10: =COUNTIFS('02_CLEAN_DATA'!$L$2:$L$570,A10,'02_CLEAN_DATA'!$W$2:$W$570,"Missed") -> 5 | F10: =IF(C10=0,"",D10/C10) -> 0.88888889 | G10: =IF(OR($B$1="",F10=""),"",F10-$B$1) | H10: =COUNTIFS('02_CLEAN_DATA'!$L$2:$L$570,A10,'02_CLEAN_DATA'!$S$2:$S$570,"Customer Contracted Reasons") -> 45 | I10: =IF(B10=0,"",H10/B10) -> 1 | J10: =IFERROR(AVERAGEIF('02_CLEAN_DATA'!$L$2:$L$570,A10,'02_CLEAN_DATA'!$O$2:$O$570),"") -> 31.538889 | K10: {=IFERROR(MEDIAN(IF('02_CLEAN_DATA'!$L$2:$L$570=A10,'02_CLEAN_DATA'!$O$2:$O$570)),"")} -> 17.63
A11: 2026-04 | B11: =COUNTIF('02_CLEAN_DATA'!$L$2:$L$570,A11) -> 40 | C11: =COUNTIFS('02_CLEAN_DATA'!$L$2:$L$570,A11,'02_CLEAN_DATA'!$R$2:$R$570,1) -> 40 | D11: =COUNTIFS('02_CLEAN_DATA'!$L$2:$L$570,A11,'02_CLEAN_DATA'!$W$2:$W$570,"Met") -> 39 | E11: =COUNTIFS('02_CLEAN_DATA'!$L$2:$L$570,A11,'02_CLEAN_DATA'!$W$2:$W$570,"Missed") -> 1 | F11: =IF(C11=0,"",D11/C11) -> 0.975 | G11: =IF(OR($B$1="",F11=""),"",F11-$B$1) | H11: =COUNTIFS('02_CLEAN_DATA'!$L$2:$L$570,A11,'02_CLEAN_DATA'!$S$2:$S$570,"Customer Contracted Reasons") -> 40 | I11: =IF(B11=0,"",H11/B11) -> 1 | J11: =IFERROR(AVERAGEIF('02_CLEAN_DATA'!$L$2:$L$570,A11,'02_CLEAN_DATA'!$O$2:$O$570),"") -> 15.99125 | K11: {=IFERROR(MEDIAN(IF('02_CLEAN_DATA'!$L$2:$L$570=A11,'02_CLEAN_DATA'!$O$2:$O$570)),"")} -> 6.84
A12: 2026-05 | B12: =COUNTIF('02_CLEAN_DATA'!$L$2:$L$570,A12) -> 38 | C12: =COUNTIFS('02_CLEAN_DATA'!$L$2:$L$570,A12,'02_CLEAN_DATA'!$R$2:$R$570,1) -> 35 | D12: =COUNTIFS('02_CLEAN_DATA'!$L$2:$L$570,A12,'02_CLEAN_DATA'!$W$2:$W$570,"Met") -> 30 | E12: =COUNTIFS('02_CLEAN_DATA'!$L$2:$L$570,A12,'02_CLEAN_DATA'!$W$2:$W$570,"Missed") -> 5 | F12: =IF(C12=0,"",D12/C12) -> 0.85714286 | G12: =IF(OR($B$1="",F12=""),"",F12-$B$1) | H12: =COUNTIFS('02_CLEAN_DATA'!$L$2:$L$570,A12,'02_CLEAN_DATA'!$S$2:$S$570,"Customer Contracted Reasons") -> 38 | I12: =IF(B12=0,"",H12/B12) -> 1 | J12: =IFERROR(AVERAGEIF('02_CLEAN_DATA'!$L$2:$L$570,A12,'02_CLEAN_DATA'!$O$2:$O$570),"") -> 20.961053 | K12: {=IFERROR(MEDIAN(IF('02_CLEAN_DATA'!$L$2:$L$570=A12,'02_CLEAN_DATA'!$O$2:$O$570)),"")} -> 14.525
A13: 2026-06 | B13: =COUNTIF('02_CLEAN_DATA'!$L$2:$L$570,A13) -> 42 | C13: =COUNTIFS('02_CLEAN_DATA'!$L$2:$L$570,A13,'02_CLEAN_DATA'!$R$2:$R$570,1) -> 30 | D13: =COUNTIFS('02_CLEAN_DATA'!$L$2:$L$570,A13,'02_CLEAN_DATA'!$W$2:$W$570,"Met") -> 18 | E13: =COUNTIFS('02_CLEAN_DATA'!$L$2:$L$570,A13,'02_CLEAN_DATA'!$W$2:$W$570,"Missed") -> 12 | F13: =IF(C13=0,"",D13/C13) -> 0.6 | G13: =IF(OR($B$1="",F13=""),"",F13-$B$1) | H13: =COUNTIFS('02_CLEAN_DATA'!$L$2:$L$570,A13,'02_CLEAN_DATA'!$S$2:$S$570,"Customer Contracted Reasons") -> 42 | I13: =IF(B13=0,"",H13/B13) -> 1 | J13: =IFERROR(AVERAGEIF('02_CLEAN_DATA'!$L$2:$L$570,A13,'02_CLEAN_DATA'!$O$2:$O$570),"") -> 30.885952 | K13: {=IFERROR(MEDIAN(IF('02_CLEAN_DATA'!$L$2:$L$570=A13,'02_CLEAN_DATA'!$O$2:$O$570)),"")} -> 20.125
A14: 2026-07 | B14: =COUNTIF('02_CLEAN_DATA'!$L$2:$L$570,A14) -> 43 | C14: =COUNTIFS('02_CLEAN_DATA'!$L$2:$L$570,A14,'02_CLEAN_DATA'!$R$2:$R$570,1) -> 29 | D14: =COUNTIFS('02_CLEAN_DATA'!$L$2:$L$570,A14,'02_CLEAN_DATA'!$W$2:$W$570,"Met") -> 19 | E14: =COUNTIFS('02_CLEAN_DATA'!$L$2:$L$570,A14,'02_CLEAN_DATA'!$W$2:$W$570,"Missed") -> 10 | F14: =IF(C14=0,"",D14/C14) -> 0.65517241 | G14: =IF(OR($B$1="",F14=""),"",F14-$B$1) | H14: =COUNTIFS('02_CLEAN_DATA'!$L$2:$L$570,A14,'02_CLEAN_DATA'!$S$2:$S$570,"Customer Contracted Reasons") -> 43 | I14: =IF(B14=0,"",H14/B14) -> 1 | J14: =IFERROR(AVERAGEIF('02_CLEAN_DATA'!$L$2:$L$570,A14,'02_CLEAN_DATA'!$O$2:$O$570),"") -> 30.18186 | K14: {=IFERROR(MEDIAN(IF('02_CLEAN_DATA'!$L$2:$L$570=A14,'02_CLEAN_DATA'!$O$2:$O$570)),"")} -> 16.55
A15: 2026-08 | B15: =COUNTIF('02_CLEAN_DATA'!$L$2:$L$570,A15) -> 16 | C15: =COUNTIFS('02_CLEAN_DATA'!$L$2:$L$570,A15,'02_CLEAN_DATA'!$R$2:$R$570,1) -> 11 | D15: =COUNTIFS('02_CLEAN_DATA'!$L$2:$L$570,A15,'02_CLEAN_DATA'!$W$2:$W$570,"Met") -> 11 | E15: =COUNTIFS('02_CLEAN_DATA'!$L$2:$L$570,A15,'02_CLEAN_DATA'!$W$2:$W$570,"Missed") -> 0 | F15: =IF(C15=0,"",D15/C15) -> 1 | G15: =IF(OR($B$1="",F15=""),"",F15-$B$1) | H15: =COUNTIFS('02_CLEAN_DATA'!$L$2:$L$570,A15,'02_CLEAN_DATA'!$S$2:$S$570,"Customer Contracted Reasons") -> 13 | I15: =IF(B15=0,"",H15/B15) -> 0.8125 | J15: =IFERROR(AVERAGEIF('02_CLEAN_DATA'!$L$2:$L$570,A15,'02_CLEAN_DATA'!$O$2:$O$570),"") -> 9.990625 | K15: {=IFERROR(MEDIAN(IF('02_CLEAN_DATA'!$L$2:$L$570=A15,'02_CLEAN_DATA'!$O$2:$O$570)),"")} -> 5.61
A16: YTD TOTAL | B16: =SUM(B3:B15) -> 568 | C16: =SUM(C3:C15) -> 435 | D16: =SUM(D3:D15) -> 337 | E16: =SUM(E3:E15) -> 98 | F16: =IF(C16=0,"",D16/C16) -> 0.77471264 | G16: =IF(OR($B$1="",F16=""),"",F16-$B$1) | H16: =SUM(H3:H15) -> 353 | I16: =IF(B16=0,"",H16/B16) -> 0.62147887 | J16: {=AVERAGE('02_CLEAN_DATA'!$O$2:$O$570)} -> 30.227606 | K16: {=MEDIAN('02_CLEAN_DATA'!$O$2:$O$570)} -> 14.04
A18: SLA % = Final SLA Met ÷ SLA Eligible tickets for the month (Adjusted / Opportunity basis — see 00_README). Enter a contracted target in B1 to populate the variance column and the reference elsewhere in this workbook. Monthly ticket totals sum to 568 of 569 YTD tickets — the one open (unclosed) ticket has no Closed Date and is therefore not bucketed into any month; it is still counted in the workbook-wide Total Tickets KPI.

Sheet 05_EXCEPTIONS_MITIGATIONS
A1: Exception / Mitigation Analysis — Column CJ (Mitigation Reason Description)
A3: Overall Distribution (All Tickets)
A4: Category | B4: Ticket Count | C4: % of All Tickets
A5: Customer Contracted Reasons | B5: =COUNTIF('02_CLEAN_DATA'!$S$2:$S$570,"Customer Contracted Reasons") -> 353 | C5: =B5/COUNTA('02_CLEAN_DATA'!$S$2:$S$570) -> 0.62038664
A6: No Exception | B6: =COUNTIF('02_CLEAN_DATA'!$S$2:$S$570,"No Exception") -> 216 | C6: =B6/COUNTA('02_CLEAN_DATA'!$S$2:$S$570) -> 0.37961336
A7: TOTAL | B7: =SUM(B5:B6) -> 569 | C7: =SUM(C5:C6) -> 1
A9: SLA Performance: Exception-Tagged vs No-Exception Tickets (SLA-Eligible Population Only)
A10: Category | B10: SLA Eligible | C10: SLA Met | D10: SLA Missed | E10: SLA % | F10: Avg Resolution (Hrs)
A11: Customer Contracted Reasons | B11: =COUNTIFS('02_CLEAN_DATA'!$S$2:$S$570,"Customer Contracted Reasons",'02_CLEAN_DATA'!$R$2:$R$570,1) -> 288 | C11: =COUNTIFS('02_CLEAN_DATA'!$S$2:$S$570,"Customer Contracted Reasons",'02_CLEAN_DATA'!$W$2:$W$570,"Met") -> 224 | D11: =COUNTIFS('02_CLEAN_DATA'!$S$2:$S$570,"Customer Contracted Reasons",'02_CLEAN_DATA'!$W$2:$W$570,"Missed") -> 64 | E11: =IF(B11=0,"",C11/B11) -> 0.77777778 | F11: {=IFERROR(AVERAGE(IF('02_CLEAN_DATA'!$S$2:$S$570="Customer Contracted Reasons",'02_CLEAN_DATA'!$O$2:$O$570)),"")} -> 32.344476
A12: No Exception | B12: =COUNTIFS('02_CLEAN_DATA'!$S$2:$S$570,"No Exception",'02_CLEAN_DATA'!$R$2:$R$570,1) -> 147 | C12: =COUNTIFS('02_CLEAN_DATA'!$S$2:$S$570,"No Exception",'02_CLEAN_DATA'!$W$2:$W$570,"Met") -> 113 | D12: =COUNTIFS('02_CLEAN_DATA'!$S$2:$S$570,"No Exception",'02_CLEAN_DATA'!$W$2:$W$570,"Missed") -> 34 | E12: =IF(B12=0,"",C12/B12) -> 0.76870748 | F12: {=IFERROR(AVERAGE(IF('02_CLEAN_DATA'!$S$2:$S$570="No Exception",'02_CLEAN_DATA'!$O$2:$O$570)),"")} -> 26.628148
A14: Interpretation note: this compares outcomes for tickets carrying a 'Customer Contracted Reasons' mitigation against tickets with none. It shows association, not causation — a mitigation reason describes why a ticket was reviewed for adjustment, not a guarantee that it changed the SLA outcome. See 00_README for exact logic.
A21: Monthly Exception Trend
A22: Month | B22: Total Tickets | C22: Exceptions (CCR) | D22: Exception Rate
A23: 2025-08 | B23: =COUNTIF('02_CLEAN_DATA'!$L$2:$L$570,A23) -> 39 | C23: =COUNTIFS('02_CLEAN_DATA'!$L$2:$L$570,A23,'02_CLEAN_DATA'!$S$2:$S$570,"Customer Contracted Reasons") -> 3 | D23: =IF(B23=0,"",C23/B23) -> 0.076923077
A24: 2025-09 | B24: =COUNTIF('02_CLEAN_DATA'!$L$2:$L$570,A24) -> 57 | C24: =COUNTIFS('02_CLEAN_DATA'!$L$2:$L$570,A24,'02_CLEAN_DATA'!$S$2:$S$570,"Customer Contracted Reasons") -> 11 | D24: =IF(B24=0,"",C24/B24) -> 0.19298246
A25: 2025-10 | B25: =COUNTIF('02_CLEAN_DATA'!$L$2:$L$570,A25) -> 56 | C25: =COUNTIFS('02_CLEAN_DATA'!$L$2:$L$570,A25,'02_CLEAN_DATA'!$S$2:$S$570,"Customer Contracted Reasons") -> 7 | D25: =IF(B25=0,"",C25/B25) -> 0.125
A26: 2025-11 | B26: =COUNTIF('02_CLEAN_DATA'!$L$2:$L$570,A26) -> 44 | C26: =COUNTIFS('02_CLEAN_DATA'!$L$2:$L$570,A26,'02_CLEAN_DATA'!$S$2:$S$570,"Customer Contracted Reasons") -> 5 | D26: =IF(B26=0,"",C26/B26) -> 0.11363636
A27: 2025-12 | B27: =COUNTIF('02_CLEAN_DATA'!$L$2:$L$570,A27) -> 50 | C27: =COUNTIFS('02_CLEAN_DATA'!$L$2:$L$570,A27,'02_CLEAN_DATA'!$S$2:$S$570,"Customer Contracted Reasons") -> 8 | D27: =IF(B27=0,"",C27/B27) -> 0.16
A28: 2026-01 | B28: =COUNTIF('02_CLEAN_DATA'!$L$2:$L$570,A28) -> 57 | C28: =COUNTIFS('02_CLEAN_DATA'!$L$2:$L$570,A28,'02_CLEAN_DATA'!$S$2:$S$570,"Customer Contracted Reasons") -> 57 | D28: =IF(B28=0,"",C28/B28) -> 1
A29: 2026-02 | B29: =COUNTIF('02_CLEAN_DATA'!$L$2:$L$570,A29) -> 41 | C29: =COUNTIFS('02_CLEAN_DATA'!$L$2:$L$570,A29,'02_CLEAN_DATA'!$S$2:$S$570,"Customer Contracted Reasons") -> 41 | D29: =IF(B29=0,"",C29/B29) -> 1
A30: 2026-03 | B30: =COUNTIF('02_CLEAN_DATA'!$L$2:$L$570,A30) -> 45 | C30: =COUNTIFS('02_CLEAN_DATA'!$L$2:$L$570,A30,'02_CLEAN_DATA'!$S$2:$S$570,"Customer Contracted Reasons") -> 45 | D30: =IF(B30=0,"",C30/B30) -> 1
A31: 2026-04 | B31: =COUNTIF('02_CLEAN_DATA'!$L$2:$L$570,A31) -> 40 | C31: =COUNTIFS('02_CLEAN_DATA'!$L$2:$L$570,A31,'02_CLEAN_DATA'!$S$2:$S$570,"Customer Contracted Reasons") -> 40 | D31: =IF(B31=0,"",C31/B31) -> 1
A32: 2026-05 | B32: =COUNTIF('02_CLEAN_DATA'!$L$2:$L$570,A32) -> 38 | C32: =COUNTIFS('02_CLEAN_DATA'!$L$2:$L$570,A32,'02_CLEAN_DATA'!$S$2:$S$570,"Customer Contracted Reasons") -> 38 | D32: =IF(B32=0,"",C32/B32) -> 1
A33: 2026-06 | B33: =COUNTIF('02_CLEAN_DATA'!$L$2:$L$570,A33) -> 42 | C33: =COUNTIFS('02_CLEAN_DATA'!$L$2:$L$570,A33,'02_CLEAN_DATA'!$S$2:$S$570,"Customer Contracted Reasons") -> 42 | D33: =IF(B33=0,"",C33/B33) -> 1
A34: 2026-07 | B34: =COUNTIF('02_CLEAN_DATA'!$L$2:$L$570,A34) -> 43 | C34: =COUNTIFS('02_CLEAN_DATA'!$L$2:$L$570,A34,'02_CLEAN_DATA'!$S$2:$S$570,"Customer Contracted Reasons") -> 43 | D34: =IF(B34=0,"",C34/B34) -> 1
A35: 2026-08 | B35: =COUNTIF('02_CLEAN_DATA'!$L$2:$L$570,A35) -> 16 | C35: =COUNTIFS('02_CLEAN_DATA'!$L$2:$L$570,A35,'02_CLEAN_DATA'!$S$2:$S$570,"Customer Contracted Reasons") -> 13 | D35: =IF(B35=0,"",C35/B35) -> 0.8125
A37: Key observation: the 'Customer Contracted Reasons' exception rate rose sharply starting January 2026 — from roughly 10-20% of monthly tickets in Aug-Dec 2025 to effectively 100% of tickets every month from Jan 2026 through Jul 2026. This coincides with the Mitigated Indicator field showing fully-processed mitigations (value 2) appearing for the first time in Jan 2026 (0 occurrences before). This is a material change in how exceptions are being applied and is recommended for review with the service vendor.

Sheet 06_STORE_ANALYSIS
A1: Store # | B1: Store Name | C1: City | D1: State | E1: Total Tickets | F1: SLA Eligible | G1: SLA Met | H1: SLA Missed | I1: SLA % | J1: Exceptions (CCR) | K1: Exception Rate | L1: Avg Resolution (Hrs) | M1: Median Resolution (Hrs) | N1: Rank Key (Avg Res, 5+ tickets) | O1: Rank Key (SLA %, 5+ tickets) | P1: Rank Key (Missed Count) | Q1: Rank Key (Below-Target, 10+ tickets)
A2: 448 | B2: Fresh Thyme #448 | C2: St. Louis | D2: MO | E2: =COUNTIF('02_CLEAN_DATA'!$B$2:$B$570,A2) -> 8 | F2: =COUNTIFS('02_CLEAN_DATA'!$B$2:$B$570,A2,'02_CLEAN_DATA'!$R$2:$R$570,1) -> 4 | G2: =COUNTIFS('02_CLEAN_DATA'!$B$2:$B$570,A2,'02_CLEAN_DATA'!$W$2:$W$570,"Met") -> 3 | H2: =COUNTIFS('02_CLEAN_DATA'!$B$2:$B$570,A2,'02_CLEAN_DATA'!$W$2:$W$570,"Missed") -> 1 | I2: =IF(F2=0,"",G2/F2) -> 0.75 | J2: =COUNTIFS('02_CLEAN_DATA'!$B$2:$B$570,A2,'02_CLEAN_DATA'!$S$2:$S$570,"Customer Contracted Reasons") -> 3 | K2: =IF(E2=0,"",J2/E2) -> 0.375 | L2: =IFERROR(AVERAGEIF('02_CLEAN_DATA'!$B$2:$B$570,A2,'02_CLEAN_DATA'!$O$2:$O$570),"") -> 13.93875 | M2: {=IFERROR(MEDIAN(IF('02_CLEAN_DATA'!$B$2:$B$570=A2,'02_CLEAN_DATA'!$O$2:$O$570)),"")} -> 8.35 | N2: =IF(E2>=5,L2+ROW()/10000000,"") -> 13.93875 | O2: =IF(E2>=5,I2+ROW()/10000000,"") -> 0.7500002 | P2: =H2+ROW()/10000000 -> 1.0000002 | Q2: =IF(AND(E2>=10,I2<>""),(1-I2)+ROW()/10000000,"")
A3: 491 | B3: Fresh Thyme #491 | C3: Kirkwood | D3: MO | E3: =COUNTIF('02_CLEAN_DATA'!$B$2:$B$570,A3) -> 4 | F3: =COUNTIFS('02_CLEAN_DATA'!$B$2:$B$570,A3,'02_CLEAN_DATA'!$R$2:$R$570,1) -> 1 | G3: =COUNTIFS('02_CLEAN_DATA'!$B$2:$B$570,A3,'02_CLEAN_DATA'!$W$2:$W$570,"Met") -> 1 | H3: =COUNTIFS('02_CLEAN_DATA'!$B$2:$B$570,A3,'02_CLEAN_DATA'!$W$2:$W$570,"Missed") -> 0 | I3: =IF(F3=0,"",G3/F3) -> 1 | J3: =COUNTIFS('02_CLEAN_DATA'!$B$2:$B$570,A3,'02_CLEAN_DATA'!$S$2:$S$570,"Customer Contracted Reasons") -> 0 | K3: =IF(E3=0,"",J3/E3) -> 0 | L3: =IFERROR(AVERAGEIF('02_CLEAN_DATA'!$B$2:$B$570,A3,'02_CLEAN_DATA'!$O$2:$O$570),"") -> 27.7375 | M3: {=IFERROR(MEDIAN(IF('02_CLEAN_DATA'!$B$2:$B$570=A3,'02_CLEAN_DATA'!$O$2:$O$570)),"")} -> 11.1 | N3: =IF(E3>=5,L3+ROW()/10000000,"") | O3: =IF(E3>=5,I3+ROW()/10000000,"") | P3: =H3+ROW()/10000000 -> 3e-07 | Q3: =IF(AND(E3>=10,I3<>""),(1-I3)+ROW()/10000000,"")
A4: 492 | B4: Fresh Thyme #492 | C4: Ballwin | D4: MO | E4: =COUNTIF('02_CLEAN_DATA'!$B$2:$B$570,A4) -> 4 | F4: =COUNTIFS('02_CLEAN_DATA'!$B$2:$B$570,A4,'02_CLEAN_DATA'!$R$2:$R$570,1) -> 1 | G4: =COUNTIFS('02_CLEAN_DATA'!$B$2:$B$570,A4,'02_CLEAN_DATA'!$W$2:$W$570,"Met") -> 1 | H4: =COUNTIFS('02_CLEAN_DATA'!$B$2:$B$570,A4,'02_CLEAN_DATA'!$W$2:$W$570,"Missed") -> 0 | I4: =IF(F4=0,"",G4/F4) -> 1 | J4: =COUNTIFS('02_CLEAN_DATA'!$B$2:$B$570,A4,'02_CLEAN_DATA'!$S$2:$S$570,"Customer Contracted Reasons") -> 2 | K4: =IF(E4=0,"",J4/E4) -> 0.5 | L4: =IFERROR(AVERAGEIF('02_CLEAN_DATA'!$B$2:$B$570,A4,'02_CLEAN_DATA'!$O$2:$O$570),"") -> 4.5075 | M4: {=IFERROR(MEDIAN(IF('02_CLEAN_DATA'!$B$2:$B$570=A4,'02_CLEAN_DATA'!$O$2:$O$570)),"")} -> 4.6 | N4: =IF(E4>=5,L4+ROW()/10000000,"") | O4: =IF(E4>=5,I4+ROW()/10000000,"") | P4: =H4+ROW()/10000000 -> 4e-07 | Q4: =IF(AND(E4>=10,I4<>""),(1-I4)+ROW()/10000000,"")
A5: 493 | B5: Fresh Thyme #493 | C5: O Fallon | D5: MO | E5: =COUNTIF('02_CLEAN_DATA'!$B$2:$B$570,A5) -> 20 | F5: =COUNTIFS('02_CLEAN_DATA'!$B$2:$B$570,A5,'02_CLEAN_DATA'!$R$2:$R$570,1) -> 11 | G5: =COUNTIFS('02_CLEAN_DATA'!$B$2:$B$570,A5,'02_CLEAN_DATA'!$W$2:$W$570,"Met") -> 9 | H5: =COUNTIFS('02_CLEAN_DATA'!$B$2:$B$570,A5,'02_CLEAN_DATA'!$W$2:$W$570,"Missed") -> 2 | I5: =IF(F5=0,"",G5/F5) -> 0.81818182 | J5: =COUNTIFS('02_CLEAN_DATA'!$B$2:$B$570,A5,'02_CLEAN_DATA'!$S$2:$S$570,"Customer Contracted Reasons") -> 13 | K5: =IF(E5=0,"",J5/E5) -> 0.65 | L5: =IFERROR(AVERAGEIF('02_CLEAN_DATA'!$B$2:$B$570,A5,'02_CLEAN_DATA'!$O$2:$O$570),"") -> 15.991 | M5: {=IFERROR(MEDIAN(IF('02_CLEAN_DATA'!$B$2:$B$570=A5,'02_CLEAN_DATA'!$O$2:$O$570)),"")} -> 15.475 | N5: =IF(E5>=5,L5+ROW()/10000000,"") -> 15.991001 | O5: =IF(E5>=5,I5+ROW()/10000000,"") -> 0.81818232 | P5: =H5+ROW()/10000000 -> 2.0000005 | Q5: =IF(AND(E5>=10,I5<>""),(1-I5)+ROW()/10000000,"") -> 0.18181868
A6: 494 | B6: Fresh Thyme #494 | C6: Saint Louis | D6: MO | E6: =COUNTIF('02_CLEAN_DATA'!$B$2:$B$570,A6) -> 13 | F6: =COUNTIFS('02_CLEAN_DATA'!$B$2:$B$570,A6,'02_CLEAN_DATA'!$R$2:$R$570,1) -> 10 | G6: =COUNTIFS('02_CLEAN_DATA'!$B$2:$B$570,A6,'02_CLEAN_DATA'!$W$2:$W$570,"Met") -> 10 | H6: =COUNTIFS('02_CLEAN_DATA'!$B$2:$B$570,A6,'02_CLEAN_DATA'!$W$2:$W$570,"Missed") -> 0 | I6: =IF(F6=0,"",G6/F6) -> 1 | J6: =COUNTIFS('02_CLEAN_DATA'!$B$2:$B$570,A6,'02_CLEAN_DATA'!$S$2:$S$570,"Customer Contracted Reasons") -> 6 | K6: =IF(E6=0,"",J6/E6) -> 0.46153846 | L6: =IFERROR(AVERAGEIF('02_CLEAN_DATA'!$B$2:$B$570,A6,'02_CLEAN_DATA'!$O$2:$O$570),"") -> 15.615385 | M6: {=IFERROR(MEDIAN(IF('02_CLEAN_DATA'!$B$2:$B$570=A6,'02_CLEAN_DATA'!$O$2:$O$570)),"")} -> 7.68 | N6: =IF(E6>=5,L6+ROW()/10000000,"") -> 15.615385 | O6: =IF(E6>=5,I6+ROW()/10000000,"") -> 1.0000006 | P6: =H6+ROW()/10000000 -> 6e-07 | Q6: =IF(AND(E6>=10,I6<>""),(1-I6)+ROW()/10000000,"") -> 6e-07
A7: 495 | B7: Fresh Thyme #495 | C7: Saint Peters | D7: MO | E7: =COUNTIF('02_CLEAN_DATA'!$B$2:$B$570,A7) -> 11 | F7: =COUNTIFS('02_CLEAN_DATA'!$B$2:$B$570,A7,'02_CLEAN_DATA'!$R$2:$R$570,1) -> 7 | G7: =COUNTIFS('02_CLEAN_DATA'!$B$2:$B$570,A7,'02_CLEAN_DATA'!$W$2:$W$570,"Met") -> 6 | H7: =COUNTIFS('02_CLEAN_DATA'!$B$2:$B$570,A7,'02_CLEAN_DATA'!$W$2:$W$570,"Missed") -> 1 | I7: =IF(F7=0,"",G7/F7) -> 0.85714286 | J7: =COUNTIFS('02_CLEAN_DATA'!$B$2:$B$570,A7,'02_CLEAN_DATA'!$S$2:$S$570,"Customer Contracted Reasons") -> 5 | K7: =IF(E7=0,"",J7/E7) -> 0.45454545 | L7: =IFERROR(AVERAGEIF('02_CLEAN_DATA'!$B$2:$B$570,A7,'02_CLEAN_DATA'!$O$2:$O$570),"") -> 16.460909 | M7: {=IFERROR(MEDIAN(IF('02_CLEAN_DATA'!$B$2:$B$570=A7,'02_CLEAN_DATA'!$O$2:$O$570)),"")} -> 4.25 | N7: =IF(E7>=5,L7+ROW()/10000000,"") -> 16.46091 | O7: =IF(E7>=5,I7+ROW()/10000000,"") -> 0.85714356 | P7: =H7+ROW()/10000000 -> 1.0000007 | Q7: =IF(AND(E7>=10,I7<>""),(1-I7)+ROW()/10000000,"") -> 0.14285784
A8: 496 | B8: Fresh Thyme #496 | C8: Bridgeville | D8: PA | E8: =COUNTIF('02_CLEAN_DATA'!$B$2:$B$570,A8) -> 6 | F8: =COUNTIFS('02_CLEAN_DATA'!$B$2:$B$570,A8,'02_CLEAN_DATA'!$R$2:$R$570,1) -> 6 | G8: =COUNTIFS('02_CLEAN_DATA'!$B$2:$B$570,A8,'02_CLEAN_DATA'!$W$2:$W$570,"Met") -> 6 | H8: =COUNTIFS('02_CLEAN_DATA'!$B$2:$B$570,A8,'02_CLEAN_DATA'!$W$2:$W$570,"Missed") -> 0 | I8: =IF(F8=0,"",G8/F8) -> 1 | J8: =COUNTIFS('02_CLEAN_DATA'!$B$2:$B$570,A8,'02_CLEAN_DATA'!$S$2:$S$570,"Customer Contracted Reasons") -> 5 | K8: =IF(E8=0,"",J8/E8) -> 0.83333333 | L8: =IFERROR(AVERAGEIF('02_CLEAN_DATA'!$B$2:$B$570,A8,'02_CLEAN_DATA'!$O$2:$O$570),"") -> 15.541667 | M8: {=IFERROR(MEDIAN(IF('02_CLEAN_DATA'!$B$2:$B$570=A8,'02_CLEAN_DATA'!$O$2:$O$570)),"")} -> 13.14 | N8: =IF(E8>=5,L8+ROW()/10000000,"") -> 15.541667 | O8: =IF(E8>=5,I8+ROW()/10000000,"") -> 1.0000008 | P8: =H8+ROW()/10000000 -> 8e-07 | Q8: =IF(AND(E8>=10,I8<>""),(1-I8)+ROW()/10000000,"")
A9: 497 | B9: Fresh Thyme #497 | C9: Pleasant Hills | D9: PA | E9: =COUNTIF('02_CLEAN_DATA'!$B$2:$B$570,A9) -> 9 | F9: =COUNTIFS('02_CLEAN_DATA'!$B$2:$B$570,A9,'02_CLEAN_DATA'!$R$2:$R$570,1) -> 7 | G9: =COUNTIFS('02_CLEAN_DATA'!$B$2:$B$570,A9,'02_CLEAN_DATA'!$W$2:$W$570,"Met") -> 7 | H9: =COUNTIFS('02_CLEAN_DATA'!$B$2:$B$570,A9,'02_CLEAN_DATA'!$W$2:$W$570,"Missed") -> 0 | I9: =IF(F9=0,"",G9/F9) -> 1 | J9: =COUNTIFS('02_CLEAN_DATA'!$B$2:$B$570,A9,'02_CLEAN_DATA'!$S$2:$S$570,"Customer Contracted Reasons") -> 6 | K9: =IF(E9=0,"",J9/E9) -> 0.66666667 | L9: =IFERROR(AVERAGEIF('02_CLEAN_DATA'!$B$2:$B$570,A9,'02_CLEAN_DATA'!$O$2:$O$570),"") -> 20.321111 | M9: {=IFERROR(MEDIAN(IF('02_CLEAN_DATA'!$B$2:$B$570=A9,'02_CLEAN_DATA'!$O$2:$O$570)),"")} -> 14.87 | N9: =IF(E9>=5,L9+ROW()/10000000,"") -> 20.321112 | O9: =IF(E9>=5,I9+ROW()/10000000,"") -> 1.0000009 | P9: =H9+ROW()/10000000 -> 9e-07 | Q9: =IF(AND(E9>=10,I9<>""),(1-I9)+ROW()/10000000,"")
A10: 498 | B10: Fresh Thyme #498 | C10: Cranberry Township | D10: PA | E10: =COUNTIF('02_CLEAN_DATA'!$B$2:$B$570,A10) -> 2 | F10: =COUNTIFS('02_CLEAN_DATA'!$B$2:$B$570,A10,'02_CLEAN_DATA'!$R$2:$R$570,1) -> 2 | G10: =COUNTIFS('02_CLEAN_DATA'!$B$2:$B$570,A10,'02_CLEAN_DATA'!$W$2:$W$570,"Met") -> 1 | H10: =COUNTIFS('02_CLEAN_DATA'!$B$2:$B$570,A10,'02_CLEAN_DATA'!$W$2:$W$570,"Missed") -> 1 | I10: =IF(F10=0,"",G10/F10) -> 0.5 | J10: =COUNTIFS('02_CLEAN_DATA'!$B$2:$B$570,A10,'02_CLEAN_DATA'!$S$2:$S$570,"Customer Contracted Reasons") -> 2 | K10: =IF(E10=0,"",J10/E10) -> 1 | L10: =IFERROR(AVERAGEIF('02_CLEAN_DATA'!$B$2:$B$570,A10,'02_CLEAN_DATA'!$O$2:$O$570),"") -> 26.31 | M10: {=IFERROR(MEDIAN(IF('02_CLEAN_DATA'!$B$2:$B$570=A10,'02_CLEAN_DATA'!$O$2:$O$570)),"")} -> 26.31 | N10: =IF(E10>=5,L10+ROW()/10000000,"") | O10: =IF(E10>=5,I10+ROW()/10000000,"") | P10: =H10+ROW()/10000000 -> 1.000001 | Q10: =IF(AND(E10>=10,I10<>""),(1-I10)+ROW()/10000000,"")
A11: 499 | B11: Fresh Thyme #499 | C11: Newport | D11: KY | E11: =COUNTIF('02_CLEAN_DATA'!$B$2:$B$570,A11) -> 1 | F11: =COUNTIFS('02_CLEAN_DATA'!$B$2:$B$570,A11,'02_CLEAN_DATA'!$R$2:$R$570,1) -> 1 | G11: =COUNTIFS('02_CLEAN_DATA'!$B$2:$B$570,A11,'02_CLEAN_DATA'!$W$2:$W$570,"Met") -> 1 | H11: =COUNTIFS('02_CLEAN_DATA'!$B$2:$B$570,A11,'02_CLEAN_DATA'!$W$2:$W$570,"Missed") -> 0 | I11: =IF(F11=0,"",G11/F11) -> 1 | J11: =COUNTIFS('02_CLEAN_DATA'!$B$2:$B$570,A11,'02_CLEAN_DATA'!$S$2:$S$570,"Customer Contracted Reasons") -> 0 | K11: =IF(E11=0,"",J11/E11) -> 0 | L11: =IFERROR(AVERAGEIF('02_CLEAN_DATA'!$B$2:$B$570,A11,'02_CLEAN_DATA'!$O$2:$O$570),"") -> 10.87 | M11: {=IFERROR(MEDIAN(IF('02_CLEAN_DATA'!$B$2:$B$570=A11,'02_CLEAN_DATA'!$O$2:$O$570)),"")} -> 10.87 | N11: =IF(E11>=5,L11+ROW()/10000000,"") | O11: =IF(E11>=5,I11+ROW()/10000000,"") | P11: =H11+ROW()/10000000 -> 1.1e-06 | Q11: =IF(AND(E11>=10,I11<>""),(1-I11)+ROW()/10000000,"")
A12: 522 | B12: Fresh Thyme #522 | C12: Indianapolis | D12: IN | E12: =COUNTIF('02_CLEAN_DATA'!$B$2:$B$570,A12) -> 13 | F12: =COUNTIFS('02_CLEAN_DATA'!$B$2:$B$570,A12,'02_CLEAN_DATA'!$R$2:$R$570,1) -> 12 | G12: =COUNTIFS('02_CLEAN_DATA'!$B$2:$B$570,A12,'02_CLEAN_DATA'!$W$2:$W$570,"Met") -> 7 | H12: =COUNTIFS('02_CLEAN_DATA'!$B$2:$B$570,A12,'02_CLEAN_DATA'!$W$2:$W$570,"Missed") -> 5 | I12: =IF(F12=0,"",G12/F12) -> 0.58333333 | J12: =COUNTIFS('02_CLEAN_DATA'!$B$2:$B$570,A12,'02_CLEAN_DATA'!$S$2:$S$570,"Customer Contracted Reasons") -> 13 | K12: =IF(E12=0,"",J12/E12) -> 1 | L12: =IFERROR(AVERAGEIF('02_CLEAN_DATA'!$B$2:$B$570,A12,'02_CLEAN_DATA'!$O$2:$O$570),"") -> 72.347692 | M12: {=IFERROR(MEDIAN(IF('02_CLEAN_DATA'!$B$2:$B$570=A12,'02_CLEAN_DATA'!$O$2:$O$570)),"")} -> 32.1 | N12: =IF(E12>=5,L12+ROW()/10000000,"") -> 72.347694 | O12: =IF(E12>=5,I12+ROW()/10000000,"") -> 0.58333453 | P12: =H12+ROW()/10000000 -> 5.0000012 | Q12: =IF(AND(E12>=10,I12<>""),(1-I12)+ROW()/10000000,"") -> 0.41666787
A13: 523 | B13: Fresh Thyme #523 | C13: Lafayette | D13: IN | E13: =COUNTIF('02_CLEAN_DATA'!$B$2:$B$570,A13) -> 7 | F13: =COUNTIFS('02_CLEAN_DATA'!$B$2:$B$570,A13,'02_CLEAN_DATA'!$R$2:$R$570,1) -> 7 | G13: =COUNTIFS('02_CLEAN_DATA'!$B$2:$B$570,A13,'02_CLEAN_DATA'!$W$2:$W$570,"Met") -> 5 | H13: =COUNTIFS('02_CLEAN_DATA'!$B$2:$B$570,A13,'02_CLEAN_DATA'!$W$2:$W$570,"Missed") -> 2 | I13: =IF(F13=0,"",G13/F13) -> 0.71428571 | J13: =COUNTIFS('02_CLEAN_DATA'!$B$2:$B$570,A13,'02_CLEAN_DATA'!$S$2:$S$570,"Customer Contracted Reasons") -> 4 | K13: =IF(E13=0,"",J13/E13) -> 0.57142857 | L13: =IFERROR(AVERAGEIF('02_CLEAN_DATA'!$B$2:$B$570,A13,'02_CLEAN_DATA'!$O$2:$O$570),"") -> 16.311429 | M13: {=IFERROR(MEDIAN(IF('02_CLEAN_DATA'!$B$2:$B$570=A13,'02_CLEAN_DATA'!$O$2:$O$570)),"")} -> 18.6 | N13: =IF(E13>=5,L13+ROW()/10000000,"") -> 16.31143 | O13: =IF(E13>=5,I13+ROW()/10000000,"") -> 0.71428701 | P13: =H13+ROW()/10000000 -> 2.0000013 | Q13: =IF(AND(E13>=10,I13<>""),(1-I13)+ROW()/10000000,"")
... A70: 968 | B70: Fresh Thyme #968 | C70: Davenport | D70: IA | E70: =COUNTIF('02_CLEAN_DATA'!$B$2:$B$570,A70) -> 6 | F70: =COUNTIFS('02_CLEAN_DATA'!$B$2:$B$570,A70,'02_CLEAN_DATA'!$R$2:$R$570,1) -> 4 | G70: =COUNTIFS('02_CLEAN_DATA'!$B$2:$B$570,A70,'02_CLEAN_DATA'!$W$2:$W$570,"Met") -> 4 | H70: =COUNTIFS('02_CLEAN_DATA'!$B$2:$B$570,A70,'02_CLEAN_DATA'!$W$2:$W$570,"Missed") -> 0 | I70: =IF(F70=0,"",G70/F70) -> 1 | J70: =COUNTIFS('02_CLEAN_DATA'!$B$2:$B$570,A70,'02_CLEAN_DATA'!$S$2:$S$570,"Customer Contracted Reasons") -> 4 | K70: =IF(E70=0,"",J70/E70) -> 0.66666667 | L70: =IFERROR(AVERAGEIF('02_CLEAN_DATA'!$B$2:$B$570,A70,'02_CLEAN_DATA'!$O$2:$O$570),"") -> 9.4383333 | M70: {=IFERROR(MEDIAN(IF('02_CLEAN_DATA'!$B$2:$B$570=A70,'02_CLEAN_DATA'!$O$2:$O$570)),"")} -> 4.55 | N70: =IF(E70>=5,L70+ROW()/10000000,"") -> 9.4383403 | O70: =IF(E70>=5,I70+ROW()/10000000,"") -> 1.000007 | P70: =H70+ROW()/10000000 -> 7e-06 | Q70: =IF(AND(E70>=10,I70<>""),(1-I70)+ROW()/10000000,"")
A73: Note: SLA % shown only for stores with SLA-eligible tickets (Opportunity Indicator = 1). Stores with very low ticket volume (<5) should be interpreted with caution — see 00_README. Columns N-Q are internal ranking helper columns used by 08_RESOLUTION_ANALYSIS and 09_ADVANCED_INSIGHTS; hidden from view.

Sheet 07_TECHNICIAN_ANALYSIS
A1: Tech Code | B1: Technician | C1: Total Tickets | D1: SLA Eligible | E1: SLA Met | F1: SLA Missed | G1: SLA % | H1: Exceptions (CCR) | I1: Avg Resolution (Hrs) | J1: Median Resolution (Hrs) | K1: Meets Min Threshold (5+) | L1: Rank Key (Avg Res, 5+ tickets) | M1: Rank Key (Missed Count)
A2: US153R72 | B2: Carlson Paul | C2: =COUNTIF('02_CLEAN_DATA'!$G$2:$G$570,A2) -> 21 | D2: =COUNTIFS('02_CLEAN_DATA'!$G$2:$G$570,A2,'02_CLEAN_DATA'!$R$2:$R$570,1) -> 14 | E2: =COUNTIFS('02_CLEAN_DATA'!$G$2:$G$570,A2,'02_CLEAN_DATA'!$W$2:$W$570,"Met") -> 9 | F2: =COUNTIFS('02_CLEAN_DATA'!$G$2:$G$570,A2,'02_CLEAN_DATA'!$W$2:$W$570,"Missed") -> 5 | G2: =IF(D2=0,"",E2/D2) -> 0.64285714 | H2: =COUNTIFS('02_CLEAN_DATA'!$G$2:$G$570,A2,'02_CLEAN_DATA'!$S$2:$S$570,"Customer Contracted Reasons") -> 8 | I2: =IFERROR(AVERAGEIF('02_CLEAN_DATA'!$G$2:$G$570,A2,'02_CLEAN_DATA'!$O$2:$O$570),"") -> 63.577619 | J2: {=IFERROR(MEDIAN(IF('02_CLEAN_DATA'!$G$2:$G$570=A2,'02_CLEAN_DATA'!$O$2:$O$570)),"")} -> 16.97 | K2: =IF(C2>=5,"Yes","No") -> Yes | L2: =IF(C2>=5,I2+ROW()/10000000,"") -> 63.577619 | M2: =F2+ROW()/10000000 -> 5.0000002
A3: US153C07 | B3: August Ronald | C3: =COUNTIF('02_CLEAN_DATA'!$G$2:$G$570,A3) -> 20 | D3: =COUNTIFS('02_CLEAN_DATA'!$G$2:$G$570,A3,'02_CLEAN_DATA'!$R$2:$R$570,1) -> 20 | E3: =COUNTIFS('02_CLEAN_DATA'!$G$2:$G$570,A3,'02_CLEAN_DATA'!$W$2:$W$570,"Met") -> 10 | F3: =COUNTIFS('02_CLEAN_DATA'!$G$2:$G$570,A3,'02_CLEAN_DATA'!$W$2:$W$570,"Missed") -> 10 | G3: =IF(D3=0,"",E3/D3) -> 0.5 | H3: =COUNTIFS('02_CLEAN_DATA'!$G$2:$G$570,A3,'02_CLEAN_DATA'!$S$2:$S$570,"Customer Contracted Reasons") -> 18 | I3: =IFERROR(AVERAGEIF('02_CLEAN_DATA'!$G$2:$G$570,A3,'02_CLEAN_DATA'!$O$2:$O$570),"") -> 29.4275 | J3: {=IFERROR(MEDIAN(IF('02_CLEAN_DATA'!$G$2:$G$570=A3,'02_CLEAN_DATA'!$O$2:$O$570)),"")} -> 24.55 | K3: =IF(C3>=5,"Yes","No") -> Yes | L3: =IF(C3>=5,I3+ROW()/10000000,"") -> 29.4275 | M3: =F3+ROW()/10000000 -> 10
A4: US153N64 | B4: Patton Alfred | C4: =COUNTIF('02_CLEAN_DATA'!$G$2:$G$570,A4) -> 15 | D4: =COUNTIFS('02_CLEAN_DATA'!$G$2:$G$570,A4,'02_CLEAN_DATA'!$R$2:$R$570,1) -> 8 | E4: =COUNTIFS('02_CLEAN_DATA'!$G$2:$G$570,A4,'02_CLEAN_DATA'!$W$2:$W$570,"Met") -> 6 | F4: =COUNTIFS('02_CLEAN_DATA'!$G$2:$G$570,A4,'02_CLEAN_DATA'!$W$2:$W$570,"Missed") -> 2 | G4: =IF(D4=0,"",E4/D4) -> 0.75 | H4: =COUNTIFS('02_CLEAN_DATA'!$G$2:$G$570,A4,'02_CLEAN_DATA'!$S$2:$S$570,"Customer Contracted Reasons") -> 9 | I4: =IFERROR(AVERAGEIF('02_CLEAN_DATA'!$G$2:$G$570,A4,'02_CLEAN_DATA'!$O$2:$O$570),"") -> 17.403333 | J4: {=IFERROR(MEDIAN(IF('02_CLEAN_DATA'!$G$2:$G$570=A4,'02_CLEAN_DATA'!$O$2:$O$570)),"")} -> 7.8 | K4: =IF(C4>=5,"Yes","No") -> Yes | L4: =IF(C4>=5,I4+ROW()/10000000,"") -> 17.403334 | M4: =F4+ROW()/10000000 -> 2.0000004
A5: US133E77 | B5: Ehret Alexander | C5: =COUNTIF('02_CLEAN_DATA'!$G$2:$G$570,A5) -> 14 | D5: =COUNTIFS('02_CLEAN_DATA'!$G$2:$G$570,A5,'02_CLEAN_DATA'!$R$2:$R$570,1) -> 3 | E5: =COUNTIFS('02_CLEAN_DATA'!$G$2:$G$570,A5,'02_CLEAN_DATA'!$W$2:$W$570,"Met") -> 2 | F5: =COUNTIFS('02_CLEAN_DATA'!$G$2:$G$570,A5,'02_CLEAN_DATA'!$W$2:$W$570,"Missed") -> 1 | G5: =IF(D5=0,"",E5/D5) -> 0.66666667 | H5: =COUNTIFS('02_CLEAN_DATA'!$G$2:$G$570,A5,'02_CLEAN_DATA'!$S$2:$S$570,"Customer Contracted Reasons") -> 8 | I5: =IFERROR(AVERAGEIF('02_CLEAN_DATA'!$G$2:$G$570,A5,'02_CLEAN_DATA'!$O$2:$O$570),"") -> 34.195714 | J5: {=IFERROR(MEDIAN(IF('02_CLEAN_DATA'!$G$2:$G$570=A5,'02_CLEAN_DATA'!$O$2:$O$570)),"")} -> 9.35 | K5: =IF(C5>=5,"Yes","No") -> Yes | L5: =IF(C5>=5,I5+ROW()/10000000,"") -> 34.195715 | M5: =F5+ROW()/10000000 -> 1.0000005
A6: US153N63 | B6: Vaughn Travis | C6: =COUNTIF('02_CLEAN_DATA'!$G$2:$G$570,A6) -> 14 | D6: =COUNTIFS('02_CLEAN_DATA'!$G$2:$G$570,A6,'02_CLEAN_DATA'!$R$2:$R$570,1) -> 8 | E6: =COUNTIFS('02_CLEAN_DATA'!$G$2:$G$570,A6,'02_CLEAN_DATA'!$W$2:$W$570,"Met") -> 7 | F6: =COUNTIFS('02_CLEAN_DATA'!$G$2:$G$570,A6,'02_CLEAN_DATA'!$W$2:$W$570,"Missed") -> 1 | G6: =IF(D6=0,"",E6/D6) -> 0.875 | H6: =COUNTIFS('02_CLEAN_DATA'!$G$2:$G$570,A6,'02_CLEAN_DATA'!$S$2:$S$570,"Customer Contracted Reasons") -> 8 | I6: =IFERROR(AVERAGEIF('02_CLEAN_DATA'!$G$2:$G$570,A6,'02_CLEAN_DATA'!$O$2:$O$570),"") -> 21.886429 | J6: {=IFERROR(MEDIAN(IF('02_CLEAN_DATA'!$G$2:$G$570=A6,'02_CLEAN_DATA'!$O$2:$O$570)),"")} -> 8.29 | K6: =IF(C6>=5,"Yes","No") -> Yes | L6: =IF(C6>=5,I6+ROW()/10000000,"") -> 21.886429 | M6: =F6+ROW()/10000000 -> 1.0000006
A7: US133E79 | B7: Qi Chuan | C7: =COUNTIF('02_CLEAN_DATA'!$G$2:$G$570,A7) -> 12 | D7: =COUNTIFS('02_CLEAN_DATA'!$G$2:$G$570,A7,'02_CLEAN_DATA'!$R$2:$R$570,1) -> 11 | E7: =COUNTIFS('02_CLEAN_DATA'!$G$2:$G$570,A7,'02_CLEAN_DATA'!$W$2:$W$570,"Met") -> 8 | F7: =COUNTIFS('02_CLEAN_DATA'!$G$2:$G$570,A7,'02_CLEAN_DATA'!$W$2:$W$570,"Missed") -> 3 | G7: =IF(D7=0,"",E7/D7) -> 0.72727273 | H7: =COUNTIFS('02_CLEAN_DATA'!$G$2:$G$570,A7,'02_CLEAN_DATA'!$S$2:$S$570,"Customer Contracted Reasons") -> 9 | I7: =IFERROR(AVERAGEIF('02_CLEAN_DATA'!$G$2:$G$570,A7,'02_CLEAN_DATA'!$O$2:$O$570),"") -> 44.696667 | J7: {=IFERROR(MEDIAN(IF('02_CLEAN_DATA'!$G$2:$G$570=A7,'02_CLEAN_DATA'!$O$2:$O$570)),"")} -> 25.915 | K7: =IF(C7>=5,"Yes","No") -> Yes | L7: =IF(C7>=5,I7+ROW()/10000000,"") -> 44.696667 | M7: =F7+ROW()/10000000 -> 3.0000007
A8: US133C72 | B8: McDonald Noah | C8: =COUNTIF('02_CLEAN_DATA'!$G$2:$G$570,A8) -> 11 | D8: =COUNTIFS('02_CLEAN_DATA'!$G$2:$G$570,A8,'02_CLEAN_DATA'!$R$2:$R$570,1) -> 11 | E8: =COUNTIFS('02_CLEAN_DATA'!$G$2:$G$570,A8,'02_CLEAN_DATA'!$W$2:$W$570,"Met") -> 10 | F8: =COUNTIFS('02_CLEAN_DATA'!$G$2:$G$570,A8,'02_CLEAN_DATA'!$W$2:$W$570,"Missed") -> 1 | G8: =IF(D8=0,"",E8/D8) -> 0.90909091 | H8: =COUNTIFS('02_CLEAN_DATA'!$G$2:$G$570,A8,'02_CLEAN_DATA'!$S$2:$S$570,"Customer Contracted Reasons") -> 11 | I8: =IFERROR(AVERAGEIF('02_CLEAN_DATA'!$G$2:$G$570,A8,'02_CLEAN_DATA'!$O$2:$O$570),"") -> 8.1190909 | J8: {=IFERROR(MEDIAN(IF('02_CLEAN_DATA'!$G$2:$G$570=A8,'02_CLEAN_DATA'!$O$2:$O$570)),"")} -> 3.37 | K8: =IF(C8>=5,"Yes","No") -> Yes | L8: =IF(C8>=5,I8+ROW()/10000000,"") -> 8.1190917 | M8: =F8+ROW()/10000000 -> 1.0000008
A9: US133U12 | B9: Rassam Zaid | C9: =COUNTIF('02_CLEAN_DATA'!$G$2:$G$570,A9) -> 11 | D9: =COUNTIFS('02_CLEAN_DATA'!$G$2:$G$570,A9,'02_CLEAN_DATA'!$R$2:$R$570,1) -> 11 | E9: =COUNTIFS('02_CLEAN_DATA'!$G$2:$G$570,A9,'02_CLEAN_DATA'!$W$2:$W$570,"Met") -> 11 | F9: =COUNTIFS('02_CLEAN_DATA'!$G$2:$G$570,A9,'02_CLEAN_DATA'!$W$2:$W$570,"Missed") -> 0 | G9: =IF(D9=0,"",E9/D9) -> 1 | H9: =COUNTIFS('02_CLEAN_DATA'!$G$2:$G$570,A9,'02_CLEAN_DATA'!$S$2:$S$570,"Customer Contracted Reasons") -> 9 | I9: =IFERROR(AVERAGEIF('02_CLEAN_DATA'!$G$2:$G$570,A9,'02_CLEAN_DATA'!$O$2:$O$570),"") -> 14.247273 | J9: {=IFERROR(MEDIAN(IF('02_CLEAN_DATA'!$G$2:$G$570=A9,'02_CLEAN_DATA'!$O$2:$O$570)),"")} -> 14.55 | K9: =IF(C9>=5,"Yes","No") -> Yes | L9: =IF(C9>=5,I9+ROW()/10000000,"") -> 14.247274 | M9: =F9+ROW()/10000000 -> 9e-07
A10: US133A17 | B10: Blain Simon | C10: =COUNTIF('02_CLEAN_DATA'!$G$2:$G$570,A10) -> 10 | D10: =COUNTIFS('02_CLEAN_DATA'!$G$2:$G$570,A10,'02_CLEAN_DATA'!$R$2:$R$570,1) -> 8 | E10: =COUNTIFS('02_CLEAN_DATA'!$G$2:$G$570,A10,'02_CLEAN_DATA'!$W$2:$W$570,"Met") -> 7 | F10: =COUNTIFS('02_CLEAN_DATA'!$G$2:$G$570,A10,'02_CLEAN_DATA'!$W$2:$W$570,"Missed") -> 1 | G10: =IF(D10=0,"",E10/D10) -> 0.875 | H10: =COUNTIFS('02_CLEAN_DATA'!$G$2:$G$570,A10,'02_CLEAN_DATA'!$S$2:$S$570,"Customer Contracted Reasons") -> 9 | I10: =IFERROR(AVERAGEIF('02_CLEAN_DATA'!$G$2:$G$570,A10,'02_CLEAN_DATA'!$O$2:$O$570),"") -> 25.446 | J10: {=IFERROR(MEDIAN(IF('02_CLEAN_DATA'!$G$2:$G$570=A10,'02_CLEAN_DATA'!$O$2:$O$570)),"")} -> 25.075 | K10: =IF(C10>=5,"Yes","No") -> Yes | L10: =IF(C10>=5,I10+ROW()/10000000,"") -> 25.446001 | M10: =F10+ROW()/10000000 -> 1.000001
A11: US153C10 | B11: Droste Michael | C11: =COUNTIF('02_CLEAN_DATA'!$G$2:$G$570,A11) -> 10 | D11: =COUNTIFS('02_CLEAN_DATA'!$G$2:$G$570,A11,'02_CLEAN_DATA'!$R$2:$R$570,1) -> 10 | E11: =COUNTIFS('02_CLEAN_DATA'!$G$2:$G$570,A11,'02_CLEAN_DATA'!$W$2:$W$570,"Met") -> 4 | F11: =COUNTIFS('02_CLEAN_DATA'!$G$2:$G$570,A11,'02_CLEAN_DATA'!$W$2:$W$570,"Missed") -> 6 | G11: =IF(D11=0,"",E11/D11) -> 0.4 | H11: =COUNTIFS('02_CLEAN_DATA'!$G$2:$G$570,A11,'02_CLEAN_DATA'!$S$2:$S$570,"Customer Contracted Reasons") -> 7 | I11: =IFERROR(AVERAGEIF('02_CLEAN_DATA'!$G$2:$G$570,A11,'02_CLEAN_DATA'!$O$2:$O$570),"") -> 44.176 | J11: {=IFERROR(MEDIAN(IF('02_CLEAN_DATA'!$G$2:$G$570=A11,'02_CLEAN_DATA'!$O$2:$O$570)),"")} -> 54.71 | K11: =IF(C11>=5,"Yes","No") -> Yes | L11: =IF(C11>=5,I11+ROW()/10000000,"") -> 44.176001 | M11: =F11+ROW()/10000000 -> 6.0000011
A12: US153N60 | B12: Welton Kira | C12: =COUNTIF('02_CLEAN_DATA'!$G$2:$G$570,A12) -> 10 | D12: =COUNTIFS('02_CLEAN_DATA'!$G$2:$G$570,A12,'02_CLEAN_DATA'!$R$2:$R$570,1) -> 5 | E12: =COUNTIFS('02_CLEAN_DATA'!$G$2:$G$570,A12,'02_CLEAN_DATA'!$W$2:$W$570,"Met") -> 5 | F12: =COUNTIFS('02_CLEAN_DATA'!$G$2:$G$570,A12,'02_CLEAN_DATA'!$W$2:$W$570,"Missed") -> 0 | G12: =IF(D12=0,"",E12/D12) -> 1 | H12: =COUNTIFS('02_CLEAN_DATA'!$G$2:$G$570,A12,'02_CLEAN_DATA'!$S$2:$S$570,"Customer Contracted Reasons") -> 5 | I12: =IFERROR(AVERAGEIF('02_CLEAN_DATA'!$G$2:$G$570,A12,'02_CLEAN_DATA'!$O$2:$O$570),"") -> 14.192 | J12: {=IFERROR(MEDIAN(IF('02_CLEAN_DATA'!$G$2:$G$570=A12,'02_CLEAN_DATA'!$O$2:$O$570)),"")} -> 8.885 | K12: =IF(C12>=5,"Yes","No") -> Yes | L12: =IF(C12>=5,I12+ROW()/10000000,"") -> 14.192001 | M12: =F12+ROW()/10000000 -> 1.2e-06
A13: US133C52 | B13: Bullock Todd | C13: =COUNTIF('02_CLEAN_DATA'!$G$2:$G$570,A13) -> 9 | D13: =COUNTIFS('02_CLEAN_DATA'!$G$2:$G$570,A13,'02_CLEAN_DATA'!$R$2:$R$570,1) -> 7 | E13: =COUNTIFS('02_CLEAN_DATA'!$G$2:$G$570,A13,'02_CLEAN_DATA'!$W$2:$W$570,"Met") -> 7 | F13: =COUNTIFS('02_CLEAN_DATA'!$G$2:$G$570,A13,'02_CLEAN_DATA'!$W$2:$W$570,"Missed") -> 0 | G13: =IF(D13=0,"",E13/D13) -> 1 | H13: =COUNTIFS('02_CLEAN_DATA'!$G$2:$G$570,A13,'02_CLEAN_DATA'!$S$2:$S$570,"Customer Contracted Reasons") -> 3 | I13: =IFERROR(AVERAGEIF('02_CLEAN_DATA'!$G$2:$G$570,A13,'02_CLEAN_DATA'!$O$2:$O$570),"") -> 5.3944444 | J13: {=IFERROR(MEDIAN(IF('02_CLEAN_DATA'!$G$2:$G$570=A13,'02_CLEAN_DATA'!$O$2:$O$570)),"")} -> 3.35 | K13: =IF(C13>=5,"Yes","No") -> Yes | L13: =IF(C13>=5,I13+ROW()/10000000,"") -> 5.3944457 | M13: =F13+ROW()/10000000 -> 1.3e-06
... A152: US153R84 | B152: Ford Ethan | C152: =COUNTIF('02_CLEAN_DATA'!$G$2:$G$570,A152) -> 1 | D152: =COUNTIFS('02_CLEAN_DATA'!$G$2:$G$570,A152,'02_CLEAN_DATA'!$R$2:$R$570,1) -> 1 | E152: =COUNTIFS('02_CLEAN_DATA'!$G$2:$G$570,A152,'02_CLEAN_DATA'!$W$2:$W$570,"Met") -> 1 | F152: =COUNTIFS('02_CLEAN_DATA'!$G$2:$G$570,A152,'02_CLEAN_DATA'!$W$2:$W$570,"Missed") -> 0 | G152: =IF(D152=0,"",E152/D152) -> 1 | H152: =COUNTIFS('02_CLEAN_DATA'!$G$2:$G$570,A152,'02_CLEAN_DATA'!$S$2:$S$570,"Customer Contracted Reasons") -> 1 | I152: =IFERROR(AVERAGEIF('02_CLEAN_DATA'!$G$2:$G$570,A152,'02_CLEAN_DATA'!$O$2:$O$570),"") -> 17.73 | J152: {=IFERROR(MEDIAN(IF('02_CLEAN_DATA'!$G$2:$G$570=A152,'02_CLEAN_DATA'!$O$2:$O$570)),"")} -> 17.73 | K152: =IF(C152>=5,"Yes","No") -> No | L152: =IF(C152>=5,I152+ROW()/10000000,"") | M152: =F152+ROW()/10000000 -> 1.52e-05
A155: Note: Minimum-ticket threshold of 5 SLA-relevant tickets is used to identify technicians with statistically meaningful performance differences (Column K). Technicians below threshold are listed for completeness but excluded from ranked comparisons in the PowerPoint and Advanced Insights tab.

Sheet 08_RESOLUTION_ANALYSIS
A1: Resolution Time Analysis
A3: Overall (All Closed Tickets)
A4: Average Resolution Time (Hrs) | B4: =AVERAGE('02_CLEAN_DATA'!$O$2:$O$570) -> 30.227606
A5: Median Resolution Time (Hrs) | B5: {=MEDIAN('02_CLEAN_DATA'!$O$2:$O$570)} -> 14.04
A6: Minimum (Hrs) | B6: =MIN('02_CLEAN_DATA'!$O$2:$O$570) -> 0.13
A7: 90th Percentile (Hrs) | B7: =PERCENTILE('02_CLEAN_DATA'!$O$2:$O$570,0.9) -> 73.947
A8: Maximum (Hrs) | B8: =MAX('02_CLEAN_DATA'!$O$2:$O$570) -> 672.22
A10: By Severity
A11: Severity | B11: Tickets | C11: SLA Eligible | D11: SLA Met | E11: SLA % | F11: Avg Resolution (Hrs) | G11: Median Resolution (Hrs)
A12: Severity 1 | B12: =COUNTIF('02_CLEAN_DATA'!$H$2:$H$570,1) -> 103 | C12: =COUNTIFS('02_CLEAN_DATA'!$H$2:$H$570,1,'02_CLEAN_DATA'!$R$2:$R$570,1) -> 81 | D12: =COUNTIFS('02_CLEAN_DATA'!$H$2:$H$570,1,'02_CLEAN_DATA'!$W$2:$W$570,"Met") -> 63 | E12: =IF(C12=0,"",D12/C12) -> 0.77777778 | F12: =IFERROR(AVERAGEIF('02_CLEAN_DATA'!$H$2:$H$570,1,'02_CLEAN_DATA'!$O$2:$O$570),"") -> 20.231359 | G12: {=IFERROR(MEDIAN(IF('02_CLEAN_DATA'!$H$2:$H$570=1,'02_CLEAN_DATA'!$O$2:$O$570)),"")} -> 6.58
A13: Severity 2 | B13: =COUNTIF('02_CLEAN_DATA'!$H$2:$H$570,2) -> 466 | C13: =COUNTIFS('02_CLEAN_DATA'!$H$2:$H$570,2,'02_CLEAN_DATA'!$R$2:$R$570,1) -> 354 | D13: =COUNTIFS('02_CLEAN_DATA'!$H$2:$H$570,2,'02_CLEAN_DATA'!$W$2:$W$570,"Met") -> 274 | E13: =IF(C13=0,"",D13/C13) -> 0.7740113 | F13: =IFERROR(AVERAGEIF('02_CLEAN_DATA'!$H$2:$H$570,2,'02_CLEAN_DATA'!$O$2:$O$570),"") -> 32.441828 | G13: {=IFERROR(MEDIAN(IF('02_CLEAN_DATA'!$H$2:$H$570=2,'02_CLEAN_DATA'!$O$2:$O$570)),"")} -> 14.915
A16: By Month
A17: Month | B17: Avg Resolution (Hrs) | C17: Median Resolution (Hrs)
A18: 2025-08 | B18: =IFERROR(AVERAGEIF('02_CLEAN_DATA'!$L$2:$L$570,A18,'02_CLEAN_DATA'!$O$2:$O$570),"") -> 32.271282 | C18: {=IFERROR(MEDIAN(IF('02_CLEAN_DATA'!$L$2:$L$570=A18,'02_CLEAN_DATA'!$O$2:$O$570)),"")} -> 21.25
A19: 2025-09 | B19: =IFERROR(AVERAGEIF('02_CLEAN_DATA'!$L$2:$L$570,A19,'02_CLEAN_DATA'!$O$2:$O$570),"") -> 42.746316 | C19: {=IFERROR(MEDIAN(IF('02_CLEAN_DATA'!$L$2:$L$570=A19,'02_CLEAN_DATA'!$O$2:$O$570)),"")} -> 14.85
A20: 2025-10 | B20: =IFERROR(AVERAGEIF('02_CLEAN_DATA'!$L$2:$L$570,A20,'02_CLEAN_DATA'!$O$2:$O$570),"") -> 41.202321 | C20: {=IFERROR(MEDIAN(IF('02_CLEAN_DATA'!$L$2:$L$570=A20,'02_CLEAN_DATA'!$O$2:$O$570)),"")} -> 20.875
A21: 2025-11 | B21: =IFERROR(AVERAGEIF('02_CLEAN_DATA'!$L$2:$L$570,A21,'02_CLEAN_DATA'!$O$2:$O$570),"") -> 59.275227 | C21: {=IFERROR(MEDIAN(IF('02_CLEAN_DATA'!$L$2:$L$570=A21,'02_CLEAN_DATA'!$O$2:$O$570)),"")} -> 15.5
A22: 2025-12 | B22: =IFERROR(AVERAGEIF('02_CLEAN_DATA'!$L$2:$L$570,A22,'02_CLEAN_DATA'!$O$2:$O$570),"") -> 23.1098 | C22: {=IFERROR(MEDIAN(IF('02_CLEAN_DATA'!$L$2:$L$570=A22,'02_CLEAN_DATA'!$O$2:$O$570)),"")} -> 12.67
A23: 2026-01 | B23: =IFERROR(AVERAGEIF('02_CLEAN_DATA'!$L$2:$L$570,A23,'02_CLEAN_DATA'!$O$2:$O$570),"") -> 22.958246 | C23: {=IFERROR(MEDIAN(IF('02_CLEAN_DATA'!$L$2:$L$570=A23,'02_CLEAN_DATA'!$O$2:$O$570)),"")} -> 4.13
A24: 2026-02 | B24: =IFERROR(AVERAGEIF('02_CLEAN_DATA'!$L$2:$L$570,A24,'02_CLEAN_DATA'!$O$2:$O$570),"") -> 11.812439 | C24: {=IFERROR(MEDIAN(IF('02_CLEAN_DATA'!$L$2:$L$570=A24,'02_CLEAN_DATA'!$O$2:$O$570)),"")} -> 3.48
A25: 2026-03 | B25: =IFERROR(AVERAGEIF('02_CLEAN_DATA'!$L$2:$L$570,A25,'02_CLEAN_DATA'!$O$2:$O$570),"") -> 31.538889 | C25: {=IFERROR(MEDIAN(IF('02_CLEAN_DATA'!$L$2:$L$570=A25,'02_CLEAN_DATA'!$O$2:$O$570)),"")} -> 17.63
A26: 2026-04 | B26: =IFERROR(AVERAGEIF('02_CLEAN_DATA'!$L$2:$L$570,A26,'02_CLEAN_DATA'!$O$2:$O$570),"") -> 15.99125 | C26: {=IFERROR(MEDIAN(IF('02_CLEAN_DATA'!$L$2:$L$570=A26,'02_CLEAN_DATA'!$O$2:$O$570)),"")} -> 6.84
A27: 2026-05 | B27: =IFERROR(AVERAGEIF('02_CLEAN_DATA'!$L$2:$L$570,A27,'02_CLEAN_DATA'!$O$2:$O$570),"") -> 20.961053 | C27: {=IFERROR(MEDIAN(IF('02_CLEAN_DATA'!$L$2:$L$570=A27,'02_CLEAN_DATA'!$O$2:$O$570)),"")} -> 14.525
A28: 2026-06 | B28: =IFERROR(AVERAGEIF('02_CLEAN_DATA'!$L$2:$L$570,A28,'02_CLEAN_DATA'!$O$2:$O$570),"") -> 30.885952 | C28: {=IFERROR(MEDIAN(IF('02_CLEAN_DATA'!$L$2:$L$570=A28,'02_CLEAN_DATA'!$O$2:$O$570)),"")} -> 20.125
A29: 2026-07 | B29: =IFERROR(AVERAGEIF('02_CLEAN_DATA'!$L$2:$L$570,A29,'02_CLEAN_DATA'!$O$2:$O$570),"") -> 30.18186 | C29: {=IFERROR(MEDIAN(IF('02_CLEAN_DATA'!$L$2:$L$570=A29,'02_CLEAN_DATA'!$O$2:$O$570)),"")} -> 16.55
A30: 2026-08 | B30: =IFERROR(AVERAGEIF('02_CLEAN_DATA'!$L$2:$L$570,A30,'02_CLEAN_DATA'!$O$2:$O$570),"") -> 9.990625 | C30: {=IFERROR(MEDIAN(IF('02_CLEAN_DATA'!$L$2:$L$570=A30,'02_CLEAN_DATA'!$O$2:$O$570)),"")} -> 5.61
A34: Slowest Stores (Avg Resolution, min. 5 tickets) | F34: Fastest Stores (Avg Resolution, min. 5 tickets)
A35: Rank | B35: Store | C35: Avg Resolution (Hrs) | D35: SLA % | F35: Rank | G35: Store | H35: Avg Resolution (Hrs) | I35: SLA %
A36: 1 | B36: {=IFERROR(INDEX('06_STORE_ANALYSIS'!$B$2:$B$70,MATCH(LARGE('06_STORE_ANALYSIS'!$N$2:$N$70,1),'06_STORE_ANALYSIS'!$N$2:$N$70,0)),"")} -> Fresh Thyme #545 | C36: {=IFERROR(INDEX('06_STORE_ANALYSIS'!$L$2:$L$70,MATCH(LARGE('06_STORE_ANALYSIS'!$N$2:$N$70,1),'06_STORE_ANALYSIS'!$N$2:$N$70,0)),"")} -> 104.00714 | D36: {=IFERROR(INDEX('06_STORE_ANALYSIS'!$I$2:$I$70,MATCH(LARGE('06_STORE_ANALYSIS'!$N$2:$N$70,1),'06_STORE_ANALYSIS'!$N$2:$N$70,0)),"")} -> 0.8 | F36: 1 | G36: {=IFERROR(INDEX('06_STORE_ANALYSIS'!$B$2:$B$70,MATCH(SMALL('06_STORE_ANALYSIS'!$N$2:$N$70,1),'06_STORE_ANALYSIS'!$N$2:$N$70,0)),"")} -> Fresh Thyme #639 | H36: {=IFERROR(INDEX('06_STORE_ANALYSIS'!$L$2:$L$70,MATCH(SMALL('06_STORE_ANALYSIS'!$N$2:$N$70,1),'06_STORE_ANALYSIS'!$N$2:$N$70,0)),"")} -> 4.5523077 | I36: {=IFERROR(INDEX('06_STORE_ANALYSIS'!$I$2:$I$70,MATCH(SMALL('06_STORE_ANALYSIS'!$N$2:$N$70,1),'06_STORE_ANALYSIS'!$N$2:$N$70,0)),"")} -> 1
A37: 2 | B37: {=IFERROR(INDEX('06_STORE_ANALYSIS'!$B$2:$B$70,MATCH(LARGE('06_STORE_ANALYSIS'!$N$2:$N$70,2),'06_STORE_ANALYSIS'!$N$2:$N$70,0)),"")} -> Fresh Thyme #647 | C37: {=IFERROR(INDEX('06_STORE_ANALYSIS'!$L$2:$L$70,MATCH(LARGE('06_STORE_ANALYSIS'!$N$2:$N$70,2),'06_STORE_ANALYSIS'!$N$2:$N$70,0)),"")} -> 85.784375 | D37: {=IFERROR(INDEX('06_STORE_ANALYSIS'!$I$2:$I$70,MATCH(LARGE('06_STORE_ANALYSIS'!$N$2:$N$70,2),'06_STORE_ANALYSIS'!$N$2:$N$70,0)),"")} -> 0.28571429 | F37: 2 | G37: {=IFERROR(INDEX('06_STORE_ANALYSIS'!$B$2:$B$70,MATCH(SMALL('06_STORE_ANALYSIS'!$N$2:$N$70,2),'06_STORE_ANALYSIS'!$N$2:$N$70,0)),"")} -> Fresh Thyme #921 | H37: {=IFERROR(INDEX('06_STORE_ANALYSIS'!$L$2:$L$70,MATCH(SMALL('06_STORE_ANALYSIS'!$N$2:$N$70,2),'06_STORE_ANALYSIS'!$N$2:$N$70,0)),"")} -> 6.8442857 | I37: {=IFERROR(INDEX('06_STORE_ANALYSIS'!$I$2:$I$70,MATCH(SMALL('06_STORE_ANALYSIS'!$N$2:$N$70,2),'06_STORE_ANALYSIS'!$N$2:$N$70,0)),"")} -> 1
A38: 3 | B38: {=IFERROR(INDEX('06_STORE_ANALYSIS'!$B$2:$B$70,MATCH(LARGE('06_STORE_ANALYSIS'!$N$2:$N$70,3),'06_STORE_ANALYSIS'!$N$2:$N$70,0)),"")} -> Fresh Thyme #522 | C38: {=IFERROR(INDEX('06_STORE_ANALYSIS'!$L$2:$L$70,MATCH(LARGE('06_STORE_ANALYSIS'!$N$2:$N$70,3),'06_STORE_ANALYSIS'!$N$2:$N$70,0)),"")} -> 72.347692 | D38: {=IFERROR(INDEX('06_STORE_ANALYSIS'!$I$2:$I$70,MATCH(LARGE('06_STORE_ANALYSIS'!$N$2:$N$70,3),'06_STORE_ANALYSIS'!$N$2:$N$70,0)),"")} -> 0.58333333 | F38: 3 | G38: {=IFERROR(INDEX('06_STORE_ANALYSIS'!$B$2:$B$70,MATCH(SMALL('06_STORE_ANALYSIS'!$N$2:$N$70,3),'06_STORE_ANALYSIS'!$N$2:$N$70,0)),"")} -> Fresh Thyme #524 | H38: {=IFERROR(INDEX('06_STORE_ANALYSIS'!$L$2:$L$70,MATCH(SMALL('06_STORE_ANALYSIS'!$N$2:$N$70,3),'06_STORE_ANALYSIS'!$N$2:$N$70,0)),"")} -> 8.0388889 | I38: {=IFERROR(INDEX('06_STORE_ANALYSIS'!$I$2:$I$70,MATCH(SMALL('06_STORE_ANALYSIS'!$N$2:$N$70,3),'06_STORE_ANALYSIS'!$N$2:$N$70,0)),"")} -> 0.875
A39: 4 | B39: {=IFERROR(INDEX('06_STORE_ANALYSIS'!$B$2:$B$70,MATCH(LARGE('06_STORE_ANALYSIS'!$N$2:$N$70,4),'06_STORE_ANALYSIS'!$N$2:$N$70,0)),"")} -> Fresh Thyme #542 | C39: {=IFERROR(INDEX('06_STORE_ANALYSIS'!$L$2:$L$70,MATCH(LARGE('06_STORE_ANALYSIS'!$N$2:$N$70,4),'06_STORE_ANALYSIS'!$N$2:$N$70,0)),"")} -> 70.924 | D39: {=IFERROR(INDEX('06_STORE_ANALYSIS'!$I$2:$I$70,MATCH(LARGE('06_STORE_ANALYSIS'!$N$2:$N$70,4),'06_STORE_ANALYSIS'!$N$2:$N$70,0)),"")} -> 0.8 | F39: 4 | G39: {=IFERROR(INDEX('06_STORE_ANALYSIS'!$B$2:$B$70,MATCH(SMALL('06_STORE_ANALYSIS'!$N$2:$N$70,4),'06_STORE_ANALYSIS'!$N$2:$N$70,0)),"")} -> Fresh Thyme #645 | H39: {=IFERROR(INDEX('06_STORE_ANALYSIS'!$L$2:$L$70,MATCH(SMALL('06_STORE_ANALYSIS'!$N$2:$N$70,4),'06_STORE_ANALYSIS'!$N$2:$N$70,0)),"")} -> 8.4428571 | I39: {=IFERROR(INDEX('06_STORE_ANALYSIS'!$I$2:$I$70,MATCH(SMALL('06_STORE_ANALYSIS'!$N$2:$N$70,4),'06_STORE_ANALYSIS'!$N$2:$N$70,0)),"")} -> 1
A40: 5 | B40: {=IFERROR(INDEX('06_STORE_ANALYSIS'!$B$2:$B$70,MATCH(LARGE('06_STORE_ANALYSIS'!$N$2:$N$70,5),'06_STORE_ANALYSIS'!$N$2:$N$70,0)),"")} -> Fresh Thyme #546 | C40: {=IFERROR(INDEX('06_STORE_ANALYSIS'!$L$2:$L$70,MATCH(LARGE('06_STORE_ANALYSIS'!$N$2:$N$70,5),'06_STORE_ANALYSIS'!$N$2:$N$70,0)),"")} -> 65.364 | D40: {=IFERROR(INDEX('06_STORE_ANALYSIS'!$I$2:$I$70,MATCH(LARGE('06_STORE_ANALYSIS'!$N$2:$N$70,5),'06_STORE_ANALYSIS'!$N$2:$N$70,0)),"")} -> 0.72727273 | F40: 5 | G40: {=IFERROR(INDEX('06_STORE_ANALYSIS'!$B$2:$B$70,MATCH(SMALL('06_STORE_ANALYSIS'!$N$2:$N$70,5),'06_STORE_ANALYSIS'!$N$2:$N$70,0)),"")} -> Fresh Thyme #649 | H40: {=IFERROR(INDEX('06_STORE_ANALYSIS'!$L$2:$L$70,MATCH(SMALL('06_STORE_ANALYSIS'!$N$2:$N$70,5),'06_STORE_ANALYSIS'!$N$2:$N$70,0)),"")} -> 8.7842857 | I40: {=IFERROR(INDEX('06_STORE_ANALYSIS'!$I$2:$I$70,MATCH(SMALL('06_STORE_ANALYSIS'!$N$2:$N$70,5),'06_STORE_ANALYSIS'!$N$2:$N$70,0)),"")} -> 1
A41: 6 | B41: {=IFERROR(INDEX('06_STORE_ANALYSIS'!$B$2:$B$70,MATCH(LARGE('06_STORE_ANALYSIS'!$N$2:$N$70,6),'06_STORE_ANALYSIS'!$N$2:$N$70,0)),"")} -> Fresh Thyme #562 | C41: {=IFERROR(INDEX('06_STORE_ANALYSIS'!$L$2:$L$70,MATCH(LARGE('06_STORE_ANALYSIS'!$N$2:$N$70,6),'06_STORE_ANALYSIS'!$N$2:$N$70,0)),"")} -> 63.572 | D41: {=IFERROR(INDEX('06_STORE_ANALYSIS'!$I$2:$I$70,MATCH(LARGE('06_STORE_ANALYSIS'!$N$2:$N$70,6),'06_STORE_ANALYSIS'!$N$2:$N$70,0)),"")} -> 0.72727273 | F41: 6 | G41: {=IFERROR(INDEX('06_STORE_ANALYSIS'!$B$2:$B$70,MATCH(SMALL('06_STORE_ANALYSIS'!$N$2:$N$70,6),'06_STORE_ANALYSIS'!$N$2:$N$70,0)),"")} -> Fresh Thyme #537 | H41: {=IFERROR(INDEX('06_STORE_ANALYSIS'!$L$2:$L$70,MATCH(SMALL('06_STORE_ANALYSIS'!$N$2:$N$70,6),'06_STORE_ANALYSIS'!$N$2:$N$70,0)),"")} -> 9.3744444 | I41: {=IFERROR(INDEX('06_STORE_ANALYSIS'!$I$2:$I$70,MATCH(SMALL('06_STORE_ANALYSIS'!$N$2:$N$70,6),'06_STORE_ANALYSIS'!$N$2:$N$70,0)),"")} -> 1
A42: 7 | B42: {=IFERROR(INDEX('06_STORE_ANALYSIS'!$B$2:$B$70,MATCH(LARGE('06_STORE_ANALYSIS'!$N$2:$N$70,7),'06_STORE_ANALYSIS'!$N$2:$N$70,0)),"")} -> Fresh Thyme #931 | C42: {=IFERROR(INDEX('06_STORE_ANALYSIS'!$L$2:$L$70,MATCH(LARGE('06_STORE_ANALYSIS'!$N$2:$N$70,7),'06_STORE_ANALYSIS'!$N$2:$N$70,0)),"")} -> 63.534118 | D42: {=IFERROR(INDEX('06_STORE_ANALYSIS'!$I$2:$I$70,MATCH(LARGE('06_STORE_ANALYSIS'!$N$2:$N$70,7),'06_STORE_ANALYSIS'!$N$2:$N$70,0)),"")} -> 0.41666667 | F42: 7 | G42: {=IFERROR(INDEX('06_STORE_ANALYSIS'!$B$2:$B$70,MATCH(SMALL('06_STORE_ANALYSIS'!$N$2:$N$70,7),'06_STORE_ANALYSIS'!$N$2:$N$70,0)),"")} -> Fresh Thyme #968 | H42: {=IFERROR(INDEX('06_STORE_ANALYSIS'!$L$2:$L$70,MATCH(SMALL('06_STORE_ANALYSIS'!$N$2:$N$70,7),'06_STORE_ANALYSIS'!$N$2:$N$70,0)),"")} -> 9.4383333 | I42: {=IFERROR(INDEX('06_STORE_ANALYSIS'!$I$2:$I$70,MATCH(SMALL('06_STORE_ANALYSIS'!$N$2:$N$70,7),'06_STORE_ANALYSIS'!$N$2:$N$70,0)),"")} -> 1
A43: 8 | B43: {=IFERROR(INDEX('06_STORE_ANALYSIS'!$B$2:$B$70,MATCH(LARGE('06_STORE_ANALYSIS'!$N$2:$N$70,8),'06_STORE_ANALYSIS'!$N$2:$N$70,0)),"")} -> Fresh Thyme #541 | C43: {=IFERROR(INDEX('06_STORE_ANALYSIS'!$L$2:$L$70,MATCH(LARGE('06_STORE_ANALYSIS'!$N$2:$N$70,8),'06_STORE_ANALYSIS'!$N$2:$N$70,0)),"")} -> 59.23125 | D43: {=IFERROR(INDEX('06_STORE_ANALYSIS'!$I$2:$I$70,MATCH(LARGE('06_STORE_ANALYSIS'!$N$2:$N$70,8),'06_STORE_ANALYSIS'!$N$2:$N$70,0)),"")} -> 0.5 | F43: 8 | G43: {=IFERROR(INDEX('06_STORE_ANALYSIS'!$B$2:$B$70,MATCH(SMALL('06_STORE_ANALYSIS'!$N$2:$N$70,8),'06_STORE_ANALYSIS'!$N$2:$N$70,0)),"")} -> Fresh Thyme #525 | H43: {=IFERROR(INDEX('06_STORE_ANALYSIS'!$L$2:$L$70,MATCH(SMALL('06_STORE_ANALYSIS'!$N$2:$N$70,8),'06_STORE_ANALYSIS'!$N$2:$N$70,0)),"")} -> 9.7522222 | I43: {=IFERROR(INDEX('06_STORE_ANALYSIS'!$I$2:$I$70,MATCH(SMALL('06_STORE_ANALYSIS'!$N$2:$N$70,8),'06_STORE_ANALYSIS'!$N$2:$N$70,0)),"")} -> 1
A44: 9 | B44: {=IFERROR(INDEX('06_STORE_ANALYSIS'!$B$2:$B$70,MATCH(LARGE('06_STORE_ANALYSIS'!$N$2:$N$70,9),'06_STORE_ANALYSIS'!$N$2:$N$70,0)),"")} -> Fresh Thyme #923 | C44: {=IFERROR(INDEX('06_STORE_ANALYSIS'!$L$2:$L$70,MATCH(LARGE('06_STORE_ANALYSIS'!$N$2:$N$70,9),'06_STORE_ANALYSIS'!$N$2:$N$70,0)),"")} -> 57.298571 | D44: {=IFERROR(INDEX('06_STORE_ANALYSIS'!$I$2:$I$70,MATCH(LARGE('06_STORE_ANALYSIS'!$N$2:$N$70,9),'06_STORE_ANALYSIS'!$N$2:$N$70,0)),"")} -> 0.75 | F44: 9 | G44: {=IFERROR(INDEX('06_STORE_ANALYSIS'!$B$2:$B$70,MATCH(SMALL('06_STORE_ANALYSIS'!$N$2:$N$70,9),'06_STORE_ANALYSIS'!$N$2:$N$70,0)),"")} -> Fresh Thyme #528 | H44: {=IFERROR(INDEX('06_STORE_ANALYSIS'!$L$2:$L$70,MATCH(SMALL('06_STORE_ANALYSIS'!$N$2:$N$70,9),'06_STORE_ANALYSIS'!$N$2:$N$70,0)),"")} -> 10.271667 | I44: {=IFERROR(INDEX('06_STORE_ANALYSIS'!$I$2:$I$70,MATCH(SMALL('06_STORE_ANALYSIS'!$N$2:$N$70,9),'06_STORE_ANALYSIS'!$N$2:$N$70,0)),"")} -> 1
A45: 10 | B45: {=IFERROR(INDEX('06_STORE_ANALYSIS'!$B$2:$B$70,MATCH(LARGE('06_STORE_ANALYSIS'!$N$2:$N$70,10),'06_STORE_ANALYSIS'!$N$2:$N$70,0)),"")} -> Fresh Thyme #715 | C45: {=IFERROR(INDEX('06_STORE_ANALYSIS'!$L$2:$L$70,MATCH(LARGE('06_STORE_ANALYSIS'!$N$2:$N$70,10),'06_STORE_ANALYSIS'!$N$2:$N$70,0)),"")} -> 49.603333 | D45: {=IFERROR(INDEX('06_STORE_ANALYSIS'!$I$2:$I$70,MATCH(LARGE('06_STORE_ANALYSIS'!$N$2:$N$70,10),'06_STORE_ANALYSIS'!$N$2:$N$70,0)),"")} -> 0 | F45: 10 | G45: {=IFERROR(INDEX('06_STORE_ANALYSIS'!$B$2:$B$70,MATCH(SMALL('06_STORE_ANALYSIS'!$N$2:$N$70,10),'06_STORE_ANALYSIS'!$N$2:$N$70,0)),"")} -> Fresh Thyme #962 | H45: {=IFERROR(INDEX('06_STORE_ANALYSIS'!$L$2:$L$70,MATCH(SMALL('06_STORE_ANALYSIS'!$N$2:$N$70,10),'06_STORE_ANALYSIS'!$N$2:$N$70,0)),"")} -> 10.347143 | I45: {=IFERROR(INDEX('06_STORE_ANALYSIS'!$I$2:$I$70,MATCH(SMALL('06_STORE_ANALYSIS'!$N$2:$N$70,10),'06_STORE_ANALYSIS'!$N$2:$N$70,0)),"")} -> 0.83333333
A47: Note: 'Resolve Duration (Hours)' in the raw source is mislabeled — it is recorded in minutes (verified: exactly 60x 'Total Time To Resolve Duration (Hours)' for every ticket). This report uses the correctly-scaled hours field throughout. See 00_README.

Sheet 09_ADVANCED_INSIGHTS
A1: Advanced Management Analysis — Operational Hotspots & Priorities
A3: Top 10 Stores Contributing Most SLA Misses | G3: Top 10 Technicians Contributing Most SLA Misses
A4: Rank | B4: Store | C4: Total Tickets | D4: SLA Missed | E4: SLA % | G4: Rank | H4: Technician | I4: Total Tickets | J4: SLA Missed | K4: SLA %
A5: 1 | B5: {=IFERROR(INDEX('06_STORE_ANALYSIS'!$B$2:$B$70,MATCH(LARGE('06_STORE_ANALYSIS'!$P$2:$P$70,1),'06_STORE_ANALYSIS'!$P$2:$P$70,0)),"")} -> Fresh Thyme #647 | C5: {=IFERROR(INDEX('06_STORE_ANALYSIS'!$E$2:$E$70,MATCH(LARGE('06_STORE_ANALYSIS'!$P$2:$P$70,1),'06_STORE_ANALYSIS'!$P$2:$P$70,0)),"")} -> 16 | D5: {=IFERROR(INDEX('06_STORE_ANALYSIS'!$H$2:$H$70,MATCH(LARGE('06_STORE_ANALYSIS'!$P$2:$P$70,1),'06_STORE_ANALYSIS'!$P$2:$P$70,0)),"")} -> 10 | E5: {=IFERROR(INDEX('06_STORE_ANALYSIS'!$I$2:$I$70,MATCH(LARGE('06_STORE_ANALYSIS'!$P$2:$P$70,1),'06_STORE_ANALYSIS'!$P$2:$P$70,0)),"")} -> 0.28571429 | G5: 1 | H5: {=IFERROR(INDEX('07_TECHNICIAN_ANALYSIS'!$B$2:$B$152,MATCH(LARGE('07_TECHNICIAN_ANALYSIS'!$M$2:$M$152,1),'07_TECHNICIAN_ANALYSIS'!$M$2:$M$152,0)),"")} -> August Ronald | I5: {=IFERROR(INDEX('07_TECHNICIAN_ANALYSIS'!$C$2:$C$152,MATCH(LARGE('07_TECHNICIAN_ANALYSIS'!$M$2:$M$152,1),'07_TECHNICIAN_ANALYSIS'!$M$2:$M$152,0)),"")} -> 20 | J5: {=IFERROR(INDEX('07_TECHNICIAN_ANALYSIS'!$F$2:$F$152,MATCH(LARGE('07_TECHNICIAN_ANALYSIS'!$M$2:$M$152,1),'07_TECHNICIAN_ANALYSIS'!$M$2:$M$152,0)),"")} -> 10 | K5: {=IFERROR(INDEX('07_TECHNICIAN_ANALYSIS'!$G$2:$G$152,MATCH(LARGE('07_TECHNICIAN_ANALYSIS'!$M$2:$M$152,1),'07_TECHNICIAN_ANALYSIS'!$M$2:$M$152,0)),"")} -> 0.5
A6: 2 | B6: {=IFERROR(INDEX('06_STORE_ANALYSIS'!$B$2:$B$70,MATCH(LARGE('06_STORE_ANALYSIS'!$P$2:$P$70,2),'06_STORE_ANALYSIS'!$P$2:$P$70,0)),"")} -> Fresh Thyme #931 | C6: {=IFERROR(INDEX('06_STORE_ANALYSIS'!$E$2:$E$70,MATCH(LARGE('06_STORE_ANALYSIS'!$P$2:$P$70,2),'06_STORE_ANALYSIS'!$P$2:$P$70,0)),"")} -> 17 | D6: {=IFERROR(INDEX('06_STORE_ANALYSIS'!$H$2:$H$70,MATCH(LARGE('06_STORE_ANALYSIS'!$P$2:$P$70,2),'06_STORE_ANALYSIS'!$P$2:$P$70,0)),"")} -> 7 | E6: {=IFERROR(INDEX('06_STORE_ANALYSIS'!$I$2:$I$70,MATCH(LARGE('06_STORE_ANALYSIS'!$P$2:$P$70,2),'06_STORE_ANALYSIS'!$P$2:$P$70,0)),"")} -> 0.41666667 | G6: 2 | H6: {=IFERROR(INDEX('07_TECHNICIAN_ANALYSIS'!$B$2:$B$152,MATCH(LARGE('07_TECHNICIAN_ANALYSIS'!$M$2:$M$152,2),'07_TECHNICIAN_ANALYSIS'!$M$2:$M$152,0)),"")} -> Droste Michael | I6: {=IFERROR(INDEX('07_TECHNICIAN_ANALYSIS'!$C$2:$C$152,MATCH(LARGE('07_TECHNICIAN_ANALYSIS'!$M$2:$M$152,2),'07_TECHNICIAN_ANALYSIS'!$M$2:$M$152,0)),"")} -> 10 | J6: {=IFERROR(INDEX('07_TECHNICIAN_ANALYSIS'!$F$2:$F$152,MATCH(LARGE('07_TECHNICIAN_ANALYSIS'!$M$2:$M$152,2),'07_TECHNICIAN_ANALYSIS'!$M$2:$M$152,0)),"")} -> 6 | K6: {=IFERROR(INDEX('07_TECHNICIAN_ANALYSIS'!$G$2:$G$152,MATCH(LARGE('07_TECHNICIAN_ANALYSIS'!$M$2:$M$152,2),'07_TECHNICIAN_ANALYSIS'!$M$2:$M$152,0)),"")} -> 0.4
A7: 3 | B7: {=IFERROR(INDEX('06_STORE_ANALYSIS'!$B$2:$B$70,MATCH(LARGE('06_STORE_ANALYSIS'!$P$2:$P$70,3),'06_STORE_ANALYSIS'!$P$2:$P$70,0)),"")} -> Fresh Thyme #715 | C7: {=IFERROR(INDEX('06_STORE_ANALYSIS'!$E$2:$E$70,MATCH(LARGE('06_STORE_ANALYSIS'!$P$2:$P$70,3),'06_STORE_ANALYSIS'!$P$2:$P$70,0)),"")} -> 6 | D7: {=IFERROR(INDEX('06_STORE_ANALYSIS'!$H$2:$H$70,MATCH(LARGE('06_STORE_ANALYSIS'!$P$2:$P$70,3),'06_STORE_ANALYSIS'!$P$2:$P$70,0)),"")} -> 6 | E7: {=IFERROR(INDEX('06_STORE_ANALYSIS'!$I$2:$I$70,MATCH(LARGE('06_STORE_ANALYSIS'!$P$2:$P$70,3),'06_STORE_ANALYSIS'!$P$2:$P$70,0)),"")} -> 0 | G7: 3 | H7: {=IFERROR(INDEX('07_TECHNICIAN_ANALYSIS'!$B$2:$B$152,MATCH(LARGE('07_TECHNICIAN_ANALYSIS'!$M$2:$M$152,3),'07_TECHNICIAN_ANALYSIS'!$M$2:$M$152,0)),"")} -> Carlson Paul | I7: {=IFERROR(INDEX('07_TECHNICIAN_ANALYSIS'!$C$2:$C$152,MATCH(LARGE('07_TECHNICIAN_ANALYSIS'!$M$2:$M$152,3),'07_TECHNICIAN_ANALYSIS'!$M$2:$M$152,0)),"")} -> 21 | J7: {=IFERROR(INDEX('07_TECHNICIAN_ANALYSIS'!$F$2:$F$152,MATCH(LARGE('07_TECHNICIAN_ANALYSIS'!$M$2:$M$152,3),'07_TECHNICIAN_ANALYSIS'!$M$2:$M$152,0)),"")} -> 5 | K7: {=IFERROR(INDEX('07_TECHNICIAN_ANALYSIS'!$G$2:$G$152,MATCH(LARGE('07_TECHNICIAN_ANALYSIS'!$M$2:$M$152,3),'07_TECHNICIAN_ANALYSIS'!$M$2:$M$152,0)),"")} -> 0.64285714
A8: 4 | B8: {=IFERROR(INDEX('06_STORE_ANALYSIS'!$B$2:$B$70,MATCH(LARGE('06_STORE_ANALYSIS'!$P$2:$P$70,4),'06_STORE_ANALYSIS'!$P$2:$P$70,0)),"")} -> Fresh Thyme #637 | C8: {=IFERROR(INDEX('06_STORE_ANALYSIS'!$E$2:$E$70,MATCH(LARGE('06_STORE_ANALYSIS'!$P$2:$P$70,4),'06_STORE_ANALYSIS'!$P$2:$P$70,0)),"")} -> 11 | D8: {=IFERROR(INDEX('06_STORE_ANALYSIS'!$H$2:$H$70,MATCH(LARGE('06_STORE_ANALYSIS'!$P$2:$P$70,4),'06_STORE_ANALYSIS'!$P$2:$P$70,0)),"")} -> 6 | E8: {=IFERROR(INDEX('06_STORE_ANALYSIS'!$I$2:$I$70,MATCH(LARGE('06_STORE_ANALYSIS'!$P$2:$P$70,4),'06_STORE_ANALYSIS'!$P$2:$P$70,0)),"")} -> 0.45454545 | G8: 4 | H8: {=IFERROR(INDEX('07_TECHNICIAN_ANALYSIS'!$B$2:$B$152,MATCH(LARGE('07_TECHNICIAN_ANALYSIS'!$M$2:$M$152,4),'07_TECHNICIAN_ANALYSIS'!$M$2:$M$152,0)),"")} -> Ogunnowo Olufemi | I8: {=IFERROR(INDEX('07_TECHNICIAN_ANALYSIS'!$C$2:$C$152,MATCH(LARGE('07_TECHNICIAN_ANALYSIS'!$M$2:$M$152,4),'07_TECHNICIAN_ANALYSIS'!$M$2:$M$152,0)),"")} -> 7 | J8: {=IFERROR(INDEX('07_TECHNICIAN_ANALYSIS'!$F$2:$F$152,MATCH(LARGE('07_TECHNICIAN_ANALYSIS'!$M$2:$M$152,4),'07_TECHNICIAN_ANALYSIS'!$M$2:$M$152,0)),"")} -> 4 | K8: {=IFERROR(INDEX('07_TECHNICIAN_ANALYSIS'!$G$2:$G$152,MATCH(LARGE('07_TECHNICIAN_ANALYSIS'!$M$2:$M$152,4),'07_TECHNICIAN_ANALYSIS'!$M$2:$M$152,0)),"")} -> 0.42857143
A9: 5 | B9: {=IFERROR(INDEX('06_STORE_ANALYSIS'!$B$2:$B$70,MATCH(LARGE('06_STORE_ANALYSIS'!$P$2:$P$70,5),'06_STORE_ANALYSIS'!$P$2:$P$70,0)),"")} -> Fresh Thyme #544 | C9: {=IFERROR(INDEX('06_STORE_ANALYSIS'!$E$2:$E$70,MATCH(LARGE('06_STORE_ANALYSIS'!$P$2:$P$70,5),'06_STORE_ANALYSIS'!$P$2:$P$70,0)),"")} -> 16 | D9: {=IFERROR(INDEX('06_STORE_ANALYSIS'!$H$2:$H$70,MATCH(LARGE('06_STORE_ANALYSIS'!$P$2:$P$70,5),'06_STORE_ANALYSIS'!$P$2:$P$70,0)),"")} -> 6 | E9: {=IFERROR(INDEX('06_STORE_ANALYSIS'!$I$2:$I$70,MATCH(LARGE('06_STORE_ANALYSIS'!$P$2:$P$70,5),'06_STORE_ANALYSIS'!$P$2:$P$70,0)),"")} -> 0.57142857 | G9: 5 | H9: {=IFERROR(INDEX('07_TECHNICIAN_ANALYSIS'!$B$2:$B$152,MATCH(LARGE('07_TECHNICIAN_ANALYSIS'!$M$2:$M$152,5),'07_TECHNICIAN_ANALYSIS'!$M$2:$M$152,0)),"")} -> Downing Keviyon | I9: {=IFERROR(INDEX('07_TECHNICIAN_ANALYSIS'!$C$2:$C$152,MATCH(LARGE('07_TECHNICIAN_ANALYSIS'!$M$2:$M$152,5),'07_TECHNICIAN_ANALYSIS'!$M$2:$M$152,0)),"")} -> 3 | J9: {=IFERROR(INDEX('07_TECHNICIAN_ANALYSIS'!$F$2:$F$152,MATCH(LARGE('07_TECHNICIAN_ANALYSIS'!$M$2:$M$152,5),'07_TECHNICIAN_ANALYSIS'!$M$2:$M$152,0)),"")} -> 3 | K9: {=IFERROR(INDEX('07_TECHNICIAN_ANALYSIS'!$G$2:$G$152,MATCH(LARGE('07_TECHNICIAN_ANALYSIS'!$M$2:$M$152,5),'07_TECHNICIAN_ANALYSIS'!$M$2:$M$152,0)),"")} -> 0
A10: 6 | B10: {=IFERROR(INDEX('06_STORE_ANALYSIS'!$B$2:$B$70,MATCH(LARGE('06_STORE_ANALYSIS'!$P$2:$P$70,6),'06_STORE_ANALYSIS'!$P$2:$P$70,0)),"")} -> Fresh Thyme #522 | C10: {=IFERROR(INDEX('06_STORE_ANALYSIS'!$E$2:$E$70,MATCH(LARGE('06_STORE_ANALYSIS'!$P$2:$P$70,6),'06_STORE_ANALYSIS'!$P$2:$P$70,0)),"")} -> 13 | D10: {=IFERROR(INDEX('06_STORE_ANALYSIS'!$H$2:$H$70,MATCH(LARGE('06_STORE_ANALYSIS'!$P$2:$P$70,6),'06_STORE_ANALYSIS'!$P$2:$P$70,0)),"")} -> 5 | E10: {=IFERROR(INDEX('06_STORE_ANALYSIS'!$I$2:$I$70,MATCH(LARGE('06_STORE_ANALYSIS'!$P$2:$P$70,6),'06_STORE_ANALYSIS'!$P$2:$P$70,0)),"")} -> 0.58333333 | G10: 6 | H10: {=IFERROR(INDEX('07_TECHNICIAN_ANALYSIS'!$B$2:$B$152,MATCH(LARGE('07_TECHNICIAN_ANALYSIS'!$M$2:$M$152,6),'07_TECHNICIAN_ANALYSIS'!$M$2:$M$152,0)),"")} -> Daugherty Nicholas | I10: {=IFERROR(INDEX('07_TECHNICIAN_ANALYSIS'!$C$2:$C$152,MATCH(LARGE('07_TECHNICIAN_ANALYSIS'!$M$2:$M$152,6),'07_TECHNICIAN_ANALYSIS'!$M$2:$M$152,0)),"")} -> 4 | J10: {=IFERROR(INDEX('07_TECHNICIAN_ANALYSIS'!$F$2:$F$152,MATCH(LARGE('07_TECHNICIAN_ANALYSIS'!$M$2:$M$152,6),'07_TECHNICIAN_ANALYSIS'!$M$2:$M$152,0)),"")} -> 3 | K10: {=IFERROR(INDEX('07_TECHNICIAN_ANALYSIS'!$G$2:$G$152,MATCH(LARGE('07_TECHNICIAN_ANALYSIS'!$M$2:$M$152,6),'07_TECHNICIAN_ANALYSIS'!$M$2:$M$152,0)),"")} -> 0.25
A11: 7 | B11: {=IFERROR(INDEX('06_STORE_ANALYSIS'!$B$2:$B$70,MATCH(LARGE('06_STORE_ANALYSIS'!$P$2:$P$70,7),'06_STORE_ANALYSIS'!$P$2:$P$70,0)),"")} -> Fresh Thyme #638 | C11: {=IFERROR(INDEX('06_STORE_ANALYSIS'!$E$2:$E$70,MATCH(LARGE('06_STORE_ANALYSIS'!$P$2:$P$70,7),'06_STORE_ANALYSIS'!$P$2:$P$70,0)),"")} -> 10 | D11: {=IFERROR(INDEX('06_STORE_ANALYSIS'!$H$2:$H$70,MATCH(LARGE('06_STORE_ANALYSIS'!$P$2:$P$70,7),'06_STORE_ANALYSIS'!$P$2:$P$70,0)),"")} -> 4 | E11: {=IFERROR(INDEX('06_STORE_ANALYSIS'!$I$2:$I$70,MATCH(LARGE('06_STORE_ANALYSIS'!$P$2:$P$70,7),'06_STORE_ANALYSIS'!$P$2:$P$70,0)),"")} -> 0.5 | G11: 7 | H11: {=IFERROR(INDEX('07_TECHNICIAN_ANALYSIS'!$B$2:$B$152,MATCH(LARGE('07_TECHNICIAN_ANALYSIS'!$M$2:$M$152,7),'07_TECHNICIAN_ANALYSIS'!$M$2:$M$152,0)),"")} -> Willea Brandon | I11: {=IFERROR(INDEX('07_TECHNICIAN_ANALYSIS'!$C$2:$C$152,MATCH(LARGE('07_TECHNICIAN_ANALYSIS'!$M$2:$M$152,7),'07_TECHNICIAN_ANALYSIS'!$M$2:$M$152,0)),"")} -> 7 | J11: {=IFERROR(INDEX('07_TECHNICIAN_ANALYSIS'!$F$2:$F$152,MATCH(LARGE('07_TECHNICIAN_ANALYSIS'!$M$2:$M$152,7),'07_TECHNICIAN_ANALYSIS'!$M$2:$M$152,0)),"")} -> 3 | K11: {=IFERROR(INDEX('07_TECHNICIAN_ANALYSIS'!$G$2:$G$152,MATCH(LARGE('07_TECHNICIAN_ANALYSIS'!$M$2:$M$152,7),'07_TECHNICIAN_ANALYSIS'!$M$2:$M$152,0)),"")} -> 0.4
A12: 8 | B12: {=IFERROR(INDEX('06_STORE_ANALYSIS'!$B$2:$B$70,MATCH(LARGE('06_STORE_ANALYSIS'!$P$2:$P$70,8),'06_STORE_ANALYSIS'!$P$2:$P$70,0)),"")} -> Fresh Thyme #634 | C12: {=IFERROR(INDEX('06_STORE_ANALYSIS'!$E$2:$E$70,MATCH(LARGE('06_STORE_ANALYSIS'!$P$2:$P$70,8),'06_STORE_ANALYSIS'!$P$2:$P$70,0)),"")} -> 15 | D12: {=IFERROR(INDEX('06_STORE_ANALYSIS'!$H$2:$H$70,MATCH(LARGE('06_STORE_ANALYSIS'!$P$2:$P$70,8),'06_STORE_ANALYSIS'!$P$2:$P$70,0)),"")} -> 3 | E12: {=IFERROR(INDEX('06_STORE_ANALYSIS'!$I$2:$I$70,MATCH(LARGE('06_STORE_ANALYSIS'!$P$2:$P$70,8),'06_STORE_ANALYSIS'!$P$2:$P$70,0)),"")} -> 0.7 | G12: 8 | H12: {=IFERROR(INDEX('07_TECHNICIAN_ANALYSIS'!$B$2:$B$152,MATCH(LARGE('07_TECHNICIAN_ANALYSIS'!$M$2:$M$152,8),'07_TECHNICIAN_ANALYSIS'!$M$2:$M$152,0)),"")} -> Bush David | I12: {=IFERROR(INDEX('07_TECHNICIAN_ANALYSIS'!$C$2:$C$152,MATCH(LARGE('07_TECHNICIAN_ANALYSIS'!$M$2:$M$152,8),'07_TECHNICIAN_ANALYSIS'!$M$2:$M$152,0)),"")} -> 9 | J12: {=IFERROR(INDEX('07_TECHNICIAN_ANALYSIS'!$F$2:$F$152,MATCH(LARGE('07_TECHNICIAN_ANALYSIS'!$M$2:$M$152,8),'07_TECHNICIAN_ANALYSIS'!$M$2:$M$152,0)),"")} -> 3 | K12: {=IFERROR(INDEX('07_TECHNICIAN_ANALYSIS'!$G$2:$G$152,MATCH(LARGE('07_TECHNICIAN_ANALYSIS'!$M$2:$M$152,8),'07_TECHNICIAN_ANALYSIS'!$M$2:$M$152,0)),"")} -> 0.66666667
A13: 9 | B13: {=IFERROR(INDEX('06_STORE_ANALYSIS'!$B$2:$B$70,MATCH(LARGE('06_STORE_ANALYSIS'!$P$2:$P$70,9),'06_STORE_ANALYSIS'!$P$2:$P$70,0)),"")} -> Fresh Thyme #632 | C13: {=IFERROR(INDEX('06_STORE_ANALYSIS'!$E$2:$E$70,MATCH(LARGE('06_STORE_ANALYSIS'!$P$2:$P$70,9),'06_STORE_ANALYSIS'!$P$2:$P$70,0)),"")} -> 7 | D13: {=IFERROR(INDEX('06_STORE_ANALYSIS'!$H$2:$H$70,MATCH(LARGE('06_STORE_ANALYSIS'!$P$2:$P$70,9),'06_STORE_ANALYSIS'!$P$2:$P$70,0)),"")} -> 3 | E13: {=IFERROR(INDEX('06_STORE_ANALYSIS'!$I$2:$I$70,MATCH(LARGE('06_STORE_ANALYSIS'!$P$2:$P$70,9),'06_STORE_ANALYSIS'!$P$2:$P$70,0)),"")} -> 0.4 | G13: 9 | H13: {=IFERROR(INDEX('07_TECHNICIAN_ANALYSIS'!$B$2:$B$152,MATCH(LARGE('07_TECHNICIAN_ANALYSIS'!$M$2:$M$152,9),'07_TECHNICIAN_ANALYSIS'!$M$2:$M$152,0)),"")} -> McAtee Megan | I13: {=IFERROR(INDEX('07_TECHNICIAN_ANALYSIS'!$C$2:$C$152,MATCH(LARGE('07_TECHNICIAN_ANALYSIS'!$M$2:$M$152,9),'07_TECHNICIAN_ANALYSIS'!$M$2:$M$152,0)),"")} -> 9 | J13: {=IFERROR(INDEX('07_TECHNICIAN_ANALYSIS'!$F$2:$F$152,MATCH(LARGE('07_TECHNICIAN_ANALYSIS'!$M$2:$M$152,9),'07_TECHNICIAN_ANALYSIS'!$M$2:$M$152,0)),"")} -> 3 | K13: {=IFERROR(INDEX('07_TECHNICIAN_ANALYSIS'!$G$2:$G$152,MATCH(LARGE('07_TECHNICIAN_ANALYSIS'!$M$2:$M$152,9),'07_TECHNICIAN_ANALYSIS'!$M$2:$M$152,0)),"")} -> 0.5
A14: 10 | B14: {=IFERROR(INDEX('06_STORE_ANALYSIS'!$B$2:$B$70,MATCH(LARGE('06_STORE_ANALYSIS'!$P$2:$P$70,10),'06_STORE_ANALYSIS'!$P$2:$P$70,0)),"")} -> Fresh Thyme #562 | C14: {=IFERROR(INDEX('06_STORE_ANALYSIS'!$E$2:$E$70,MATCH(LARGE('06_STORE_ANALYSIS'!$P$2:$P$70,10),'06_STORE_ANALYSIS'!$P$2:$P$70,0)),"")} -> 15 | D14: {=IFERROR(INDEX('06_STORE_ANALYSIS'!$H$2:$H$70,MATCH(LARGE('06_STORE_ANALYSIS'!$P$2:$P$70,10),'06_STORE_ANALYSIS'!$P$2:$P$70,0)),"")} -> 3 | E14: {=IFERROR(INDEX('06_STORE_ANALYSIS'!$I$2:$I$70,MATCH(LARGE('06_STORE_ANALYSIS'!$P$2:$P$70,10),'06_STORE_ANALYSIS'!$P$2:$P$70,0)),"")} -> 0.72727273 | G14: 10 | H14: {=IFERROR(INDEX('07_TECHNICIAN_ANALYSIS'!$B$2:$B$152,MATCH(LARGE('07_TECHNICIAN_ANALYSIS'!$M$2:$M$152,10),'07_TECHNICIAN_ANALYSIS'!$M$2:$M$152,0)),"")} -> Qi Chuan | I14: {=IFERROR(INDEX('07_TECHNICIAN_ANALYSIS'!$C$2:$C$152,MATCH(LARGE('07_TECHNICIAN_ANALYSIS'!$M$2:$M$152,10),'07_TECHNICIAN_ANALYSIS'!$M$2:$M$152,0)),"")} -> 12 | J14: {=IFERROR(INDEX('07_TECHNICIAN_ANALYSIS'!$F$2:$F$152,MATCH(LARGE('07_TECHNICIAN_ANALYSIS'!$M$2:$M$152,10),'07_TECHNICIAN_ANALYSIS'!$M$2:$M$152,0)),"")} -> 3 | K14: {=IFERROR(INDEX('07_TECHNICIAN_ANALYSIS'!$G$2:$G$152,MATCH(LARGE('07_TECHNICIAN_ANALYSIS'!$M$2:$M$152,10),'07_TECHNICIAN_ANALYSIS'!$M$2:$M$152,0)),"")} -> 0.72727273
A17: High-Volume Stores Below 80% SLA (10+ tickets, worst first) | G17: Monthly SLA Performance — Extremes
A18: Rank | B18: Store | C18: Total Tickets | D18: SLA % | H18: Month | I18: SLA %
A19: 1 | B19: {=IFERROR(INDEX('06_STORE_ANALYSIS'!$B$2:$B$70,MATCH(LARGE('06_STORE_ANALYSIS'!$Q$2:$Q$70,1),'06_STORE_ANALYSIS'!$Q$2:$Q$70,0)),"")} -> Fresh Thyme #647 | C19: {=IFERROR(INDEX('06_STORE_ANALYSIS'!$E$2:$E$70,MATCH(LARGE('06_STORE_ANALYSIS'!$Q$2:$Q$70,1),'06_STORE_ANALYSIS'!$Q$2:$Q$70,0)),"")} -> 16 | D19: {=IFERROR(INDEX('06_STORE_ANALYSIS'!$I$2:$I$70,MATCH(LARGE('06_STORE_ANALYSIS'!$Q$2:$Q$70,1),'06_STORE_ANALYSIS'!$Q$2:$Q$70,0)),"")} -> 0.28571429 | G19: Strongest | H19: {=INDEX('04_SLA_TREND'!$A$3:$A$15,MATCH(MAX('04_SLA_TREND'!$F$3:$F$15),'04_SLA_TREND'!$F$3:$F$15,0))} -> 2026-02 | I19: =MAX('04_SLA_TREND'!$F$3:$F$15) -> 1
A20: 2 | B20: {=IFERROR(INDEX('06_STORE_ANALYSIS'!$B$2:$B$70,MATCH(LARGE('06_STORE_ANALYSIS'!$Q$2:$Q$70,2),'06_STORE_ANALYSIS'!$Q$2:$Q$70,0)),"")} -> Fresh Thyme #931 | C20: {=IFERROR(INDEX('06_STORE_ANALYSIS'!$E$2:$E$70,MATCH(LARGE('06_STORE_ANALYSIS'!$Q$2:$Q$70,2),'06_STORE_ANALYSIS'!$Q$2:$Q$70,0)),"")} -> 17 | D20: {=IFERROR(INDEX('06_STORE_ANALYSIS'!$I$2:$I$70,MATCH(LARGE('06_STORE_ANALYSIS'!$Q$2:$Q$70,2),'06_STORE_ANALYSIS'!$Q$2:$Q$70,0)),"")} -> 0.41666667 | G20: Weakest | H20: {=INDEX('04_SLA_TREND'!$A$3:$A$15,MATCH(MIN('04_SLA_TREND'!$F$3:$F$15),'04_SLA_TREND'!$F$3:$F$15,0))} -> 2025-11 | I20: =MIN('04_SLA_TREND'!$F$3:$F$15) -> 0.39285714
A21: 3 | B21: {=IFERROR(INDEX('06_STORE_ANALYSIS'!$B$2:$B$70,MATCH(LARGE('06_STORE_ANALYSIS'!$Q$2:$Q$70,3),'06_STORE_ANALYSIS'!$Q$2:$Q$70,0)),"")} -> Fresh Thyme #637 | C21: {=IFERROR(INDEX('06_STORE_ANALYSIS'!$E$2:$E$70,MATCH(LARGE('06_STORE_ANALYSIS'!$Q$2:$Q$70,3),'06_STORE_ANALYSIS'!$Q$2:$Q$70,0)),"")} -> 11 | D21: {=IFERROR(INDEX('06_STORE_ANALYSIS'!$I$2:$I$70,MATCH(LARGE('06_STORE_ANALYSIS'!$Q$2:$Q$70,3),'06_STORE_ANALYSIS'!$Q$2:$Q$70,0)),"")} -> 0.45454545
A22: 4 | B22: {=IFERROR(INDEX('06_STORE_ANALYSIS'!$B$2:$B$70,MATCH(LARGE('06_STORE_ANALYSIS'!$Q$2:$Q$70,4),'06_STORE_ANALYSIS'!$Q$2:$Q$70,0)),"")} -> Fresh Thyme #638 | C22: {=IFERROR(INDEX('06_STORE_ANALYSIS'!$E$2:$E$70,MATCH(LARGE('06_STORE_ANALYSIS'!$Q$2:$Q$70,4),'06_STORE_ANALYSIS'!$Q$2:$Q$70,0)),"")} -> 10 | D22: {=IFERROR(INDEX('06_STORE_ANALYSIS'!$I$2:$I$70,MATCH(LARGE('06_STORE_ANALYSIS'!$Q$2:$Q$70,4),'06_STORE_ANALYSIS'!$Q$2:$Q$70,0)),"")} -> 0.5
A23: 5 | B23: {=IFERROR(INDEX('06_STORE_ANALYSIS'!$B$2:$B$70,MATCH(LARGE('06_STORE_ANALYSIS'!$Q$2:$Q$70,5),'06_STORE_ANALYSIS'!$Q$2:$Q$70,0)),"")} -> Fresh Thyme #544 | C23: {=IFERROR(INDEX('06_STORE_ANALYSIS'!$E$2:$E$70,MATCH(LARGE('06_STORE_ANALYSIS'!$Q$2:$Q$70,5),'06_STORE_ANALYSIS'!$Q$2:$Q$70,0)),"")} -> 16 | D23: {=IFERROR(INDEX('06_STORE_ANALYSIS'!$I$2:$I$70,MATCH(LARGE('06_STORE_ANALYSIS'!$Q$2:$Q$70,5),'06_STORE_ANALYSIS'!$Q$2:$Q$70,0)),"")} -> 0.57142857
A24: 6 | B24: {=IFERROR(INDEX('06_STORE_ANALYSIS'!$B$2:$B$70,MATCH(LARGE('06_STORE_ANALYSIS'!$Q$2:$Q$70,6),'06_STORE_ANALYSIS'!$Q$2:$Q$70,0)),"")} -> Fresh Thyme #522 | C24: {=IFERROR(INDEX('06_STORE_ANALYSIS'!$E$2:$E$70,MATCH(LARGE('06_STORE_ANALYSIS'!$Q$2:$Q$70,6),'06_STORE_ANALYSIS'!$Q$2:$Q$70,0)),"")} -> 13 | D24: {=IFERROR(INDEX('06_STORE_ANALYSIS'!$I$2:$I$70,MATCH(LARGE('06_STORE_ANALYSIS'!$Q$2:$Q$70,6),'06_STORE_ANALYSIS'!$Q$2:$Q$70,0)),"")} -> 0.58333333
A25: 7 | B25: {=IFERROR(INDEX('06_STORE_ANALYSIS'!$B$2:$B$70,MATCH(LARGE('06_STORE_ANALYSIS'!$Q$2:$Q$70,7),'06_STORE_ANALYSIS'!$Q$2:$Q$70,0)),"")} -> Fresh Thyme #634 | C25: {=IFERROR(INDEX('06_STORE_ANALYSIS'!$E$2:$E$70,MATCH(LARGE('06_STORE_ANALYSIS'!$Q$2:$Q$70,7),'06_STORE_ANALYSIS'!$Q$2:$Q$70,0)),"")} -> 15 | D25: {=IFERROR(INDEX('06_STORE_ANALYSIS'!$I$2:$I$70,MATCH(LARGE('06_STORE_ANALYSIS'!$Q$2:$Q$70,7),'06_STORE_ANALYSIS'!$Q$2:$Q$70,0)),"")} -> 0.7
A26: 8 | B26: {=IFERROR(INDEX('06_STORE_ANALYSIS'!$B$2:$B$70,MATCH(LARGE('06_STORE_ANALYSIS'!$Q$2:$Q$70,8),'06_STORE_ANALYSIS'!$Q$2:$Q$70,0)),"")} -> Fresh Thyme #562 | C26: {=IFERROR(INDEX('06_STORE_ANALYSIS'!$E$2:$E$70,MATCH(LARGE('06_STORE_ANALYSIS'!$Q$2:$Q$70,8),'06_STORE_ANALYSIS'!$Q$2:$Q$70,0)),"")} -> 15 | D26: {=IFERROR(INDEX('06_STORE_ANALYSIS'!$I$2:$I$70,MATCH(LARGE('06_STORE_ANALYSIS'!$Q$2:$Q$70,8),'06_STORE_ANALYSIS'!$Q$2:$Q$70,0)),"")} -> 0.72727273
A27: 9 | B27: {=IFERROR(INDEX('06_STORE_ANALYSIS'!$B$2:$B$70,MATCH(LARGE('06_STORE_ANALYSIS'!$Q$2:$Q$70,9),'06_STORE_ANALYSIS'!$Q$2:$Q$70,0)),"")} -> Fresh Thyme #546 | C27: {=IFERROR(INDEX('06_STORE_ANALYSIS'!$E$2:$E$70,MATCH(LARGE('06_STORE_ANALYSIS'!$Q$2:$Q$70,9),'06_STORE_ANALYSIS'!$Q$2:$Q$70,0)),"")} -> 15 | D27: {=IFERROR(INDEX('06_STORE_ANALYSIS'!$I$2:$I$70,MATCH(LARGE('06_STORE_ANALYSIS'!$Q$2:$Q$70,9),'06_STORE_ANALYSIS'!$Q$2:$Q$70,0)),"")} -> 0.72727273
A28: 10 | B28: {=IFERROR(INDEX('06_STORE_ANALYSIS'!$B$2:$B$70,MATCH(LARGE('06_STORE_ANALYSIS'!$Q$2:$Q$70,10),'06_STORE_ANALYSIS'!$Q$2:$Q$70,0)),"")} -> Fresh Thyme #701 | C28: {=IFERROR(INDEX('06_STORE_ANALYSIS'!$E$2:$E$70,MATCH(LARGE('06_STORE_ANALYSIS'!$Q$2:$Q$70,10),'06_STORE_ANALYSIS'!$Q$2:$Q$70,0)),"")} -> 10 | D28: {=IFERROR(INDEX('06_STORE_ANALYSIS'!$I$2:$I$70,MATCH(LARGE('06_STORE_ANALYSIS'!$Q$2:$Q$70,10),'06_STORE_ANALYSIS'!$Q$2:$Q$70,0)),"")} -> 0.77777778
A31: Key Management Findings
A32: 1. YTD Adjusted/Opportunity SLA performance is 77.5% (337 of 435 SLA-eligible tickets met), against a raw gross rate of 78.6% for the same eligible population — the mitigation review process has a small net effect on final Met/Missed outcomes; its larger effect is on which tickets are counted at all (134 of 569 tickets, 23.5%, are excluded from the SLA opportunity population).
A35: 2. Exception usage changed sharply starting January 2026: 'Customer Contracted Reasons' mitigations, tagged on roughly 10-20% of tickets Aug-Dec 2025, appear on effectively 100% of tickets every month from Jan 2026 through Jul 2026. This coincides with fully-processed mitigations (Mitigated Indicator = 2) appearing in the data for the first time in Jan 2026. Recommend a governance review with the service vendor on how mitigations are being applied.
A38: 3. November 2025 (39.3% SLA) and June 2026 (60.0% SLA) are the weakest months YTD; February-April 2026 and August 2026 are the strongest, at or near 100%.
A41: 4. See the ranked lists above for the specific stores and technicians contributing the largest number of SLA misses, and the high-volume stores currently running below an 80% SLA rate — these represent the highest-leverage targets for operational follow-up.
A44: 5. Severity 1 (higher-priority) tickets resolve faster on average (~20 hrs) than Severity 2 tickets (~32 hrs), as expected, with comparable SLA attainment (~78%) across both — see 08_RESOLUTION_ANALYSIS.
A47: 6. Data-quality note: the source 'Resolve Duration (Hours)' field is mislabeled and stored in minutes; this report uses the correctly-scaled duration field throughout. See 00_README for the full methodology and additional data-quality notes.

Sheet 02_CLEAN_DATA
A1: Ticket ID | B1: Store Number | C1: Store Name | D1: City | E1: State | F1: Technician Name | G1: Technician Code | H1: Severity | I1: Request Type | J1: Entered Date | K1: Closed Date | L1: Closed Month | M1: Status | N1: Resolve Limit (Hrs) | O1: Resolution Time (Hrs) | P1: Raw SLA Met | Q1: Raw SLA Met (Net) | R1: SLA Eligible (Opportunity) | S1: Exception Category | T1: Mitigated Indicator | U1: Mitigated SLA Met | V1: Final SLA Met | W1: Final SLA Result | Y1: Analysis layer derived from 01_RAW_DATA. Columns L, V, W are live formulas. 'Final SLA Met' = Mitigated SLA Resolve Met Indicator when populated (mitigation fully processed), else the Net SLA Resolve Met Indicator — evaluated only for tickets flagged SLA Eligible (Opportunity=1). See 00_README for full methodology.
A2: 7526314205 | B2: 962 | C2: Fresh Thyme #962 | D2: West Des Moines | E2: IA | F2: Green Jason | G2: US153R46 | H2: 2 | I2: CHGC | J2: 45920.574 | K2: 45920 | L2: =IF(K2="","",TEXT(K2,"YYYY-MM")) -> 2025-09 | M2: closed | N2: 16 | O2: 5.83 | P2: 0 | Q2: 0 | R2: 0 | S2: No Exception | T2: 0 | V2: =IF(R2=0,"",IF(U2<>"",U2,Q2)) | W2: =IF(R2=0,"Not Eligible",IF(V2=1,"Met","Missed")) -> Not Eligible
A3: 7621502464 | B3: 606 | C3: Fresh Thyme #606 | D3: Grand Rapids | E3: MI | F3: Willea Brandon | G3: US133B47 | H3: 2 | I3: MNT | J3: 46236.917 | K3: 46237 | L3: =IF(K3="","",TEXT(K3,"YYYY-MM")) -> 2026-08 | M3: closed | N3: 16 | O3: 11.42 | P3: 1 | Q3: 1 | R3: 1 | S3: Customer Contracted Reasons | T3: 2 | U3: 1 | V3: =IF(R3=0,"",IF(U3<>"",U3,Q3)) -> 1 | W3: =IF(R3=0,"Not Eligible",IF(V3=1,"Met","Missed")) -> Met
A4: 7534505738 | B4: 643 | C4: Fresh Thyme #643 | D4: Troy | E4: MI | F4: Richie Mark | G4: US133U38 | H4: 2 | I4: CHGC | J4: 46002.495 | K4: 46002 | L4: =IF(K4="","",TEXT(K4,"YYYY-MM")) -> 2025-12 | M4: closed | N4: 16 | O4: 1.83 | P4: 0 | Q4: 0 | R4: 0 | S4: No Exception | T4: 0 | V4: =IF(R4=0,"",IF(U4<>"",U4,Q4)) | W4: =IF(R4=0,"Not Eligible",IF(V4=1,"Met","Missed")) -> Not Eligible
A5: 7521807604 | B5: 647 | C5: Fresh Thyme #647 | D5: Portage | E5: MI | F5: Shell Caleb | G5: US133B52 | H5: 2 | I5: CHGC | J5: 45875.614 | K5: 45875 | L5: =IF(K5="","",TEXT(K5,"YYYY-MM")) -> 2025-08 | M5: closed | N5: 16 | O5: 0.8 | P5: 0 | Q5: 0 | R5: 0 | S5: No Exception | T5: 0 | V5: =IF(R5=0,"",IF(U5<>"",U5,Q5)) | W5: =IF(R5=0,"Not Eligible",IF(V5=1,"Met","Missed")) -> Not Eligible
A6: 7621504463 | B6: 536 | C6: Fresh Thyme #536 | D6: Bloomington | E6: IN | F6: Cannon Thomas | G6: US133E75 | H6: 2 | I6: MNT | J6: 46237.395 | K6: 46238 | L6: =IF(K6="","",TEXT(K6,"YYYY-MM")) -> 2026-08 | M6: closed | N6: 16 | O6: 26.15 | P6: 1 | Q6: 1 | R6: 1 | S6: Customer Contracted Reasons | T6: 2 | U6: 1 | V6: =IF(R6=0,"",IF(U6<>"",U6,Q6)) -> 1 | W6: =IF(R6=0,"Not Eligible",IF(V6=1,"Met","Missed")) -> Met
A7: 7527904317 | B7: 631 | C7: Fresh Thyme #631 | D7: Fairview Heights | E7: IL | F7: Johnson Brock | G7: US153N74 | H7: 1 | I7: MNT | J7: 45936.418 | K7: 45937 | L7: =IF(K7="","",TEXT(K7,"YYYY-MM")) -> 2025-10 | M7: closed | N7: 12 | O7: 26.53 | P7: 0 | Q7: 0 | R7: 1 | S7: No Exception | T7: 0 | V7: =IF(R7=0,"",IF(U7<>"",U7,Q7)) -> 0 | W7: =IF(R7=0,"Not Eligible",IF(V7=1,"Met","Missed")) -> Missed
A8: 7618403340 | B8: 638 | C8: Fresh Thyme #638 | D8: Bloomington | E8: IL | F8: Daugherty Nicholas | G8: US153R54 | H8: 2 | I8: MNT | J8: 46206.671 | K8: 46209 | L8: =IF(K8="","",TEXT(K8,"YYYY-MM")) -> 2026-07 | M8: closed | N8: 16 | O8: 68.05 | P8: 0 | Q8: 0 | R8: 1 | S8: Customer Contracted Reasons | T8: 0 | U8: 0 | V8: =IF(R8=0,"",IF(U8<>"",U8,Q8)) -> 0 | W8: =IF(R8=0,"Not Eligible",IF(V8=1,"Met","Missed")) -> Missed
A9: 7530306800 | B9: 448 | C9: Fresh Thyme #448 | D9: St. Louis | E9: MO | F9: Schnur Blake | G9: US153N79 | H9: 2 | I9: MNT | J9: 45960.548 | K9: 45960 | L9: =IF(K9="","",TEXT(K9,"YYYY-MM")) -> 2025-10 | M9: closed | N9: 16 | O9: 6.83 | P9: 1 | Q9: 1 | R9: 1 | S9: No Exception | T9: 0 | V9: =IF(R9=0,"",IF(U9<>"",U9,Q9)) -> 1 | W9: =IF(R9=0,"Not Eligible",IF(V9=1,"Met","Missed")) -> Met
A10: 7610001329 | B10: 545 | C10: Fresh Thyme #545 | D10: Vadnais Heights | E10: MN | F10: Ogunnowo Olufemi | G10: US153R24 | H10: 2 | I10: MNT | J10: 46122.649 | K10: 46129 | L10: =IF(K10="","",TEXT(K10,"YYYY-MM")) -> 2026-04 | M10: closed | N10: 0 | O10: 166.07 | P10: 1 | Q10: 1 | R10: 1 | S10: Customer Contracted Reasons | T10: 1 | V10: =IF(R10=0,"",IF(U10<>"",U10,Q10)) -> 1 | W10: =IF(R10=0,"Not Eligible",IF(V10=1,"Met","Missed")) -> Met
A11: 7526100324 | B11: 926 | C11: Fresh Thyme #926 | D11: Columbus | E11: OH | F11: Mumaw Jayden | G11: US133C17 | H11: 2 | I11: CHGC | J11: 45918.704 | K11: 45925 | L11: =IF(K11="","",TEXT(K11,"YYYY-MM")) -> 2025-09 | M11: closed | N11: 16 | O11: 163.93 | P11: 0 | Q11: 0 | R11: 0 | S11: Customer Contracted Reasons | T11: 1 | V11: =IF(R11=0,"",IF(U11<>"",U11,Q11)) | W11: =IF(R11=0,"Not Eligible",IF(V11=1,"Met","Missed")) -> Not Eligible
A12: 7621012398 | B12: 526 | C12: Fresh Thyme #526 | D12: Indianapolis | E12: IN | F12: McAtee Megan | G12: US133E72 | H12: 2 | I12: CHGC | J12: 46232.578 | K12: 46232 | L12: =IF(K12="","",TEXT(K12,"YYYY-MM")) -> 2026-07 | M12: closed | N12: 16 | O12: 1.28 | P12: 0 | Q12: 0 | R12: 0 | S12: Customer Contracted Reasons | T12: 2 | U12: 1 | V12: =IF(R12=0,"",IF(U12<>"",U12,Q12)) | W12: =IF(R12=0,"Not Eligible",IF(V12=1,"Met","Missed")) -> Not Eligible
A13: 7619803959 | B13: 523 | C13: Fresh Thyme #523 | D13: Lafayette | E13: IN | F13: Bolde Thomas | G13: US153R61 | H13: 2 | I13: MNT | J13: 46220.62 | K13: 46221 | L13: =IF(K13="","",TEXT(K13,"YYYY-MM")) -> 2026-07 | M13: closed | N13: 16 | O13: 27 | P13: 1 | Q13: 1 | R13: 1 | S13: Customer Contracted Reasons | T13: 2 | U13: 1 | V13: =IF(R13=0,"",IF(U13<>"",U13,Q13)) -> 1 | W13: =IF(R13=0,"Not Eligible",IF(V13=1,"Met","Missed")) -> Met
A14: 7526401175 | B14: 925 | C14: Fresh Thyme #925 | D14: Mayfield Heights | E14: OH | F14: Brannon Marquis | G14: US133C75 | H14: 2 | I14: MNT | J14: 45921.631 | K14: 45922 | L14: =IF(K14="","",TEXT(K14,"YYYY-MM")) -> 2025-09 | M14: closed | N14: 16 | O14: 24.53 | P14: 1 | Q14: 1 | R14: 1 | S14: No Exception | T14: 0 | V14: =IF(R14=0,"",IF(U14<>"",U14,Q14)) -> 1 | W14: =IF(R14=0,"Not Eligible",IF(V14=1,"Met","Missed")) -> Met
A15: 7603603855 | B15: 546 | C15: Fresh Thyme #546 | D15: Plymouth | E15: MN | F15: Carlson Paul | G15: US153R72 | H15: 2 | I15: CHGC | J15: 46058.584 | K15: 46058 | L15: =IF(K15="","",TEXT(K15,"YYYY-MM")) -> 2026-02 | M15: closed | N15: 0 | O15: 2.03 | P15: 1 | Q15: 1 | R15: 1 | S15: Customer Contracted Reasons | T15: 2 | U15: 1 | V15: =IF(R15=0,"",IF(U15<>"",U15,Q15)) -> 1 | W15: =IF(R15=0,"Not Eligible",IF(V15=1,"Met","Missed")) -> Met
A16: 7610405508 | B16: 497 | C16: Fresh Thyme #497 | D16: Pleasant Hills | E16: PA | F16: Sutara Robert | G16: US133A18 | H16: 1 | I16: MNT | J16: 46126.463 | K16: 46126 | L16: =IF(K16="","",TEXT(K16,"YYYY-MM")) -> 2026-04 | M16: closed | N16: 0 | O16: 1.78 | P16: 1 | Q16: 1 | R16: 1 | S16: Customer Contracted Reasons | T16: 2 | U16: 1 | V16: =IF(R16=0,"",IF(U16<>"",U16,Q16)) -> 1 | W16: =IF(R16=0,"Not Eligible",IF(V16=1,"Met","Missed")) -> Met
A17: 7617903140 | B17: 541 | C17: Fresh Thyme #541 | D17: Bloomington | E17: MN | F17: Begley Adam | G17: US153R27 | H17: 2 | I17: MNT | J17: 46201.407 | K17: 46201 | L17: =IF(K17="","",TEXT(K17,"YYYY-MM")) -> 2026-06 | M17: closed | N17: 16 | O17: 7.17 | P17: 1 | Q17: 1 | R17: 1 | S17: Customer Contracted Reasons | T17: 2 | U17: 1 | V17: =IF(R17=0,"",IF(U17<>"",U17,Q17)) -> 1 | W17: =IF(R17=0,"Not Eligible",IF(V17=1,"Met","Missed")) -> Met
A18: 7612003885 | B18: 929 | C18: Fresh Thyme #929 | D18: Toledo | E18: OH | F18: Kramer Alec | G18: US133C42 | H18: 2 | I18: MNT | J18: 46142.332 | K18: 46142 | L18: =IF(K18="","",TEXT(K18,"YYYY-MM")) -> 2026-04 | M18: closed | N18: 16 | O18: 4.18 | P18: 1 | Q18: 1 | R18: 1 | S18: Customer Contracted Reasons | T18: 2 | U18: 1 | V18: =IF(R18=0,"",IF(U18<>"",U18,Q18)) -> 1 | W18: =IF(R18=0,"Not Eligible",IF(V18=1,"Met","Missed")) -> Met
A19: 7601102256 | B19: 493 | C19: Fresh Thyme #493 | D19: O Fallon | E19: MO | F19: Vaughn Travis | G19: US153N63 | H19: 2 | I19: CHGC | J19: 46033.569 | K19: 46033 | L19: =IF(K19="","",TEXT(K19,"YYYY-MM")) -> 2026-01 | M19: closed | N19: 16 | O19: 2.52 | P19: 0 | Q19: 0 | R19: 0 | S19: Customer Contracted Reasons | T19: 2 | U19: 1 | V19: =IF(R19=0,"",IF(U19<>"",U19,Q19)) | W19: =IF(R19=0,"Not Eligible",IF(V19=1,"Met","Missed")) -> Not Eligible
A20: 7601501624 | B20: 542 | C20: Fresh Thyme #542 | D20: Apple Valley | E20: MN | F20: Begley Adam | G20: US153R79 | H20: 2 | I20: MNT | J20: 46037.709 | K20: 46037 | L20: =IF(K20="","",TEXT(K20,"YYYY-MM")) -> 2026-01 | M20: closed | N20: 16 | O20: 1.72 | P20: 1 | Q20: 1 | R20: 1 | S20: Customer Contracted Reasons | T20: 2 | U20: 1 | V20: =IF(R20=0,"",IF(U20<>"",U20,Q20)) -> 1 | W20: =IF(R20=0,"Not Eligible",IF(V20=1,"Met","Missed")) -> Met
A21: 7525901406 | B21: 648 | C21: Fresh Thyme #648 | D21: Ypsilanti | E21: MI | F21: Al-Azawy Mustafa | G21: US133U14 | H21: 2 | I21: MNT | J21: 45916.745 | K21: 45917 | L21: =IF(K21="","",TEXT(K21,"YYYY-MM")) -> 2025-09 | M21: closed | N21: 16 | O21: 17.57 | P21: 1 | Q21: 1 | R21: 1 | S21: No Exception | T21: 0 | V21: =IF(R21=0,"",IF(U21<>"",U21,Q21)) -> 1 | W21: =IF(R21=0,"Not Eligible",IF(V21=1,"Met","Missed")) -> Met
A22: 7531506970 | B22: 632 | C22: Fresh Thyme #632 | D22: Downers Grove | E22: IL | F22: O'Connor Bill | G22: US153C13 | H22: 2 | I22: MNT | J22: 45972.529 | K22: 45973 | L22: =IF(K22="","",TEXT(K22,"YYYY-MM")) -> 2025-11 | M22: closed | N22: 16 | O22: 28.5 | P22: 0 | Q22: 0 | R22: 1 | S22: No Exception | T22: 0 | V22: =IF(R22=0,"",IF(U22<>"",U22,Q22)) -> 0 | W22: =IF(R22=0,"Not Eligible",IF(V22=1,"Met","Missed")) -> Missed
A23: 7523303294 | B23: 647 | C23: Fresh Thyme #647 | D23: Portage | E23: MI | F23: Dishman Saundra | G23: US133B54 | H23: 2 | I23: MNT | J23: 45890.361 | K23: 45892 | L23: =IF(K23="","",TEXT(K23,"YYYY-MM")) -> 2025-08 | M23: canceled as duplicate | N23: 16 | O23: 59.87 | P23: 0 | Q23: 0 | R23: 0 | S23: No Exception | T23: 0 | V23: =IF(R23=0,"",IF(U23<>"",U23,Q23)) | W23: =IF(R23=0,"Not Eligible",IF(V23=1,"Met","Missed")) -> Not Eligible
A24: 7620602557 | B24: 931 | C24: Fresh Thyme #931 | D24: North Canton | E24: OH | F24: Workman Truman | G24: US133C48 | H24: 1 | I24: MNT | J24: 46228.619 | K24: 46228 | L24: =IF(K24="","",TEXT(K24,"YYYY-MM")) -> 2026-07 | M24: closed | N24: 12 | O24: 1.9 | P24: 1 | Q24: 1 | R24: 1 | S24: Customer Contracted Reasons | T24: 2 | U24: 1 | V24: =IF(R24=0,"",IF(U24<>"",U24,Q24)) -> 1 | W24: =IF(R24=0,"Not Eligible",IF(V24=1,"Met","Missed")) -> Met
A25: 7524404738 | B25: 544 | C25: Fresh Thyme #544 | D25: Savage | E25: MN | F25: Ogunnowo Olufemi | G25: US153R70 | H25: 2 | I25: MNT | J25: 45901.315 | K25: 45902 | L25: =IF(K25="","",TEXT(K25,"YYYY-MM")) -> 2025-09 | M25: closed | N25: 16 | O25: 35.6 | P25: 0 | Q25: 0 | R25: 1 | S25: Customer Contracted Reasons | T25: 1 | V25: =IF(R25=0,"",IF(U25<>"",U25,Q25)) -> 0 | W25: =IF(R25=0,"Not Eligible",IF(V25=1,"Met","Missed")) -> Missed
A26: 7611409193 | B26: 633 | C26: Fresh Thyme #633 | D26: Naperville | E26: IL | F26: O'Connor Bill | G26: US153C13 | H26: 2 | I26: MNT | J26: 46136.646 | K26: 46137 | L26: =IF(K26="","",TEXT(K26,"YYYY-MM")) -> 2026-04 | M26: closed | N26: 0 | O26: 24.52 | P26: 1 | Q26: 1 | R26: 1 | S26: Customer Contracted Reasons | T26: 2 | U26: 1 | V26: =IF(R26=0,"",IF(U26<>"",U26,Q26)) -> 1 | W26: =IF(R26=0,"Not Eligible",IF(V26=1,"Met","Missed")) -> Met
A27: 7531403109 | B27: 522 | C27: Fresh Thyme #522 | D27: Indianapolis | E27: IN | F27: Ehret Alexander | G27: US133E77 | H27: 1 | I27: MNT | J27: 45971.375 | K27: 45981 | L27: =IF(K27="","",TEXT(K27,"YYYY-MM")) -> 2025-11 | M27: closed | N27: 12 | O27: 244.8 | P27: 0 | Q27: 0 | R27: 1 | S27: Customer Contracted Reasons | T27: 1 | V27: =IF(R27=0,"",IF(U27<>"",U27,Q27)) -> 0 | W27: =IF(R27=0,"Not Eligible",IF(V27=1,"Met","Missed")) -> Missed
A28: 7620100963 | B28: 524 | C28: Fresh Thyme #524 | D28: Fort Wayne | E28: IN | F28: Berkey Scott | G28: US133E62 | H28: 2 | I28: MNT | J28: 46223.393 | K28: 46223 | L28: =IF(K28="","",TEXT(K28,"YYYY-MM")) -> 2026-07 | M28: closed | N28: 16 | O28: 7.98 | P28: 1 | Q28: 1 | R28: 1 | S28: Customer Contracted Reasons | T28: 2 | U28: 1 | V28: =IF(R28=0,"",IF(U28<>"",U28,Q28)) -> 1 | W28: =IF(R28=0,"Not Eligible",IF(V28=1,"Met","Missed")) -> Met
A29: 7535501543 | B29: 647 | C29: Fresh Thyme #647 | D29: Portage | E29: MI | F29: Willea Brandon | G29: US133B47 | H29: 2 | I29: MNT | J29: 46011.865 | K29: 46024 | L29: =IF(K29="","",TEXT(K29,"YYYY-MM")) -> 2026-01 | M29: closed | N29: 16 | O29: 307.87 | P29: 0 | Q29: 0 | R29: 1 | S29: Customer Contracted Reasons | T29: 1 | V29: =IF(R29=0,"",IF(U29<>"",U29,Q29)) -> 0 | W29: =IF(R29=0,"Not Eligible",IF(V29=1,"Met","Missed")) -> Missed
A30: 7530106514 | B30: 640 | C30: Fresh Thyme #640 | D30: East Lansing | E30: MI | F30: Crane Travis | G30: US133B36 | H30: 1 | I30: MNT | J30: 45958.603 | K30: 45959 | L30: =IF(K30="","",TEXT(K30,"YYYY-MM")) -> 2025-10 | M30: closed | N30: 12 | O30: 21.45 | P30: 1 | Q30: 1 | R30: 1 | S30: No Exception | T30: 0 | V30: =IF(R30=0,"",IF(U30<>"",U30,Q30)) -> 1 | W30: =IF(R30=0,"Not Eligible",IF(V30=1,"Met","Missed")) -> Met
A31: 7600504723 | B31: 928 | C31: Fresh Thyme #928 | D31: Westlake | E31: OH | F31: McDonald Noah | G31: US133C72 | H31: 2 | I31: MNT | J31: 46027.394 | K31: 46027 | L31: =IF(K31="","",TEXT(K31,"YYYY-MM")) -> 2026-01 | M31: closed | N31: 16 | O31: 3.62 | P31: 1 | Q31: 1 | R31: 1 | S31: Customer Contracted Reasons | T31: 2 | U31: 1 | V31: =IF(R31=0,"",IF(U31<>"",U31,Q31)) -> 1 | W31: =IF(R31=0,"Not Eligible",IF(V31=1,"Met","Missed")) -> Met
A32: 7524606956 | B32: 544 | C32: Fresh Thyme #544 | D32: Savage | E32: MN | F32: Bush David | G32: US153R73 | H32: 1 | I32: MNT | J32: 45903.435 | K32: 45903 | L32: =IF(K32="","",TEXT(K32,"YYYY-MM")) -> 2025-09 | M32: closed | N32: 12 | O32: 2.97 | P32: 1 | Q32: 1 | R32: 1 | S32: No Exception | T32: 0 | V32: =IF(R32=0,"",IF(U32<>"",U32,Q32)) -> 1 | W32: =IF(R32=0,"Not Eligible",IF(V32=1,"Met","Missed")) -> Met
A33: 7618000492 | B33: 493 | C33: Fresh Thyme #493 | D33: O Fallon | E33: MO | F33: Ling Daniel | G33: US153N76 | H33: 1 | I33: CHGC | J33: 46201.841 | K33: 46203 | L33: =IF(K33="","",TEXT(K33,"YYYY-MM")) -> 2026-06 | M33: closed | N33: 12 | O33: 42.82 | P33: 0 | Q33: 0 | R33: 0 | S33: Customer Contracted Reasons | T33: 1 | V33: =IF(R33=0,"",IF(U33<>"",U33,Q33)) | W33: =IF(R33=0,"Not Eligible",IF(V33=1,"Met","Missed")) -> Not Eligible
A34: 7606002257 | B34: 639 | C34: Fresh Thyme #639 | D34: Geneva | E34: IL | F34: Birchfield Jeffrey | G34: US153C14 | H34: 1 | I34: MNT | J34: 46082.392 | K34: 46082 | L34: =IF(K34="","",TEXT(K34,"YYYY-MM")) -> 2026-03 | M34: closed | N34: 0 | O34: 3.07 | P34: 1 | Q34: 1 | R34: 1 | S34: Customer Contracted Reasons | T34: 2 | U34: 1 | V34: =IF(R34=0,"",IF(U34<>"",U34,Q34)) -> 1 | W34: =IF(R34=0,"Not Eligible",IF(V34=1,"Met","Missed")) -> Met
A35: 7525201332 | B35: 494 | C35: Fresh Thyme #494 | D35: Saint Louis | E35: MO | F35: Coghill John | G35: US153N66 | H35: 2 | I35: CHGC | J35: 45909.665 | K35: 45909 | L35: =IF(K35="","",TEXT(K35,"YYYY-MM")) -> 2025-09 | M35: closed | N35: 16 | O35: 2.37 | P35: 0 | Q35: 0 | R35: 0 | S35: No Exception | T35: 0 | V35: =IF(R35=0,"",IF(U35<>"",U35,Q35)) | W35: =IF(R35=0,"Not Eligible",IF(V35=1,"Met","Missed")) -> Not Eligible
A36: 7600205143 | B36: 931 | C36: Fresh Thyme #931 | D36: North Canton | E36: OH | F36: Grismer Bill | G36: US133C87 | H36: 2 | I36: CHGC | J36: 46024.779 | K36: 46025 | L36: =IF(K36="","",TEXT(K36,"YYYY-MM")) -> 2026-01 | M36: closed | N36: 16 | O36: 19.7 | P36: 0 | Q36: 0 | R36: 0 | S36: Customer Contracted Reasons | T36: 1 | V36: =IF(R36=0,"",IF(U36<>"",U36,Q36)) | W36: =IF(R36=0,"Not Eligible",IF(V36=1,"Met","Missed")) -> Not Eligible
A37: 7604100360 | B37: 640 | C37: Fresh Thyme #640 | D37: East Lansing | E37: MI | F37: Tait Laura | G37: US133B35 | H37: 2 | I37: MNT | J37: 46063.66 | K37: 46067 | L37: =IF(K37="","",TEXT(K37,"YYYY-MM")) -> 2026-02 | M37: closed | N37: 0 | O37: 91.73 | P37: 1 | Q37: 1 | R37: 1 | S37: Customer Contracted Reasons | T37: 1 | V37: =IF(R37=0,"",IF(U37<>"",U37,Q37)) -> 1 | W37: =IF(R37=0,"Not Eligible",IF(V37=1,"Met","Missed")) -> Met
A38: 7612213351 | B38: 710 | C38: Fresh Thyme #710 | D38: Greenfield | E38: WI | F38: Kelly James | G38: US153C54 | H38: 2 | I38: MNT | J38: 46144.528 | K38: 46144 | L38: =IF(K38="","",TEXT(K38,"YYYY-MM")) -> 2026-05 | M38: closed | N38: 0 | O38: 2.32 | P38: 1 | Q38: 1 | R38: 1 | S38: Customer Contracted Reasons | T38: 2 | U38: 1 | V38: =IF(R38=0,"",IF(U38<>"",U38,Q38)) -> 1 | W38: =IF(R38=0,"Not Eligible",IF(V38=1,"Met","Missed")) -> Met
A39: 7521704609 | B39: 546 | C39: Fresh Thyme #546 | D39: Plymouth | E39: MN | F39: Carlson Paul | G39: US153R72 | H39: 2 | I39: CHGC | J39: 45874.573 | K39: 45876 | L39: =IF(K39="","",TEXT(K39,"YYYY-MM")) -> 2025-08 | M39: closed | N39: 16 | O39: 43.2 | P39: 0 | Q39: 0 | R39: 0 | S39: No Exception | T39: 0 | V39: =IF(R39=0,"",IF(U39<>"",U39,Q39)) | W39: =IF(R39=0,"Not Eligible",IF(V39=1,"Met","Missed")) -> Not Eligible
A40: 7532709357 | B40: 648 | C40: Fresh Thyme #648 | D40: Ypsilanti | E40: MI | F40: Al-Azawy Mustafa | G40: US133U14 | H40: 2 | I40: CHGC | J40: 45983.893 | K40: 45984 | L40: =IF(K40="","",TEXT(K40,"YYYY-MM")) -> 2025-11 | M40: closed | N40: 16 | O40: 9.87 | P40: 0 | Q40: 0 | R40: 0 | S40: No Exception | T40: 0 | V40: =IF(R40=0,"",IF(U40<>"",U40,Q40)) | W40: =IF(R40=0,"Not Eligible",IF(V40=1,"Met","Missed")) -> Not Eligible
A41: 7601201077 | B41: 546 | C41: Fresh Thyme #546 | D41: Plymouth | E41: MN | F41: Begley Adam | G41: US153R79 | H41: 2 | I41: MNT | J41: 46034.558 | K41: 46034 | L41: =IF(K41="","",TEXT(K41,"YYYY-MM")) -> 2026-01 | M41: closed | N41: 16 | O41: 6.85 | P41: 1 | Q41: 1 | R41: 1 | S41: Customer Contracted Reasons | T41: 2 | U41: 1 | V41: =IF(R41=0,"",IF(U41<>"",U41,Q41)) -> 1 | W41: =IF(R41=0,"Not Eligible",IF(V41=1,"Met","Missed")) -> Met
A42: 7523105395 | B42: 647 | C42: Fresh Thyme #647 | D42: Portage | E42: MI | F42: Lenardson Joshua | G42: US133B55 | H42: 2 | I42: MNT | J42: 45888.681 | K42: 45896 | L42: =IF(K42="","",TEXT(K42,"YYYY-MM")) -> 2025-08 | M42: closed | N42: 16 | O42: 193.7 | P42: 0 | Q42: 0 | R42: 1 | S42: No Exception | T42: 0 | V42: =IF(R42=0,"",IF(U42<>"",U42,Q42)) -> 0 | W42: =IF(R42=0,"Not Eligible",IF(V42=1,"Met","Missed")) -> Missed
A43: 7525513317 | B43: 701 | C43: Fresh Thyme #701 | D43: Milwaukee | E43: WI | F43: Kelly James | G43: US153R04 | H43: 1 | I43: MNT | J43: 45912.766 | K43: 45912 | L43: =IF(K43="","",TEXT(K43,"YYYY-MM")) -> 2025-09 | M43: closed | N43: 12 | O43: 1.93 | P43: 1 | Q43: 1 | R43: 1 | S43: No Exception | T43: 0 | V43: =IF(R43=0,"",IF(U43<>"",U43,Q43)) -> 1 | W43: =IF(R43=0,"Not Eligible",IF(V43=1,"Met","Missed")) -> Met
A44: 7614112943 | B44: 528 | C44: Fresh Thyme #528 | D44: Carmel | E44: IN | F44: Ehret Alexander | G44: US133E77 | H44: 2 | I44: CHGC | J44: 46163.52 | K44: 46163 | L44: =IF(K44="","",TEXT(K44,"YYYY-MM")) -> 2026-05 | M44: closed | N44: 16 | O44: 1.95 | P44: 0 | Q44: 0 | R44: 0 | S44: Customer Contracted Reasons | T44: 2 | U44: 1 | V44: =IF(R44=0,"",IF(U44<>"",U44,Q44)) | W44: =IF(R44=0,"Not Eligible",IF(V44=1,"Met","Missed")) -> Not Eligible
A45: 7614109881 | B45: 562 | C45: Fresh Thyme #562 | D45: Waite Park | E45: MN | F45: Larson Warren | G45: US153R19 | H45: 2 | I45: MNT | J45: 46162.854 | K45: 46163 | L45: =IF(K45="","",TEXT(K45,"YYYY-MM")) -> 2026-05 | M45: closed | N45: 16 | O45: 14.15 | P45: 1 | Q45: 1 | R45: 1 | S45: Customer Contracted Reasons | T45: 2 | U45: 1 | V45: =IF(R45=0,"",IF(U45<>"",U45,Q45)) -> 1 | W45: =IF(R45=0,"Not Eligible",IF(V45=1,"Met","Missed")) -> Met
A46: 7606605823 | B46: 532 | C46: Fresh Thyme #532 | D46: Indianapolis | E46: IN | F46: May Nicholas | G46: US133E71 | H46: 2 | I46: MNT | J46: 46088.39 | K46: 46091 | L46: =IF(K46="","",TEXT(K46,"YYYY-MM")) -> 2026-03 | M46: closed | N46: 0 | O46: 80.37 | P46: 1 | Q46: 1 | R46: 1 | S46: Customer Contracted Reasons | T46: 1 | V46: =IF(R46=0,"",IF(U46<>"",U46,Q46)) -> 1 | W46: =IF(R46=0,"Not Eligible",IF(V46=1,"Met","Missed")) -> Met
A47: 7528302118 | B47: 546 | C47: Fresh Thyme #546 | D47: Plymouth | E47: MN | F47: Carlson Paul | G47: US153R72 | H47: 2 | I47: CHGC | J47: 45940.651 | K47: 45941 | L47: =IF(K47="","",TEXT(K47,"YYYY-MM")) -> 2025-10 | M47: closed | N47: 16 | O47: 16.97 | P47: 0 | Q47: 0 | R47: 0 | S47: No Exception | T47: 0 | V47: =IF(R47=0,"",IF(U47<>"",U47,Q47)) | W47: =IF(R47=0,"Not Eligible",IF(V47=1,"Met","Missed")) -> Not Eligible
A48: 7613405652 | B48: 494 | C48: Fresh Thyme #494 | D48: Saint Louis | E48: MO | F48: Patton Alfred | G48: US153N64 | H48: 1 | I48: MNT | J48: 46156.512 | K48: 46156 | L48: =IF(K48="","",TEXT(K48,"YYYY-MM")) -> 2026-05 | M48: closed | N48: 0 | O48: 4.38 | P48: 1 | Q48: 1 | R48: 1 | S48: Customer Contracted Reasons | T48: 2 | U48: 1 | V48: =IF(R48=0,"",IF(U48<>"",U48,Q48)) -> 1 | W48: =IF(R48=0,"Not Eligible",IF(V48=1,"Met","Missed")) -> Met
A49: 7534506026 | B49: 537 | C49: Fresh Thyme #537 | D49: West Lafayette | E49: IN | F49: Wolff Travis | G49: US153C41 | H49: 1 | I49: MNT | J49: 46002.555 | K49: 46002 | L49: =IF(K49="","",TEXT(K49,"YYYY-MM")) -> 2025-12 | M49: closed | N49: 12 | O49: 2.52 | P49: 1 | Q49: 1 | R49: 1 | S49: No Exception | T49: 0 | V49: =IF(R49=0,"",IF(U49<>"",U49,Q49)) -> 1 | W49: =IF(R49=0,"Not Eligible",IF(V49=1,"Met","Missed")) -> Met
A50: 7608203087 | B50: 533 | C50: Fresh Thyme #533 | D50: Terre Haute | E50: IN | F50: Ownby Ryan | G50: US133E44 | H50: 2 | I50: MNT | J50: 46104.287 | K50: 46104 | L50: =IF(K50="","",TEXT(K50,"YYYY-MM")) -> 2026-03 | M50: closed | N50: 0 | O50: 9.78 | P50: 1 | Q50: 1 | R50: 1 | S50: Customer Contracted Reasons | T50: 2 | U50: 1 | V50: =IF(R50=0,"",IF(U50<>"",U50,Q50)) -> 1 | W50: =IF(R50=0,"Not Eligible",IF(V50=1,"Met","Missed")) -> Met
A51: 7619303079 | B51: 493 | C51: Fresh Thyme #493 | D51: O Fallon | E51: MO | F51: Patton Alfred | G51: US153N64 | H51: 2 | I51: CHGC | J51: 46215.534 | K51: 46215 | L51: =IF(K51="","",TEXT(K51,"YYYY-MM")) -> 2026-07 | M51: closed | N51: 16 | O51: 3.97 | P51: 0 | Q51: 0 | R51: 0 | S51: Customer Contracted Reasons | T51: 2 | U51: 1 | V51: =IF(R51=0,"",IF(U51<>"",U51,Q51)) | W51: =IF(R51=0,"Not Eligible",IF(V51=1,"Met","Missed")) -> Not Eligible
A52: 7617502553 | B52: 928 | C52: Fresh Thyme #928 | D52: Westlake | E52: OH | F52: McDonald Noah | G52: US133C72 | H52: 2 | I52: MNT | J52: 46197.394 | K52: 46199 | L52: =IF(K52="","",TEXT(K52,"YYYY-MM")) -> 2026-06 | M52: closed | N52: 16 | O52: 57.43 | P52: 0 | Q52: 0 | R52: 1 | S52: Customer Contracted Reasons | T52: 1 | V52: =IF(R52=0,"",IF(U52<>"",U52,Q52)) -> 0 | W52: =IF(R52=0,"Not Eligible",IF(V52=1,"Met","Missed")) -> Missed
A53: 7618110245 | B53: 639 | C53: Fresh Thyme #639 | D53: Geneva | E53: IL | F53: Lopez Marcos | G53: US153C15 | H53: 2 | I53: MNT | J53: 46203.625 | K53: 46203 | L53: =IF(K53="","",TEXT(K53,"YYYY-MM")) -> 2026-06 | M53: closed | N53: 16 | O53: 3.05 | P53: 1 | Q53: 1 | R53: 1 | S53: Customer Contracted Reasons | T53: 2 | U53: 1 | V53: =IF(R53=0,"",IF(U53<>"",U53,Q53)) -> 1 | W53: =IF(R53=0,"Not Eligible",IF(V53=1,"Met","Missed")) -> Met
A54: 7521704683 | B54: 701 | C54: Fresh Thyme #701 | D54: Milwaukee | E54: WI | F54: Farrington Katrel | G54: US153R01 | H54: 2 | I54: MNT | J54: 45874.586 | K54: 45877 | L54: =IF(K54="","",TEXT(K54,"YYYY-MM")) -> 2025-08 | M54: closed | N54: 16 | O54: 72.85 | P54: 0 | Q54: 0 | R54: 1 | S54: No Exception | T54: 0 | V54: =IF(R54=0,"",IF(U54<>"",U54,Q54)) -> 0 | W54: =IF(R54=0,"Not Eligible",IF(V54=1,"Met","Missed")) -> Missed
A55: 7618212327 | B55: 524 | C55: Fresh Thyme #524 | D55: Fort Wayne | E55: IN | F55: Berkey Scott | G55: US133E62 | H55: 2 | I55: MNT | J55: 46204.408 | K55: 46204 | L55: =IF(K55="","",TEXT(K55,"YYYY-MM")) -> 2026-07 | M55: closed | N55: 16 | O55: 2.02 | P55: 1 | Q55: 1 | R55: 1 | S55: Customer Contracted Reasons | T55: 2 | U55: 1 | V55: =IF(R55=0,"",IF(U55<>"",U55,Q55)) -> 1 | W55: =IF(R55=0,"Not Eligible",IF(V55=1,"Met","Missed")) -> Met
A56: 7606002214 | B56: 643 | C56: Fresh Thyme #643 | D56: Troy | E56: MI | F56: Piazzi Gail | G56: US133U01 | H56: 1 | I56: MNT | J56: 46082.409 | K56: 46082 | L56: =IF(K56="","",TEXT(K56,"YYYY-MM")) -> 2026-03 | M56: closed | N56: 0 | O56: 5.03 | P56: 1 | Q56: 1 | R56: 1 | S56: Customer Contracted Reasons | T56: 2 | U56: 1 | V56: =IF(R56=0,"",IF(U56<>"",U56,Q56)) -> 1 | W56: =IF(R56=0,"Not Eligible",IF(V56=1,"Met","Missed")) -> Met
A57: 7536509827 | B57: 525 | C57: Fresh Thyme #525 | D57: Indianapolis | E57: IN | F57: Brown Jordan | G57: US133E73 | H57: 2 | I57: MNT | J57: 46022.638 | K57: 46022 | L57: =IF(K57="","",TEXT(K57,"YYYY-MM")) -> 2025-12 | M57: closed | N57: 16 | O57: 1.97 | P57: 1 | Q57: 1 | R57: 1 | S57: No Exception | T57: 0 | V57: =IF(R57=0,"",IF(U57<>"",U57,Q57)) -> 1 | W57: =IF(R57=0,"Not Eligible",IF(V57=1,"Met","Missed")) -> Met
A58: 7601102405 | B58: 526 | C58: Fresh Thyme #526 | D58: Indianapolis | E58: IN | F58: Qi Chuan | G58: US133E79 | H58: 2 | I58: CHGC | J58: 46033.666 | K58: 46033 | L58: =IF(K58="","",TEXT(K58,"YYYY-MM")) -> 2026-01 | M58: closed | N58: 16 | O58: 3.53 | P58: 0 | Q58: 0 | R58: 0 | S58: Customer Contracted Reasons | T58: 2 | U58: 1 | V58: =IF(R58=0,"",IF(U58<>"",U58,Q58)) | W58: =IF(R58=0,"Not Eligible",IF(V58=1,"Met","Missed")) -> Not Eligible
A59: 7620907076 | B59: 636 | C59: Fresh Thyme #636 | D59: River Forest | E59: IL | F59: Thames Perry | G59: US153C21 | H59: 2 | I59: CHGC | J59: 46231.424 | K59: 46234 | L59: =IF(K59="","",TEXT(K59,"YYYY-MM")) -> 2026-07 | M59: closed | N59: 16 | O59: 72.2 | P59: 0 | Q59: 0 | R59: 0 | S59: Customer Contracted Reasons | T59: 1 | V59: =IF(R59=0,"",IF(U59<>"",U59,Q59)) | W59: =IF(R59=0,"Not Eligible",IF(V59=1,"Met","Missed")) -> Not Eligible
A60: 7527205737 | B60: 561 | C60: Fresh Thyme #561 | D60: Minneapolis | E60: MN | F60: Carlson Paul | G60: US153R72 | H60: 2 | I60: MNT | J60: 45929.554 | K60: 45931 | L60: =IF(K60="","",TEXT(K60,"YYYY-MM")) -> 2025-10 | M60: closed | N60: 16 | O60: 50.27 | P60: 0 | Q60: 0 | R60: 1 | S60: Customer Contracted Reasons | T60: 1 | V60: =IF(R60=0,"",IF(U60<>"",U60,Q60)) -> 0 | W60: =IF(R60=0,"Not Eligible",IF(V60=1,"Met","Missed")) -> Missed
A61: 7617605712 | B61: 931 | C61: Fresh Thyme #931 | D61: North Canton | E61: OH | F61: Hovanec Marc | G61: US133C90 | H61: 1 | I61: MNT | J61: 46198.604 | K61: 46199 | L61: =IF(K61="","",TEXT(K61,"YYYY-MM")) -> 2026-06 | M61: closed | N61: 12 | O61: 20.95 | P61: 1 | Q61: 1 | R61: 1 | S61: Customer Contracted Reasons | T61: 2 | U61: 1 | V61: =IF(R61=0,"",IF(U61<>"",U61,Q61)) -> 1 | W61: =IF(R61=0,"Not Eligible",IF(V61=1,"Met","Missed")) -> Met
A62: 7525214566 | B62: 528 | C62: Fresh Thyme #528 | D62: Carmel | E62: IN | F62: Qi Chuan | G62: US133E79 | H62: 2 | I62: MNT | J62: 45909.401 | K62: 45910 | L62: =IF(K62="","",TEXT(K62,"YYYY-MM")) -> 2025-09 | M62: closed | N62: 16 | O62: 24.38 | P62: 1 | Q62: 1 | R62: 1 | S62: No Exception | T62: 0 | V62: =IF(R62=0,"",IF(U62<>"",U62,Q62)) -> 1 | W62: =IF(R62=0,"Not Eligible",IF(V62=1,"Met","Missed")) -> Met
A63: 7525401279 | B63: 537 | C63: Fresh Thyme #537 | D63: West Lafayette | E63: IN | F63: Wolff Travis | G63: US153C41 | H63: 2 | I63: MNT | J63: 45911.724 | K63: 45912 | L63: =IF(K63="","",TEXT(K63,"YYYY-MM")) -> 2025-09 | M63: closed | N63: 16 | O63: 19.72 | P63: 1 | Q63: 1 | R63: 1 | S63: No Exception | T63: 0 | V63: =IF(R63=0,"",IF(U63<>"",U63,Q63)) -> 1 | W63: =IF(R63=0,"Not Eligible",IF(V63=1,"Met","Missed")) -> Met
A64: 7611912938 | B64: 637 | C64: Fresh Thyme #637 | D64: Crystal Lake | E64: IL | F64: Droste Michael | G64: US153C10 | H64: 2 | I64: MNT | J64: 46141.522 | K64: 46143 | L64: =IF(K64="","",TEXT(K64,"YYYY-MM")) -> 2026-05 | M64: closed | N64: 16 | O64: 54.95 | P64: 0 | Q64: 0 | R64: 1 | S64: Customer Contracted Reasons | T64: 1 | V64: =IF(R64=0,"",IF(U64<>"",U64,Q64)) -> 0 | W64: =IF(R64=0,"Not Eligible",IF(V64=1,"Met","Missed")) -> Missed
A65: 7604703168 | B65: 631 | C65: Fresh Thyme #631 | D65: Fairview Heights | E65: IL | F65: Johnson Brock | G65: US153N74 | H65: 2 | I65: MNT | J65: 46069.437 | K65: 46069 | L65: =IF(K65="","",TEXT(K65,"YYYY-MM")) -> 2026-02 | M65: closed | N65: 0 | O65: 7.03 | P65: 1 | Q65: 1 | R65: 1 | S65: Customer Contracted Reasons | T65: 2 | U65: 1 | V65: =IF(R65=0,"",IF(U65<>"",U65,Q65)) -> 1 | W65: =IF(R65=0,"Not Eligible",IF(V65=1,"Met","Missed")) -> Met
A66: 7534008699 | B66: 535 | C66: Fresh Thyme #535 | D66: Muncie | E66: IN | F66: Brown Jordan | G66: US133E73 | H66: 1 | I66: MNT | J66: 45997.775 | K66: 45998 | L66: =IF(K66="","",TEXT(K66,"YYYY-MM")) -> 2025-12 | M66: closed | N66: 12 | O66: 20.4 | P66: 1 | Q66: 1 | R66: 1 | S66: No Exception | T66: 0 | V66: =IF(R66=0,"",IF(U66<>"",U66,Q66)) -> 1 | W66: =IF(R66=0,"Not Eligible",IF(V66=1,"Met","Missed")) -> Met
A67: 7524606974 | B67: 544 | C67: Fresh Thyme #544 | D67: Savage | E67: MN | F67: Bush David | G67: US153R73 | H67: 1 | I67: MNT | J67: 45903.438 | K67: 45903 | L67: =IF(K67="","",TEXT(K67,"YYYY-MM")) -> 2025-09 | M67: closed | N67: 12 | O67: 3 | P67: 1 | Q67: 1 | R67: 1 | S67: No Exception | T67: 0 | V67: =IF(R67=0,"",IF(U67<>"",U67,Q67)) -> 1 | W67: =IF(R67=0,"Not Eligible",IF(V67=1,"Met","Missed")) -> Met
A68: 7601403432 | B68: 493 | C68: Fresh Thyme #493 | D68: O Fallon | E68: MO | F68: Schindler Nathan | G68: US153N62 | H68: 1 | I68: MNT | J68: 46036.346 | K68: 46037 | L68: =IF(K68="","",TEXT(K68,"YYYY-MM")) -> 2026-01 | M68: closed | N68: 12 | O68: 31.07 | P68: 0 | Q68: 0 | R68: 1 | S68: Customer Contracted Reasons | T68: 1 | V68: =IF(R68=0,"",IF(U68<>"",U68,Q68)) -> 0 | W68: =IF(R68=0,"Not Eligible",IF(V68=1,"Met","Missed")) -> Missed
A69: 7617300249 | B69: 931 | C69: Fresh Thyme #931 | D69: North Canton | E69: OH | F69: Nichols Ty | G69: US133C84 | H69: 1 | I69: CHGC | J69: 46195.694 | K69: 46197 | L69: =IF(K69="","",TEXT(K69,"YYYY-MM")) -> 2026-06 | M69: closed | N69: 12 | O69: 41.95 | P69: 0 | Q69: 0 | R69: 0 | S69: Customer Contracted Reasons | T69: 1 | V69: =IF(R69=0,"",IF(U69<>"",U69,Q69)) | W69: =IF(R69=0,"Not Eligible",IF(V69=1,"Met","Missed")) -> Not Eligible
A70: 7622205665 | B70: 448 | C70: Fresh Thyme #448 | D70: St. Louis | E70: MO | F70: Patton Alfred | G70: US153N64 | H70: 1 | I70: CHGC | J70: 46244.428 | K70: 46244 | L70: =IF(K70="","",TEXT(K70,"YYYY-MM")) -> 2026-08 | M70: closed | N70: 12 | O70: 7.8 | P70: 0 | Q70: 0 | R70: 0 | S70: No Exception | T70: 0 | V70: =IF(R70=0,"",IF(U70<>"",U70,Q70)) | W70: =IF(R70=0,"Not Eligible",IF(V70=1,"Met","Missed")) -> Not Eligible
A71: 7523502631 | B71: 525 | C71: Fresh Thyme #525 | D71: Indianapolis | E71: IN | F71: Isaac Hany | G71: US133E70 | H71: 2 | I71: CHGC | J71: 45892.819 | K71: 45893 | L71: =IF(K71="","",TEXT(K71,"YYYY-MM")) -> 2025-08 | M71: closed | N71: 16 | O71: 20.2 | P71: 0 | Q71: 0 | R71: 0 | S71: No Exception | T71: 0 | V71: =IF(R71=0,"",IF(U71<>"",U71,Q71)) | W71: =IF(R71=0,"Not Eligible",IF(V71=1,"Met","Missed")) -> Not Eligible
A72: 7533602044 | B72: 537 | C72: Fresh Thyme #537 | D72: West Lafayette | E72: IN | F72: Wolff Travis | G72: US153C41 | H72: 2 | I72: MNT | J72: 45993.692 | K72: 45994 | L72: =IF(K72="","",TEXT(K72,"YYYY-MM")) -> 2025-12 | M72: closed | N72: 16 | O72: 20.9 | P72: 1 | Q72: 1 | R72: 1 | S72: No Exception | T72: 0 | V72: =IF(R72=0,"",IF(U72<>"",U72,Q72)) -> 1 | W72: =IF(R72=0,"Not Eligible",IF(V72=1,"Met","Missed")) -> Met
A73: 7618701084 | B73: 634 | C73: Fresh Thyme #634 | D73: Joliet | E73: IL | F73: Arrington Timothy | G73: US153C28 | H73: 2 | I73: MNT | J73: 46209.607 | K73: 46218 | L73: =IF(K73="","",TEXT(K73,"YYYY-MM")) -> 2026-07 | M73: closed | N73: 16 | O73: 216.5 | P73: 0 | Q73: 0 | R73: 1 | S73: Customer Contracted Reasons | T73: 0 | U73: 0 | V73: =IF(R73=0,"",IF(U73<>"",U73,Q73)) -> 0 | W73: =IF(R73=0,"Not Eligible",IF(V73=1,"Met","Missed")) -> Missed
A74: 7610604948 | B74: 648 | C74: Fresh Thyme #648 | D74: Ypsilanti | E74: MI | F74: Unassigned | G74: UNASSIGNED | H74: 2 | I74: MNT | J74: 46128.427 | K74: 46128 | L74: =IF(K74="","",TEXT(K74,"YYYY-MM")) -> 2026-04 | M74: canceled by ncr | N74: 0 | O74: 0.13 | P74: 1 | Q74: 1 | R74: 1 | S74: Customer Contracted Reasons | T74: 1 | V74: =IF(R74=0,"",IF(U74<>"",U74,Q74)) -> 1 | W74: =IF(R74=0,"Not Eligible",IF(V74=1,"Met","Missed")) -> Met
A75: 7620802549 | B75: 637 | C75: Fresh Thyme #637 | D75: Crystal Lake | E75: IL | F75: Droste Michael | G75: US153C10 | H75: 2 | I75: MNT | J75: 46230.604 | K75: 46230 | L75: =IF(K75="","",TEXT(K75,"YYYY-MM")) -> 2026-07 | M75: closed | N75: 16 | O75: 4.03 | P75: 1 | Q75: 1 | R75: 1 | S75: Customer Contracted Reasons | T75: 2 | U75: 1 | V75: =IF(R75=0,"",IF(U75<>"",U75,Q75)) -> 1 | W75: =IF(R75=0,"Not Eligible",IF(V75=1,"Met","Missed")) -> Met
A76: 7613500273 | B76: 633 | C76: Fresh Thyme #633 | D76: Naperville | E76: IL | F76: August Ronald | G76: US153C07 | H76: 2 | I76: MNT | J76: 46157.658 | K76: 46161 | L76: =IF(K76="","",TEXT(K76,"YYYY-MM")) -> 2026-05 | M76: closed | N76: 16 | O76: 96.7 | P76: 0 | Q76: 0 | R76: 1 | S76: Customer Contracted Reasons | T76: 0 | U76: 0 | V76: =IF(R76=0,"",IF(U76<>"",U76,Q76)) -> 0 | W76: =IF(R76=0,"Not Eligible",IF(V76=1,"Met","Missed")) -> Missed
A77: 7615315154 | B77: 562 | C77: Fresh Thyme #562 | D77: Waite Park | E77: MN | F77: Larson Warren | G77: US153R19 | H77: 2 | I77: MNT | J77: 46175.515 | K77: 46175 | L77: =IF(K77="","",TEXT(K77,"YYYY-MM")) -> 2026-06 | M77: closed | N77: 16 | O77: 3.47 | P77: 1 | Q77: 1 | R77: 1 | S77: Customer Contracted Reasons | T77: 2 | U77: 1 | V77: =IF(R77=0,"",IF(U77<>"",U77,Q77)) -> 1 | W77: =IF(R77=0,"Not Eligible",IF(V77=1,"Met","Missed")) -> Met
A78: 7602702923 | B78: 635 | C78: Fresh Thyme #635 | D78: Chicago | E78: IL | F78: Gooden Jamell | G78: US153C12 | H78: 2 | I78: MNT | J78: 46049.349 | K78: 46049 | L78: =IF(K78="","",TEXT(K78,"YYYY-MM")) -> 2026-01 | M78: closed | N78: 16 | O78: 2.75 | P78: 1 | Q78: 1 | R78: 1 | S78: Customer Contracted Reasons | T78: 2 | U78: 1 | V78: =IF(R78=0,"",IF(U78<>"",U78,Q78)) -> 1 | W78: =IF(R78=0,"Not Eligible",IF(V78=1,"Met","Missed")) -> Met
A79: 7606400037 | B79: 494 | C79: Fresh Thyme #494 | D79: Saint Louis | E79: MO | F79: Patton Alfred | G79: US153N64 | H79: 1 | I79: CHGC | J79: 46086.549 | K79: 46087 | L79: =IF(K79="","",TEXT(K79,"YYYY-MM")) -> 2026-03 | M79: closed | N79: 0 | O79: 26.75 | P79: 1 | Q79: 1 | R79: 1 | S79: Customer Contracted Reasons | T79: 1 | V79: =IF(R79=0,"",IF(U79<>"",U79,Q79)) -> 1 | W79: =IF(R79=0,"Not Eligible",IF(V79=1,"Met","Missed")) -> Met
A80: 7606609442 | B80: 649 | C80: Fresh Thyme #649 | D80: Canton | E80: MI | F80: Al-Azawy Mustafa | G80: US133U14 | H80: 2 | I80: MNT | J80: 46088.665 | K80: 46089 | L80: =IF(K80="","",TEXT(K80,"YYYY-MM")) -> 2026-03 | M80: closed | N80: 0 | O80: 14.5 | P80: 1 | Q80: 1 | R80: 1 | S80: Customer Contracted Reasons | T80: 2 | U80: 1 | V80: =IF(R80=0,"",IF(U80<>"",U80,Q80)) -> 1 | W80: =IF(R80=0,"Not Eligible",IF(V80=1,"Met","Missed")) -> Met
A81: 7535201789 | B81: 546 | C81: Fresh Thyme #546 | D81: Plymouth | E81: MN | F81: Ogunnowo Olufemi | G81: US153R70 | H81: 2 | I81: MNT | J81: 46009.67 | K81: 46009 | L81: =IF(K81="","",TEXT(K81,"YYYY-MM")) -> 2025-12 | M81: closed | N81: 16 | O81: 4.35 | P81: 1 | Q81: 1 | R81: 1 | S81: No Exception | T81: 0 | V81: =IF(R81=0,"",IF(U81<>"",U81,Q81)) -> 1 | W81: =IF(R81=0,"Not Eligible",IF(V81=1,"Met","Missed")) -> Met
A82: 7605405426 | B82: 639 | C82: Fresh Thyme #639 | D82: Geneva | E82: IL | F82: August Ronald | G82: US153C07 | H82: 1 | I82: MNT | J82: 46076.352 | K82: 46076 | L82: =IF(K82="","",TEXT(K82,"YYYY-MM")) -> 2026-02 | M82: closed | N82: 0 | O82: 3.4 | P82: 1 | Q82: 1 | R82: 1 | S82: Customer Contracted Reasons | T82: 2 | U82: 1 | V82: =IF(R82=0,"",IF(U82<>"",U82,Q82)) -> 1 | W82: =IF(R82=0,"Not Eligible",IF(V82=1,"Met","Missed")) -> Met
A83: 7531903475 | B83: 647 | C83: Fresh Thyme #647 | D83: Portage | E83: MI | F83: Poley Gavin | G83: US133B43 | H83: 2 | I83: MNT | J83: 45976.438 | K83: 45982 | L83: =IF(K83="","",TEXT(K83,"YYYY-MM")) -> 2025-11 | M83: closed | N83: 16 | O83: 146.78 | P83: 0 | Q83: 0 | R83: 1 | S83: Customer Contracted Reasons | T83: 1 | V83: =IF(R83=0,"",IF(U83<>"",U83,Q83)) -> 0 | W83: =IF(R83=0,"Not Eligible",IF(V83=1,"Met","Missed")) -> Missed
A84: 7621902493 | B84: 643 | C84: Fresh Thyme #643 | D84: Troy | E84: MI | F84: Anderson John | G84: US133U32 | H84: 2 | I84: CHGC | J84: 46241.414 | K84: 46242 | L84: =IF(K84="","",TEXT(K84,"YYYY-MM")) -> 2026-08 | M84: closed | N84: 16 | O84: 24.47 | P84: 0 | Q84: 0 | R84: 0 | S84: Customer Contracted Reasons | T84: 2 | U84: 1 | V84: =IF(R84=0,"",IF(U84<>"",U84,Q84)) | W84: =IF(R84=0,"Not Eligible",IF(V84=1,"Met","Missed")) -> Not Eligible
A85: 7600505547 | B85: 928 | C85: Fresh Thyme #928 | D85: Westlake | E85: OH | F85: McDonald Noah | G85: US133C72 | H85: 2 | I85: MNT | J85: 46027.383 | K85: 46027 | L85: =IF(K85="","",TEXT(K85,"YYYY-MM")) -> 2026-01 | M85: closed | N85: 16 | O85: 2.6 | P85: 1 | Q85: 1 | R85: 1 | S85: Customer Contracted Reasons | T85: 2 | U85: 1 | V85: =IF(R85=0,"",IF(U85<>"",U85,Q85)) -> 1 | W85: =IF(R85=0,"Not Eligible",IF(V85=1,"Met","Missed")) -> Met
A86: 7618302591 | B86: 649 | C86: Fresh Thyme #649 | D86: Canton | E86: MI | F86: Browall Chris | G86: US133U34 | H86: 2 | I86: MNT | J86: 46205.47 | K86: 46205 | L86: =IF(K86="","",TEXT(K86,"YYYY-MM")) -> 2026-07 | M86: closed | N86: 16 | O86: 6.17 | P86: 1 | Q86: 1 | R86: 1 | S86: Customer Contracted Reasons | T86: 2 | U86: 1 | V86: =IF(R86=0,"",IF(U86<>"",U86,Q86)) -> 1 | W86: =IF(R86=0,"Not Eligible",IF(V86=1,"Met","Missed")) -> Met
A87: 7608004726 | B87: 708 | C87: Fresh Thyme #708 | D87: Kenosha | E87: WI | F87: Kelly James | G87: US153R04 | H87: 2 | I87: MNT | J87: 46102.574 | K87: 46102 | L87: =IF(K87="","",TEXT(K87,"YYYY-MM")) -> 2026-03 | M87: closed | N87: 0 | O87: 7.22 | P87: 1 | Q87: 1 | R87: 1 | S87: Customer Contracted Reasons | T87: 2 | U87: 1 | V87: =IF(R87=0,"",IF(U87<>"",U87,Q87)) -> 1 | W87: =IF(R87=0,"Not Eligible",IF(V87=1,"Met","Missed")) -> Met
A88: 7525904672 | B88: 494 | C88: Fresh Thyme #494 | D88: Saint Louis | E88: MO | F88: Welton Kira | G88: US153N60 | H88: 2 | I88: MNT | J88: 45916.522 | K88: 45916 | L88: =IF(K88="","",TEXT(K88,"YYYY-MM")) -> 2025-09 | M88: closed | N88: 16 | O88: 4.15 | P88: 1 | Q88: 1 | R88: 1 | S88: No Exception | T88: 0 | V88: =IF(R88=0,"",IF(U88<>"",U88,Q88)) -> 1 | W88: =IF(R88=0,"Not Eligible",IF(V88=1,"Met","Missed")) -> Met
A89: 7615711241 | B89: 525 | C89: Fresh Thyme #525 | D89: Indianapolis | E89: IN | F89: Qi Chuan | G89: US133E79 | H89: 2 | I89: MNT | J89: 46179.578 | K89: 46179 | L89: =IF(K89="","",TEXT(K89,"YYYY-MM")) -> 2026-06 | M89: closed | N89: 16 | O89: 3.12 | P89: 1 | Q89: 1 | R89: 1 | S89: Customer Contracted Reasons | T89: 2 | U89: 1 | V89: =IF(R89=0,"",IF(U89<>"",U89,Q89)) -> 1 | W89: =IF(R89=0,"Not Eligible",IF(V89=1,"Met","Missed")) -> Met
A90: 7612506377 | B90: 534 | C90: Fresh Thyme #534 | D90: Evansville | E90: IN | F90: Williams Timothy | G90: US133E40 | H90: 2 | I90: MNT | J90: 46147.419 | K90: 46147 | L90: =IF(K90="","",TEXT(K90,"YYYY-MM")) -> 2026-05 | M90: closed | N90: 0 | O90: 5.2 | P90: 1 | Q90: 1 | R90: 1 | S90: Customer Contracted Reasons | T90: 2 | U90: 1 | V90: =IF(R90=0,"",IF(U90<>"",U90,Q90)) -> 1 | W90: =IF(R90=0,"Not Eligible",IF(V90=1,"Met","Missed")) -> Met
A91: 7611702338 | B91: 563 | C91: Fresh Thyme #563 | D91: Rochester | E91: MN | F91: James Ire | G91: US153R10 | H91: 1 | I91: MNT | J91: 46139.409 | K91: 46139 | L91: =IF(K91="","",TEXT(K91,"YYYY-MM")) -> 2026-04 | M91: closed | N91: 12 | O91: 4.33 | P91: 1 | Q91: 1 | R91: 1 | S91: Customer Contracted Reasons | T91: 2 | U91: 1 | V91: =IF(R91=0,"",IF(U91<>"",U91,Q91)) -> 1 | W91: =IF(R91=0,"Not Eligible",IF(V91=1,"Met","Missed")) -> Met
A92: 7607202680 | B92: 497 | C92: Fresh Thyme #497 | D92: Pleasant Hills | E92: PA | F92: Blain Simon | G92: US133A17 | H92: 2 | I92: MNT | J92: 46094.545 | K92: 46097 | L92: =IF(K92="","",TEXT(K92,"YYYY-MM")) -> 2026-03 | M92: closed | N92: 0 | O92: 67.78 | P92: 1 | Q92: 1 | R92: 1 | S92: Customer Contracted Reasons | T92: 1 | V92: =IF(R92=0,"",IF(U92<>"",U92,Q92)) -> 1 | W92: =IF(R92=0,"Not Eligible",IF(V92=1,"Met","Missed")) -> Met
A93: 7604005123 | B93: 493 | C93: Fresh Thyme #493 | D93: O Fallon | E93: MO | F93: Miller Michael | G93: US153N91 | H93: 2 | I93: MNT | J93: 46062.439 | K93: 46062 | L93: =IF(K93="","",TEXT(K93,"YYYY-MM")) -> 2026-02 | M93: closed | N93: 0 | O93: 4.63 | P93: 1 | Q93: 1 | R93: 1 | S93: Customer Contracted Reasons | T93: 2 | U93: 1 | V93: =IF(R93=0,"",IF(U93<>"",U93,Q93)) -> 1 | W93: =IF(R93=0,"Not Eligible",IF(V93=1,"Met","Missed")) -> Met
A94: 7602703663 | B94: 715 | C94: Fresh Thyme #715 | D94: Ashwaubenon | E94: WI | F94: August Ronald | G94: US153C07 | H94: 2 | I94: MNT | J94: 46049.354 | K94: 46051 | L94: =IF(K94="","",TEXT(K94,"YYYY-MM")) -> 2026-01 | M94: closed | N94: 16 | O94: 53.25 | P94: 0 | Q94: 0 | R94: 1 | S94: Customer Contracted Reasons | T94: 1 | V94: =IF(R94=0,"",IF(U94<>"",U94,Q94)) -> 0 | W94: =IF(R94=0,"Not Eligible",IF(V94=1,"Met","Missed")) -> Missed
A95: 7607100040 | B95: 634 | C95: Fresh Thyme #634 | D95: Joliet | E95: IL | F95: Reed Austin | G95: US153C27 | H95: 2 | I95: MNT | J95: 46093.591 | K95: 46093 | L95: =IF(K95="","",TEXT(K95,"YYYY-MM")) -> 2026-03 | M95: closed | N95: 0 | O95: 5.3 | P95: 1 | Q95: 1 | R95: 1 | S95: Customer Contracted Reasons | T95: 2 | U95: 1 | V95: =IF(R95=0,"",IF(U95<>"",U95,Q95)) -> 1 | W95: =IF(R95=0,"Not Eligible",IF(V95=1,"Met","Missed")) -> Met
A96: 7605704708 | B96: 707 | C96: Fresh Thyme #707 | D96: Brookfield | E96: WI | F96: Kelly James | G96: US153R04 | H96: 2 | I96: MNT | J96: 46079.619 | K96: 46079 | L96: =IF(K96="","",TEXT(K96,"YYYY-MM")) -> 2026-02 | M96: closed | N96: 0 | O96: 4.3 | P96: 1 | Q96: 1 | R96: 1 | S96: Customer Contracted Reasons | T96: 2 | U96: 1 | V96: =IF(R96=0,"",IF(U96<>"",U96,Q96)) -> 1 | W96: =IF(R96=0,"Not Eligible",IF(V96=1,"Met","Missed")) -> Met
A97: 7607504786 | B97: 562 | C97: Fresh Thyme #562 | D97: Waite Park | E97: MN | F97: Nelson Tony | G97: US153R80 | H97: 1 | I97: MNT | J97: 46097.789 | K97: 46098 | L97: =IF(K97="","",TEXT(K97,"YYYY-MM")) -> 2026-03 | M97: closed | N97: 12 | O97: 16.95 | P97: 1 | Q97: 1 | R97: 1 | S97: Customer Contracted Reasons | T97: 2 | U97: 1 | V97: =IF(R97=0,"",IF(U97<>"",U97,Q97)) -> 1 | W97: =IF(R97=0,"Not Eligible",IF(V97=1,"Met","Missed")) -> Met
A98: 7606400046 | B98: 494 | C98: Fresh Thyme #494 | D98: Saint Louis | E98: MO | F98: Patton Alfred | G98: US153N64 | H98: 1 | I98: MNT | J98: 46086.552 | K98: 46086 | L98: =IF(K98="","",TEXT(K98,"YYYY-MM")) -> 2026-03 | M98: closed | N98: 0 | O98: 5.53 | P98: 1 | Q98: 1 | R98: 1 | S98: Customer Contracted Reasons | T98: 2 | U98: 1 | V98: =IF(R98=0,"",IF(U98<>"",U98,Q98)) -> 1 | W98: =IF(R98=0,"Not Eligible",IF(V98=1,"Met","Missed")) -> Met
A99: 7605302048 | B99: 643 | C99: Fresh Thyme #643 | D99: Troy | E99: MI | F99: Browall Chris | G99: US133U34 | H99: 2 | I99: CHGC | J99: 46075.386 | K99: 46076 | L99: =IF(K99="","",TEXT(K99,"YYYY-MM")) -> 2026-02 | M99: closed | N99: 0 | O99: 29.27 | P99: 1 | Q99: 1 | R99: 1 | S99: Customer Contracted Reasons | T99: 1 | V99: =IF(R99=0,"",IF(U99<>"",U99,Q99)) -> 1 | W99: =IF(R99=0,"Not Eligible",IF(V99=1,"Met","Missed")) -> Met
A100: 7618302295 | B100: 931 | C100: Fresh Thyme #931 | D100: North Canton | E100: OH | F100: Workman Truman | G100: US133C48 | H100: 2 | I100: MNT | J100: 46205.402 | K100: 46208 | L100: =IF(K100="","",TEXT(K100,"YYYY-MM")) -> 2026-07 | M100: closed | N100: 16 | O100: 73.8 | P100: 0 | Q100: 0 | R100: 1 | S100: Customer Contracted Reasons | T100: 0 | U100: 0 | V100: =IF(R100=0,"",IF(U100<>"",U100,Q100)) -> 0 | W100: =IF(R100=0,"Not Eligible",IF(V100=1,"Met","Missed")) -> Missed
...

Sheet 01_RAW_DATA
A1: Instance Identifier | B1: Service Request Number | C1: Area of Failure Code | D1: Area of Failure Description | E1: Area Name | F1: Service Request Arrival to Closure Duration (Hours) | G1: As Of Date Time (LTZ) | H1: As Of Date Time (UTC) | I1: Service Request Assign to Dispatch Duration (Hours) | J1: Best Fit PID Identifier | K1: Best Fit PID Description | L1: Best Fit Item Instance Number | M1: Best Fit Serial Number | N1: Branch Code | O1: Caller Name | P1: Failure Cause Description | Q1: Failure Cause Code | R1: Customer Engineer Arrival Date Time (LTZ) | S1: Customer Engineer Arrival Date Time (UTC) | T1: Customer Engineer Global Identifier | U1: Cash in Transit Supplier Code | V1: Account Site City Name | W1: Service Request Closed Date | X1: Service Request Closed Date Time (LTZ) | Y1: Service Request Closed Date Time (UTC) | Z1: Service Request Comment Text | AA1: Contractor Indicator | AB1: Account Site Country Code | AC1: Account Site Country Name | AD1: PID Service Coverage Code | AE1: PID Service Coverage Name | AF1: Service Coverage Indicator | AG1: Current NAICS Code | AH1: Current NAICS Description | AI1: Account Industry Code | AJ1: Account Industry Name | AK1: Customer Engineer Code | AL1: Customer Engineer Quicklook Identifier | AM1: Account Site Name | AN1: Account Name | AO1: Account Number | AP1: Account Site Store Number | AQ1: Cash Deposit Module Name | AR1: Service Request Dispatch to Arrival Duration (Hours) | AS1: Cash Dispenser Module Name | AT1: Entered By System Code | AU1: Entered Date Time (LTZ) | AV1: Entered Date Time (UTC) | AW1: Environmental Code | AX1: Environmental Code Description | AY1: Source System Code | AZ1: Field Customer Engineer Code | BA1: Field Customer Engineer Name | BB1: Fill From Emergency Stocking Location Indicator | BC1: Fill From Non Emergency Stocking Location Indicator | BD1: Fill From Personal Parts Kit Indicatior | BE1: Final Serial Number | BF1: First Operation Elapsed Duration (Hours) | BG1: Next Business Day Applied Indicator | BH1: Next Business Day Date Time (LTZ) | BI1: Next Business Day Resolve Applied Indicator | BJ1: Next Business Day Resolve Date Time (LTZ) | BK1: Customer Engineer Onsite Indicator | BL1: Service Activity Code Labor Indicator | BM1: Hand Held Device Indicator | BN1: Original Service Request Type Code | BO1: Item Instance Number | BP1: Last Updated Date Time (UTC) | BQ1: Account Site Latitude Number | BR1: Account Site Number | BS1: Account Site Longitude Number | BT1: Mitigated Indicator | BU1: Mitigated Date Time (UTC) | BV1: Mitigated Model Code | BW1: Mitigated PID Class Code | BX1: Mitigated PID Identifier | BY1: Mitigated Resolve Limit Duration (Minutes) | BZ1: Mitigated Resolve Set Indicator | CA1: Mitigated Resolve Duration (Minutes) | CB1: Mitigated Response Limit Duration (Minutes) | CC1: Mitigated Response Set Indicator | CD1: Mitigated Response Duration (Minutes) | CE1: Mitigated Service Level Agreement Resolve Met Indicator | CF1: Mitigated Service Level Agreement Response Met Indicator | CG1: Mitigated Global Service Request Type Code | CH1: Mitigated Sub Model Code | CI1: Mitigation Reason Code | CJ1: Mitigation Reason Description | CK1: Mitigation Sub Category Level 1 Code | CL1: Mitigation Sub Category Level 2 Code | CM1: PID Model Code | CN1: Not Scanned Reason Name | CO1: PID Class Code | CP1: Onsite Labor Duration (Hours) | CQ1: Onsite Repair Duration (Hours) | CR1: Travel To Duration (Hours) | CS1: Open to Assign Duration (Hours) | CT1: Service Request Ordered Date Time (UTC) | CU1: Service Request Ordered Date Time (LTZ) | CV1: Original PID Identifier | CW1: Original PID Description | CX1: Original Serial Number | CY1: Parts Ordered Indicator | CZ1: Parts Used Indicator | DA1: PID Unformatted Identifier | DB1: Equipment Placement Location Name | DC1: Account Site Postal Code | DD1: Principal Period of Maintenance Duration (Hours) | DE1: Predictive Code | DF1: Problem Code | DG1: Product Family Name | DH1: Product Industry Name | DI1: PID Identifier | DJ1: Product Reference Code | DK1: Mitigation Quicklook Idenifier | DL1: Region Name | DM1: Remote Activity Only Indicator | DN1: Remote Labor Duration (Hours) | DO1: Repair Code | DP1: Repair Description | DQ1: Resolve Limit Duration (Hours) | DR1: Resolve Net Duration (Hours) | DS1: Resolve Duration (Hours) | DT1: Elapsed Response Duration (Hours) | DU1: Response Limit Duration (Hours) | DV1: Reviewed Indicator | DW1: Reporting Service Request Severity Code | DX1: Reporting Service Request Type Code | DY1: Serial Number | DZ1: Service Level Agreement Resolve Met Indicator | EA1: Service Level Agreement Resolve Met Net Indicator | EB1: Service Level Agreement Resolve Opportunity Indicator | EC1: Service Level Agreement Response Met Indicator | ED1: Service Level Agreement Response Met Net Indicator | EE1: Service Level Agreement Response Opportunity Indicator | EF1: Serial Number Update Method Name | EG1: Service Request Status Name | EH1: Global Service Request Type Code | EI1: Local Service Request Type Code | EJ1: Account Site State Name | EK1: PID Sub Model Code | EL1: Suspended For Parts Indicator | EM1: Territory Code | EN1: Travel Duration (Hours) | EO1: Total Time To Resolve Duration (Hours) | EP1: UNSPSC Code | EQ1: UNSPSC Description | ER1: UNSPSC Hierarchy 1 Code | ES1: UNSPSC Hierarchy 1 Description | ET1: UNSPSC Hierarchy 2 Code | EU1: UNSPSC Hierarchy 2 Description | EV1: Update Method Name | EW1: US Area Name | EX1: US Branch Code | EY1: US Territory Code | EZ1: US National Service Area Name | FA1: US National Service Area Tier Code | FB1: Service Request Valid for Time Calculations Indicator | FC1: Customer Engineer Visit Count | FD1: Service Request Closed Week Ending Date | FE1: Service Request Closed Year Month | FF1: Last Note Line Number | FG1: Note Max1 Description | FH1: Note Max1 Date Time(LTZ) | FI1: Note Max1 Indicator | FJ1: Note Max2 Description | FK1: Note Max2 Date Time(LTZ) | FL1: Note Max2 Indicator | FM1: Note Max3 Description | FN1: Note Max3 Date Time(LTZ) | FO1: Note Max3 Indicator | FP1: Note Min1 Description | FQ1: Note Min1 Date Time(LTZ) | FR1: Note Min1 Indicator | FS1: Note Min2 Description | FT1: Note Min2 Date Time(LTZ) | FU1: Note Min2 Indicator | FV1: Note Min3 Description | FW1: Note Min3 Date Time(LTZ) | FX1: Note Min3 Indicator | FY1: Note Status Description | FZ1: All Notes Description | GA1: Note Max1 Resolution Description | GB1: Note Max1 Resolution Indicator | GC1: Note Max2 Resolution Description | GD1: Note Max2 Resolution Indicator | GE1: Note Max3 Resolution Description | GF1: Note Max3 Resolution Indicator | GG1: Note Resolution Indicator | GH1: Note Type Resolution Code | GI1: Note Type Resolution Description | GJ1: Note Max1 Resolution Date Time(LTZ) | GK1: Note Max2 Resolution Date Time(LTZ) | GL1: Note Max3 Resolution Date Time(LTZ) | GM1: First Visit Resolution (Opportunity) | GN1: First Visit Resolution (Miss or Met) | GO1: 3 Day revisit (Fail) | GP1: 3 Day revisit (Opportunity) | GQ1: 3 Day AOF revisit (Opportunity) | GR1: 3 Day AOF revisit (Fail) | GS1: 14 Day revisit (Opportunity) | GT1: 14 Day revisit (Fail) | GU1: 14 Day AOF revisit (Opportunity) | GV1: 14 Day AOF revisit (Fail) | GW1: 7 Day revisit (Opportunity) | GX1: 7 Day revisit (Fail) | GY1: 7 Day AOF revisit (Opportunity) | GZ1: 7 Day AOF revisit (Fail) | HA1: Ce Code Final | HB1: Region Demand | HC1: Area Demand | HD1: Country Demand | HE1: Branch Demand | HF1: Territory Demand | HG1: Region Workforce | HH1: Area Workforce | HI1: Country Workforce | HJ1: Branch Workforce | HK1: Territory Workforce | HL1: SVC City Name | HM1: Contract Customer Name | HN1: Contract Customer Number | HO1: Exclude | HP1: SVC State Name | HQ1: Transaction Company Owner Name | HR1: Transaction Business Tag Name | HS1: Environment Tag Name | HU1: Verbatim export from Fresh_Thyme_Year_to_Date_08_01_2025.xlsx. Do not edit — this tab preserves source fidelity for audit/reconciliation.
A2: 8702 | B2: 7526314205 | C2: 8P | D2: COIN RECYCLER | E2: US West | F2: 1 | G2: 2025-09-21T00:50:30.000Z | H2: 2025-09-21T00:50:30.000Z | I2: 0 | J2: 7360-4010-9090 | K2: SSCO R6C Full Function, No Bag, XR7 Plus | L2: 152946661 | M2: 57-60587817 | N2: US153 | O2: AUTOMATIC | P2: COIN_RECYCLER | Q2: 8PCV | R2: 2025-09-20T18:24:00.000Z | S2: 2025-09-20T23:24:00.000Z | T2: 41477124076 | V2: WEST DES MOINES | W2: 45920 | X2: 2025-09-20T19:36:00.000Z | Y2: 2025-09-21T00:36:00.000Z | AA2: 0 | AB2: US | AC2: UNITED STATES | AD2: 7820C4ES | AE2: 7 days,8am to 8pm, 4hrs Resp,12 hrs Resol | AF2: 1 | AG2: 452210 | AH2: Department Stores | AI2: RET | AJ2: Retail | AK2: US153R46 | AL2: JG185443 | AM2: MEIJER/FRESH THYME #962 | AN2: MEIJER INC | AO2: 36805 | AP2: 962 | AQ2: No Intelligent Deposit | AR2: 66123023 | AS2: S1 | AU2: 2025-09-20T13:46:14.000Z | AV2: 2025-09-20T18:46:14.000Z | AW2: 19KR | AX2: 19KR-ATM OPERATING AS EXPECTED ON ARRIVAL | AY2: ES | AZ2: US153R46 | BA2: Green Jason | BB2: 0 | BC2: 0 | BD2: 0 | BE2: 57-60587817 | BF2: 0 | BG2: 0 | BH2: 1900-01-01T00:00:00.000Z | BI2: 0 | BJ2: 1900-01-01T00:00:00.000Z | BK2: 1 | BL2: 0 | BM2: 0 | BN2: MNT | BO2: 152946661 | BP2: 2025-09-21T00:50:30.000Z | BR2: 42793657 | BT2: 0 | CM2: 4010 | CO2: 7360 | CP2: 1.2 | CQ2: 1.2 | CR2: 0.4167 | CS2: 4 | CT2: 2025-09-20T18:46:17.000Z | CU2: 2025-09-20T13:46:17.000Z | CV2: 7360-4010-9090 | CW2: SSCO R6C Full Function, No Bag, XR7 Plus | CX2: 57-60587817 | CY2: 0 | CZ2: 0 | DA2: 7360-4010-9090 | DB2: TTW WU | DC2: 50266 | DD2: 5.8333 | DE2: REACTIVE | DG2: Fastlane | DH2: Retail | DI2: 7244-0930-9898 | DL2: WCS - North America | DM2: 0 | DN2: 0 | DO2: 2 | DP2: ADJUST/CALIBRATE | DQ2: 16 | DR2: 350 | DS2: 350 | DT2: 4.6333 | DU2: 4 | DW2: 2 | DX2: CHGC | DY2: 57-60587817 | DZ2: 0 | EA2: 0 | EB2: 0 | EC2: 0 | ED2: 0 | EE2: 0 | EF2: Manual | EG2: closed | EH2: CHGC 2 | EI2: CHGC 2 | EJ2: IA | EK2: 9090 | EL2: 0 | EM2: US153R | EN2: 0.4167 | EO2: 5.8333333 | EP2: 99991120 | EQ2: Self check out | ER2: HW | ES2: Hardware | ET2: SCO | EU2: SCO | EV2: Manual | EX2: US153 | EY2: US153R | EZ2: Des Moines IA | FA2: C | FB2: 1 | FC2: 1 | FD2: 45920 | FE2: 2025/9 | FF2: 5 | FI2: 0 | FJ2: no fault found. checked everything including pml and no error codes. | FK2: 2025-09-20T19:36:47.000Z | FL2: 1 | FM2: New Item :7360-4010-9090 New Serial Number :57-60587817 Old Item :7360-4010-9090 Old Serial Number :57-60587817 | FN2: 2025-09-20T19:36:49.000Z | FO2: 1 | FP2: SCO11 has a Debris Flap Stuck error (Error code; 16-6-0--99-131844 ) This is a reoccuring issue. Last time NCR was on site for same issue and said may need replacement part [Generated by Portal Login: most14 Contact: Staci Mowder 3096133038 ftfmsupport@rdspos.com] | FQ2: 2025-09-20T13:46:18.000Z | FR2: 1 | FS2: CE IS NOW US153R46 | FT2: 2025-09-20T13:50:11.000Z | FU2: 1 | FV2: No fault found. Checked everything including PML and no error codes. | FW2: 2025-09-20T19:36:47.000Z | FX2: 1 | FY2: E | FZ2: SCO11 has a Debris Flap Stuck error (Error code; 16-6-0--99-131844 ) This is a reoccuring issue. Last time NCR was on site for same issue and said may need replacement part [Generated by Portal Login: most14 Contact: Staci Mowder 3096133038 ftfmsupport@rdspos.com]-CE IS NOW US153R46-No fault found. Checked everything including PML and no error codes.-no fault found. checked everything including pml and no error codes.-New Item :7360-4010-9090 New Serial Number :57-60587817 Old Item :7360-4010-9090 Old Serial Number :57-60587817 | GA2: no fault found. checked everything including pml and no error codes. | GB2: 1 | GD2: 0 | GF2: 0 | GG2: 1 | GH2: CS_RESOLUTION | GI2: Resolution Description | GJ2: 2025-09-20T19:36:47.000Z | GM2: 1 | GN2: 1 | GO2: 0 | GP2: 1 | GQ2: 1 | GR2: 0 | GS2: 1 | GT2: 0 | GU2: 1 | GV2: 0 | GW2: 1 | GX2: 0 | GY2: 1 | GZ2: 0 | HA2: US153R46 | HB2: NAMER | HC2: NAMER West | HD2: US | HE2: US153 | HF2: US153R | HG2: NAMER | HH2: NAMER West | HI2: US | HJ2: US153 | HK2: US153R | HL2: WEST DES MOINES | HM2: MEIJER INC | HN2: 36805 | HP2: IA | HQ2: NCR | HR2: NCR | HS2: NCR
A3: 8702 | B3: 7621502464 | C3: 8P | D3: COIN RECYCLER | E3: US Southeast | F3: 1 | G3: 2026-08-03T13:36:37.000Z | H3: 2026-08-03T13:36:37.000Z | I3: 0 | J3: 7360-4010-9090 | K3: SSCO R6C Full Function, No Bag, XR7 Plus | L3: 155403173 | M3: 57-60591637 | N3: US133 | O3: AUTOMATIC | P3: COIN_RECYCLER | Q3: 8PCZ | R3: 2026-08-03T08:36:00.000Z | S3: 2026-08-03T12:36:00.000Z | T3: 41477095563 | V3: GRAND RAPIDS | W3: 46237 | X3: 2026-08-03T09:25:00.000Z | Y3: 2026-08-03T13:25:00.000Z | AA3: 0 | AB3: US | AC3: UNITED STATES | AD3: 7820C4W2 | AE3: 7 days/w, 08 AM-8 PM, 4 HR, Response,12 HR. Resolv | AF3: 1 | AG3: 452210 | AH3: Department Stores | AI3: RET | AJ3: Retail | AK3: US133B47 | AL3: BW185129 | AM3: Meijer/Fresh Thyme #606 | AN3: MEIJER INC | AO3: 36805 | AP3: 606 | AQ3: No Intelligent Deposit | AR3: 66578915 | AS3: S1 | AU3: 2026-08-02T22:00:40.000Z | AV3: 2026-08-03T02:00:40.000Z | AX3: Undefined | AY3: ES | AZ3: US133B47 | BA3: Willea Brandon | BB3: 0 | BC3: 0 | BD3: 0 | BE3: 57-60591637 | BF3: 0 | BG3: 0 | BH3: 1900-01-01T00:00:00.000Z | BI3: 0 | BJ3: 1900-01-01T00:00:00.000Z | BK3: 1 | BL3: 1 | BM3: 0 | BN3: MNT | BO3: 155403173 | BP3: 2026-08-03T13:36:37.000Z | BQ3: 42.926002 | BR3: 42810759 | BS3: -85.605987 | BT3: 2 | BU3: 2026-08-11T13:33:58.000Z | BY3: 16 | CA3: 1 | CE3: 1 | CI3: 11 | CJ3: Customer Contracted Reasons | CM3: 4010 | CO3: 7360 | CP3: 0.8167 | CQ3: 0.8167 | CR3: 0.6167 | CS3: 45 | CT3: 2026-08-03T02:00:42.000Z | CU3: 2026-08-02T22:00:42.000Z | CV3: 7360-4010-9090 | CW3: SSCO R6C Full Function, No Bag, XR7 Plus | CX3: 57-60591637 | CY3: 0 | CZ3: 0 | DA3: 7360-4010-9090 | DB3: TTW WU | DC3: 49546 | DD3: 1.4167 | DE3: REACTIVE | DG3: Fastlane | DH3: Retail | DI3: G554-0312-0000 | DK3: ft185038 | DL3: WCS - North America | DM3: 0 | DN3: 0 | DO3: 3 | DP3: CLEAR MEDIA/DEBRIS | DQ3: 16 | DR3: 85 | DS3: 685 | DT3: 0.6 | DU3: 4 | DV3: 1 | DW3: 2 | DX3: MNT | DY3: 57-60591637 | DZ3: 1 | EA3: 1 | EB3: 1 | EC3: 1 | ED3: 1 | EE3: 1 | EF3: Scanned | EG3: closed | EH3: MNT 2 | EI3: MNT 2 | EJ3: MI | EK3: 9090 | EL3: 0 | EM3: US133B | EN3: 0.6167 | EO3: 11.416667 | EP3: 99991120 | EQ3: Self check out | ER3: HW | ES3: Hardware | ET3: SCO | EU3: SCO | EV3: Scanned | EX3: US133 | EY3: US133A | EZ3: Grand Rapids MI | FA3: B | FB3: 1 | FC3: 1 | FD3: 46242 | FE3: 2026/8 | FF3: 4 | FI3: 0 | FL3: 0 | FM3: New Item :7360-4010-9090 New Serial Number :57-60591637 Old Item :7360-4010-9090 Old Serial Number :57-60591646 | FN3: 2026-08-03T09:25:42.000Z | FO3: 1 | FP3: SCO12 has a Coin recycler error-Coin box motor jammed error [Generated by Portal Login: most14 Contact: Staci Mowder 2694689716 FTFMSupport@rdspos.com] | FQ3: 2026-08-02T22:00:42.000Z | FR3: 1 | FS3: CE IS NOW US133B47 | FT3: 2026-08-02T22:45:06.000Z | FU3: 1 | FV3: coin recycler in error, acb jammed. cleared jam and tested working | FW3: 2026-08-03T09:25:39.000Z | FX3: 1 | FY3: E | FZ3: SCO12 has a Coin recycler error-Coin box motor jammed error [Generated by Portal Login: most14 Contact: Staci Mowder 2694689716 FTFMSupport@rdspos.com]-CE IS NOW US133B47-coin recycler in error, acb jammed. cleared jam and tested working-New Item :7360-4010-9090 New Serial Number :57-60591637 Old Item :7360-4010-9090 Old Serial Number :57-60591646 | GA3: coin recycler in error, acb jammed. cleared jam and tested working | GB3: 1 | GD3: 0 | GF3: 0 | GG3: 1 | GH3: CS_RESOLUTION | GI3: Resolution Description | GJ3: 2026-08-03T09:25:39.000Z | GM3: 1 | GN3: 1 | GO3: 0 | GP3: 1 | GQ3: 1 | GR3: 0 | GS3: 1 | GT3: 0 | GU3: 1 | GV3: 0 | GW3: 1 | GX3: 0 | GY3: 1 | GZ3: 0 | HA3: US133B47 | HB3: NAMER | HC3: NAMER South | HD3: US | HE3: US133 | HF3: US133A | HG3: NAMER | HH3: NAMER South | HI3: US | HJ3: US133 | HK3: US133B | HL3: GRAND RAPIDS | HM3: MEIJER INC | HN3: 36805 | HP3: MI | HQ3: NCR | HR3: NCR | HS3: NCR
A4: 8702 | B4: 7534505738 | C4: NR | D4: NOTE RECYCLER | E4: US Southeast | F4: 0 | G4: 2025-12-11T18:58:52.000Z | H4: 2025-12-11T18:58:52.000Z | I4: 0 | J4: 7360-4010-9090 | K4: SSCO R6C Full Function, No Bag, XR7 Plus | L4: 153406439 | M4: 57-60591378 | N4: US133 | O4: AUTOMATIC | P4: NOTE_RECYCLER | Q4: NRQG | R4: 2025-12-11T13:13:00.000Z | S4: 2025-12-11T18:13:00.000Z | T4: 41477014545 | V4: Troy | W4: 46002 | X4: 2025-12-11T13:43:00.000Z | Y4: 2025-12-11T18:43:00.000Z | AA4: 0 | AB4: US | AC4: UNITED STATES | AD4: 7820C4ES | AE4: 7 days,8am to 8pm, 4hrs Resp,12 hrs Resol | AF4: 1 | AG4: 452210 | AH4: Department Stores | AI4: RET | AJ4: Retail | AK4: US133U38 | AL4: MR250470 | AM4: MEIJER/FRESH THYME #643 | AN4: MEIJER INC | AO4: 36805 | AP4: 643 | AQ4: No Intelligent Deposit | AR4: 66240792 | AS4: S1 | AU4: 2025-12-11T11:53:08.000Z | AV4: 2025-12-11T16:53:08.000Z | AW4: 19NR | AX4: 19NR-OTHER ISSUES BEYOND THOSE THAT HAVE ALREADY BEEN CHARACTERIZED | AY4: ES | AZ4: US133U38 | BA4: Richie Mark | BB4: 0 | BC4: 0 | BD4: 0 | BE4: 57-60591378 | BF4: 0 | BG4: 0 | BH4: 1900-01-01T00:00:00.000Z | BI4: 0 | BJ4: 1900-01-01T00:00:00.000Z | BK4: 1 | BL4: 0 | BM4: 0 | BN4: MNT | BO4: 153406439 | BP4: 2025-12-11T18:58:52.000Z | BQ4: 42.564008 | BR4: 42791774 | BS4: -83.130439 | BT4: 0 | CM4: 4010 | CO4: 7360 | CP4: 0.5 | CQ4: 0.5 | CR4: 1.0667 | CS4: 8 | CT4: 2025-12-11T16:53:08.000Z | CU4: 2025-12-11T11:53:08.000Z | CV4: 7360-4010-9090 | CW4: SSCO R6C Full Function, No Bag, XR7 Plus | CX4: 57-60591378 | CY4: 0 | CZ4: 0 | DA4: 7360-4010-9090 | DB4: TTW WU | DC4: 48083 | DD4: 1.8333 | DE4: REACTIVE | DG4: Fastlane | DH4: Retail | DL4: WCS - North America | DM4: 0 | DN4: 0 | DO4: 3 | DP4: CLEAR MEDIA/DEBRIS | DQ4: 16 | DR4: 110 | DS4: 110 | DT4: 1.3333 | DU4: 4 | DW4: 2 | DX4: CHGC | DY4: 57-60591378 | DZ4: 0 | EA4: 0 | EB4: 0 | EC4: 0 | ED4: 0 | EE4: 0 | EF4: Scanned | EG4: closed | EH4: CHGC 2 | EI4: CHGC 2 | EJ4: MI | EK4: 9090 | EL4: 0 | EM4: US133U | EN4: 1.0667 | EO4: 1.8333333 | EP4: 99991120 | EQ4: Self check out | ER4: HW | ES4: Hardware | ET4: SCO | EU4: SCO | EV4: Scanned | EX4: US113 | EY4: US113V | EZ4: Detroit MI | FA4: A | FB4: 1 | FC4: 1 | FD4: 46004 | FE4: 2025/12 | FF4: 7 | FG4: There was a $5 billion stuck behind the second recycler, I carefully was able to remove the $5 bill. Put it in the cash box went into ADD ran tests were fine.Put back in service job complete. | FH4: 2025-12-11T13:44:03.000Z | FI4: 1 | FJ4: There was a $5 billion stuck behind the second recycler, I carefully was able to remove the $5 bill. Put it in the cash box went into ADD ran tests were fine.Put back in service job complete. | FK4: 2025-12-11T13:44:03.000Z | FL4: 1 | FM4: New Item :7360-4010-9090 New Serial Number :57-60591378 Old Item :7360-4010-9090 Old Serial Number :57-60591364 | FN4: 2025-12-11T13:44:05.000Z | FO4: 1 | FP4: Booted up with Note recycler error, note jammed at RNCK2 sensor, Error code: 15-9-0-5-63010 [Generated by Portal Login: coas14 Contact: Ashley 309-213-1564 ftfmsupport@rdspos.com] | FQ4: 2025-12-11T11:53:09.000Z | FR4: 1 | FS4: CE IS NOW US133U34 | FT4: 2025-12-11T12:01:09.000Z | FU4: 1 | FV4: CE WAS US133U34 | FW4: 2025-12-11T12:06:36.000Z | FX4: 1 | FY4: E | FZ4: Booted up with Note recycler error, note jammed at RNCK2 sensor, Error code: 15-9-0-5-63010 [Generated by Portal Login: coas14 Contact: Ashley 309-213-1564 ftfmsupport@rdspos.com]-CE IS NOW US133U34-CE WAS US133U34-CE IS NOW US133U38-There was a $5 billion stuck behind the second recycler, I carefully was able to remove the $5 bill. Put it in the cash box went into ADD ran tests were fine.Put back in service job complete.-There was a $5 billion stuck behind the second recycler, I carefully was able to remove the $5 bill. Put it in the cash box went into ADD ran tests were fine.Put back in service job complete.-New Item :7360-4010-9090 New Serial Number :57-60591378 Old Item :7360-4010-9090 Old Serial Number :57-60591364 | GA4: There was a $5 billion stuck behind the second recycler, I carefully was able to remove the $5 bill. Put it in the cash box went into ADD ran tests were fine.Put back in service job complete. | GB4: 1 | GD4: 0 | GF4: 0 | GG4: 1 | GH4: CS_RESOLUTION | GI4: Resolution Description | GJ4: 2025-12-11T13:44:03.000Z | GM4: 1 | GN4: 1 | GO4: 0 | GP4: 1 | GQ4: 1 | GR4: 0 | GS4: 1 | GT4: 0 | GU4: 1 | GV4: 0 | GW4: 1 | GX4: 0 | GY4: 1 | GZ4: 0 | HA4: US133U38 | HB4: NAMER | HC4: NAMER South | HD4: US | HE4: US133 | HF4: US133A | HG4: NAMER | HH4: NAMER South | HI4: US | HJ4: US133 | HK4: US133U | HL4: Troy | HM4: MEIJER INC | HN4: 36805 | HP4: MI | HQ4: NCR | HR4: NCR | HS4: NCR
A5: 8702 | B5: 7521807604 | C5: 82 | D5: SCANNER/SCAN-SCALE | E5: US Southeast | F5: 0 | G5: 2025-08-06T19:59:18.000Z | H5: 2025-08-06T19:59:18.000Z | I5: 0 | J5: 7360-4010-9090 | K5: SSCO R6C Full Function, No Bag, XR7 Plus | L5: 156046215 | M5: 57-60595316 | N5: US133 | O5: AUTOMATIC | P5: SCALE | Q5: 82SL | R5: 2025-08-06T15:27:00.000Z | S5: 2025-08-06T19:27:00.000Z | T5: 41477119633 | V5: Portage | W5: 45875 | X5: 2025-08-06T15:31:00.000Z | Y5: 2025-08-06T19:31:00.000Z | AA5: 0 | AB5: US | AC5: UNITED STATES | AD5: 7820C4ES | AE5: 7 days,8am to 8pm, 4hrs Resp,12 hrs Resol | AF5: 1 | AG5: 452210 | AH5: Department Stores | AI5: RET | AJ5: Retail | AK5: US133B52 | AL5: CS185400 | AM5: MEIJER/FRESH THYME #647 | AN5: MEIJER INC | AO5: 36805 | AP5: 647 | AQ5: No Intelligent Deposit | AR5: 66058046 | AS5: S1 | AU5: 2025-08-06T14:43:48.000Z | AV5: 2025-08-06T18:43:48.000Z | AW5: 19N2 | AX5: 19N2-DEPOSIT OR DISPENSER CASSETTE BROKEN OR DAMAGE | AY5: ES | AZ5: US133B52 | BA5: Shell Caleb | BB5: 0 | BC5: 0 | BD5: 0 | BE5: 57-60595316 | BF5: 0 | BG5: 0 | BH5: 1900-01-01T00:00:00.000Z | BI5: 0 | BJ5: 1900-01-01T00:00:00.000Z | BK5: 1 | BL5: 0 | BM5: 0 | BN5: MNT | BO5: 156046215 | BP5: 2025-08-06T19:59:18.000Z | BR5: 42791779 | BT5: 0 | CM5: 4010 | CO5: 7360 | CP5: 0.0667 | CQ5: 0.0667 | CR5: 0.6667 | CS5: 1 | CT5: 2025-08-06T18:43:48.000Z | CU5: 2025-08-06T14:43:48.000Z | CV5: 7360-4010-9090 | CW5: SSCO R6C Full Function, No Bag, XR7 Plus | CX5: 57-60595316 | CY5: 0 | CZ5: 0 | DA5: 7360-4010-9090 | DB5: TTW WU | DC5: 49002 | DD5: 0.8 | DE5: REACTIVE | DG5: Fastlane | DH5: Retail | DI5: G370-3975-0000 | DL5: WCS - North America | DM5: 0 | DN5: 0 | DO5: 1 | DP5: CLEANED | DQ5: 16 | DR5: 48 | DS5: 48 | DT5: 0.7333 | DU5: 4 | DW5: 2 | DX5: CHGC | DY5: 57-60595316 | DZ5: 0 | EA5: 0 | EB5: 0 | EC5: 0 | ED5: 0 | EE5: 0 | EF5: Manual | EG5: closed | EH5: CHGC 2 | EI5: CHGC 2 | EJ5: MI | EK5: 9090 | EL5: 0 | EM5: US133B | EN5: 0.6667 | EO5: 0.8 | EP5: 99991120 | EQ5: Self check out | ER5: HW | ES5: Hardware | ET5: SCO | EU5: SCO | EV5: Manual | EX5: US113 | EY5: US113R | EZ5: Grand Rapids MI | FA5: B | FB5: 1 | FC5: 1 | FD5: 45878 | FE5: 2025/8 | FF5: 5 | FI5: 0 | FJ5: arravied to site checked all scale cable connections and found no issues. manager told me there was a printer printing short issue checked that out and ran a full functions test on the sco. | FK5: 2025-08-06T15:46:19.000Z | FL5: 1 | FM5: New Item :7360-4010-9090 New Serial Number :57-60595316 Old Item :7360-4010-9090 Old Serial Number :57-60595316 | FN5: 2025-08-06T15:46:20.000Z | FO5: 1 | FP5: Scanner/scale not weighing items on SCO17 [Generated by Portal Login: most14 Contact: Staci Mowder 3096133038 smowder@rdspos.com] | FQ5: 2025-08-06T14:43:48.000Z | FR5: 1 | FS5: CE IS NOW US133B52 | FT5: 2025-08-06T14:44:23.000Z | FU5: 1 | FV5: arravied to site checked all scale cable connections and found no issues. manager told me there was a printer printing short issue checked that out and ran a full functions test on the sco. | FW5: 2025-08-06T15:46:19.000Z | FX5: 1 | FY5: E | FZ5: Scanner/scale not weighing items on SCO17 [Generated by Portal Login: most14 Contact: Staci Mowder 3096133038 smowder@rdspos.com]-CE IS NOW US133B52-arravied to site checked all scale cable connections and found no issues. manager told me there was a printer printing short issue checked that out and ran a full functions test on the sco.-arravied to site checked all scale cable connections and found no issues. manager told me there was a printer printing short issue checked that out and ran a full functions test on the sco.-New Item :7360-4010-9090 New Serial Number :57-60595316 Old Item :7360-4010-9090 Old Serial Number :57-60595316 | GA5: arravied to site checked all scale cable connections and found no issues. manager told me there was a printer printing short issue checked that out and ran a full functions test on the sco. | GB5: 1 | GD5: 0 | GF5: 0 | GG5: 1 | GH5: CS_RESOLUTION | GI5: Resolution Description | GJ5: 2025-08-06T15:46:19.000Z | GM5: 1 | GN5: 1 | GO5: 0 | GP5: 1 | GQ5: 1 | GR5: 0 | GS5: 1 | GT5: 0 | GU5: 1 | GV5: 0 | GW5: 1 | GX5: 0 | GY5: 1 | GZ5: 0 | HA5: US133B52 | HB5: NAMER | HC5: NAMER South | HD5: US | HE5: US133 | HF5: US133A | HG5: NAMER | HH5: NAMER South | HI5: US | HJ5: US133 | HK5: US133B | HL5: Portage | HM5: MEIJER INC | HN5: 36805 | HP5: MI | HQ5: NCR | HR5: NCR | HS5: NCR
A6: 8702 | B6: 7621504463 | C6: 34 | D6: CORE ELECTRONICS | E6: US Southeast | F6: 1 | G6: 2026-08-04T15:56:23.000Z | H6: 2026-08-04T15:56:23.000Z | I6: 0 | J6: 7360-4010-9090 | K6: SSCO R6C Full Function, No Bag, XR7 Plus | L6: 156046174 | M6: 57-60595329 | N6: US133 | O6: AUTOMATIC | P6: CORE_ELECTRONICS | Q6: 34TL | R6: 2026-08-04T10:40:00.000Z | S6: 2026-08-04T14:40:00.000Z | T6: 41477121725 | V6: BLOOMINGTON | W6: 46238 | X6: 2026-08-04T11:38:00.000Z | Y6: 2026-08-04T15:38:00.000Z | AA6: 0 | AB6: US | AC6: UNITED STATES | AD6: 7820C4W2 | AE6: 7 days/w, 08 AM-8 PM, 4 HR, Response,12 HR. Resolv | AF6: 1 | AG6: 452210 | AH6: Department Stores | AI6: RET | AJ6: Retail | AK6: US133E75 | AL6: TC185228 | AM6: MEIJER/FRESH THYME #536 | AN6: MEIJER INC | AO6: 36805 | AP6: 536 | AQ6: No Intelligent Deposit | AR6: 66580479 | AS6: S1 | AU6: 2026-08-03T09:29:17.000Z | AV6: 2026-08-03T13:29:17.000Z | AX6: Undefined | AY6: ES | AZ6: US133E75 | BA6: Cannon Thomas | BB6: 0 | BC6: 1 | BD6: 0 | BE6: 57-60595329 | BF6: 0 | BG6: 0 | BH6: 1900-01-01T00:00:00.000Z | BI6: 0 | BJ6: 1900-01-01T00:00:00.000Z | BK6: 1 | BL6: 1 | BM6: 0 | BN6: MNT | BO6: 156046174 | BP6: 2026-08-04T15:56:23.000Z | BR6: 42791478 | BT6: 2 | BU6: 2026-08-11T13:33:58.000Z | BY6: 16 | CA6: 14 | CE6: 1 | CI6: 11 | CJ6: Customer Contracted Reasons | CM6: 4010 | CO6: 7360 | CP6: 0.9667 | CQ6: 0.9667 | CR6: 1.7667 | CS6: 5 | CT6: 2026-08-03T13:29:17.000Z | CU6: 2026-08-03T09:29:17.000Z | CV6: 7360-4010-9090 | CW6: SSCO R6C Full Function, No Bag, XR7 Plus | CX6: 57-60595329 | CY6: 1 | CZ6: 1 | DA6: 7360-4010-9090 | DB6: TTW WU | DC6: 47401 | DD6: 14.15 | DE6: REACTIVE | DG6: Fastlane | DH6: Retail | DI6: G370-3975-0000 | DK6: ft185038 | DL6: WCS - North America | DM6: 0 | DN6: 0 | DO6: 11 | DP6: REPLACE DEF PART | DQ6: 16 | DR6: 849 | DS6: 1569 | DT6: 13.1833 | DU6: 4 | DV6: 1 | DW6: 2 | DX6: MNT | DY6: 57-60595329 | DZ6: 1 | EA6: 1 | EB6: 1 | EC6: 0 | ED6: 0 | EE6: 1 | EF6: Manual | EG6: closed | EH6: MNT 2 | EI6: MNT 2 | EJ6: IN | EK6: 9090 | EL6: 0 | EM6: US133E | EN6: 1.7667 | EO6: 26.15 | EP6: 99991120 | EQ6: Self check out | ER6: HW | ES6: Hardware | ET6: SCO | EU6: SCO | EV6: Manual | EX6: US133 | EY6: US133D | EZ6: Indianapolis IN | FA6: B | FB6: 1 | FC6: 1 | FD6: 46242 | FE6: 2026/8 | FF6: 11 | FG6: CEM4333803:defective part | FH6: 2026-08-04T11:40:07.000Z | FI6: 1 | FJ6: arroved onsite and found that SCO12 was working. checked with store, store said light is experiencing intermittent flashing and strobing issue. Replaced lane light. Tested, new lane light is working as intended. | FK6: 2026-08-04T11:40:07.000Z | FL6: 1 | FM6: New Item :7360-4010-9090 New Serial Number :57-60595329 Old Item :7360-4010-9090 Old Serial Number :57-60595329 | FN6: 2026-08-04T11:40:10.000Z | FO6: 1 | FP6: SCO12 light is flashing and dimming, may need replaced. [Generated by Portal Login: most14 Contact: Staci Mowder 2694689716 FTFMSupport@rdspos.com] | FQ6: 2026-08-03T09:29:17.000Z | FR6: 1 | FS6: CE IS NOW US133E80 | FT6: 2026-08-03T09:34:57.000Z | FU6: 1 | FV6: CE WAS US133E80 | FW6: 2026-08-03T11:58:04.000Z | FX6: 1 | FY6: E | FZ6: SCO12 light is flashing and dimming, may need replaced. [Generated by Portal Login: most14 Contact: Staci Mowder 2694689716 FTFMSupport@rdspos.com]-CE IS NOW US133E80-CE WAS US133E80-CE IS NOW US133E76-CE WAS US133E76-CE IS NOW US133E75-LOM Order Processing, Part has been Ordered, Remedy ID 000000015097232- (Pick Up) by Agent Auto CE pickup-Oracle Order Shipped for Remedy Id: U018975638, Order/Receipt # 182468613, Ordered Part 4970525295, Part Description - KIT - R6 TRI-LIGHT W/IP CAMERA, Shipment/Receipt #2120107003, Part has been Shipped, Qty 1, Priority NFO, Shipping Method CE Pickup After Hours, BOL/Job NA, Source Location UFF USFIND1G-CEM4333803:defective part-arroved onsite and found that SCO12 was working. checked with store, store said light is experiencing intermittent flashing and strobing issue. Replaced lane light. Tested, new lane light is working as intended.-New Item :7360-4010-9090 New Serial Number :57-60595329 Old Item :7360-4010-9090 Old Serial Number :57-60595329 | GA6: arroved onsite and found that SCO12 was working. checked with store, store said light is experiencing intermittent flashing and strobing issue. Replaced lane light. Tested, new lane light is working as intended. | GB6: 1 | GD6: 0 | GF6: 0 | GG6: 1 | GH6: CS_RESOLUTION | GI6: Resolution Description | GJ6: 2026-08-04T11:40:07.000Z | GM6: 1 | GN6: 1 | GO6: 0 | GP6: 1 | GQ6: 1 | GR6: 0 | GS6: 1 | GT6: 0 | GU6: 1 | GV6: 0 | GW6: 1 | GX6: 0 | GY6: 1 | GZ6: 0 | HA6: US133E75 | HB6: NAMER | HC6: NAMER South | HD6: US | HE6: US133 | HF6: US133D | HG6: NAMER | HH6: NAMER South | HI6: US | HJ6: US133 | HK6: US133E | HL6: BLOOMINGTON | HM6: MEIJER INC | HN6: 36805 | HP6: IN | HQ6: NCR | HR6: NCR | HS6: NCR
A7: 8702 | B7: 7527904317 | C7: 34 | D7: CORE ELECTRONICS | E7: US West | F7: 0 | G7: 2025-10-07T17:50:47.000Z | H7: 2025-10-07T17:50:47.000Z | I7: 0 | J7: 7360-4010-9090 | K7: SSCO R6C Full Function, No Bag, XR7 Plus | L7: 153406533 | M7: 57-60590128 | N7: US153 | O7: AUTOMATIC | P7: CORE_ELECTRONICS | Q7: 34D9 | R7: 2025-10-06T11:43:00.000Z | S7: 2025-10-06T16:43:00.000Z | T7: 41477075518 | V7: Fairview Heights | W7: 45937 | X7: 2025-10-07T12:33:00.000Z | Y7: 2025-10-07T17:33:00.000Z | AA7: 0 | AB7: US | AC7: UNITED STATES | AD7: 7820C4ES | AE7: 7 days,8am to 8pm, 4hrs Resp,12 hrs Resol | AF7: 1 | AG7: 452210 | AH7: Department Stores | AI7: RET | AJ7: Retail | AK7: US153N74 | AL7: BJ185069 | AM7: MEIJER/FRESH THYME #631 | AN7: MEIJER INC | AO7: 36805 | AP7: 631 | AQ7: No Intelligent Deposit | AR7: 66147130 | AS7: S1 | AU7: 2025-10-06T10:01:55.000Z | AV7: 2025-10-06T15:01:55.000Z | AX7: Undefined | AY7: ES | AZ7: US153N74 | BA7: Johnson Brock | BB7: 0 | BC7: 1 | BD7: 0 | BE7: 57-60590128 | BF7: 0 | BG7: 0 | BH7: 1900-01-01T00:00:00.000Z | BI7: 0 | BJ7: 1900-01-01T00:00:00.000Z | BK7: 1 | BL7: 1 | BM7: 0 | BN7: MNT | BO7: 153406533 | BP7: 2025-10-07T17:50:47.000Z | BR7: 42791743 | BT7: 0 | CM7: 4010 | CO7: 7360 | CP7: 0.7833 | CQ7: 0.7833 | CR7: 0.45 | CS7: 0 | CT7: 2025-10-06T15:01:55.000Z | CU7: 2025-10-06T10:01:55.000Z | CV7: 7360-4010-9090 | CW7: SSCO R6C Full Function, No Bag, XR7 Plus | CX7: 57-60590128 | CY7: 1 | CZ7: 1 | DA7: 7360-4010-9090 | DB7: TTW WU | DC7: 62208 | DD7: 14.5333 | DE7: REACTIVE | DG7: Fastlane | DH7: Retail | DL7: WCS - North America | DM7: 0 | DN7: 0 | DO7: 11 | DP7: REPLACE DEF PART | DQ7: 12 | DR7: 872 | DS7: 1592 | DT7: 1.7 | DU7: 4 | DW7: 1 | DX7: MNT | DY7: 57-60590128 | DZ7: 0 | EA7: 0 | EB7: 1 | EC7: 1 | ED7: 1 | EE7: 1 | EF7: Scanned | EG7: closed | EH7: MNT 1 | EI7: MNT 1 | EJ7: IL | EK7: 9090 | EL7: 1 | EM7: US153N | EN7: 0.45 | EO7: 26.533333 | EP7: 99991120 | EQ7: Self check out | ER7: HW | ES7: Hardware | ET7: SCO | EU7: SCO | EV7: Scanned | EX7: US133 | EY7: US133A | EZ7: St Louis MO | FA7: B | FB7: 1 | FC7: 2 | FD7: 45941 | FE7: 2025/10 | FF7: 8 | FG7: CEM3923090:def | FH7: 2025-10-07T12:34:01.000Z | FI7: 1 | FJ7: Arrived on site and spoke to MOD - accessed SCO and replaced the UPC and spare standard power cable. Successfully tested. Lane is functioning as intended. | FK7: 2025-10-07T12:34:01.000Z | FL7: 1 | FM7: New Item :7360-4010-9090 New Serial Number :57-60590128 Old Item :7360-4010-9090 Old Serial Number :57-60587845 | FN7: 2025-10-07T12:34:04.000Z | FO7: 1 | FP7: Battery Backup is dead, SCO is completely down, requesting service today please [Generated by Portal Login: coas14 Contact: Ashley 3092131564 ftfmsupport@rdspos.com] | FQ7: 2025-10-06T10:01:55.000Z | FR7: 1 | FS7: CE IS NOW US153N74 | FT7: 2025-10-06T10:32:27.000Z | FU7: 1 | FV7: Arrived on site and spoke to MOD regarding issues - accessed SCO and UPC is dead, batt depleted, suspending and ordering replacement - PN: 4970506744 | FW7: 2025-10-06T12:08:29.000Z | FX7: 1 | FY7: E | FZ7: Battery Backup is dead, SCO is completely down, requesting service today please [Generated by Portal Login: coas14 Contact: Ashley 3092131564 ftfmsupport@rdspos.com]-CE IS NOW US153N74-Arrived on site and spoke to MOD regarding issues - accessed SCO and UPC is dead, batt depleted, suspending and ordering replacement - PN: 4970506744-LOM order processing, Part has been Ordered , Remedy Id 000000014880731 - (Next Day) by Agent AUTO VIP-Oracle Order Shipped for Remedy Id: U018768683, Order/Receipt # 181756106, Ordered Part 4970527939, Part Description - R6.0 UPS 110V 800VA with USB communication port & EMC Improvements, Shipment/Receipt #2111109683, Part has been Shipped, Qty 1, Priority OVERNIGHT, Shipping Method UPS-Air-Next Day Air Saver, BOL/Job 1ZH92Y061300524892, Source Location UFF USFEWR1G-CEM3923090:def-Arrived on site and spoke to MOD - accessed SCO and replaced the UPC and spare standard power cable. Successfully tested. Lane is functioning as intended.-New Item :7360-4010-9090 New Serial Number :57-60590128 Old Item :7360-4010-9090 Old Serial Number :57-60587845 | GA7: Arrived on site and spoke to MOD - accessed SCO and replaced the UPC and spare standard power cable. Successfully tested. Lane is functioning as intended. | GB7: 1 | GD7: 0 | GF7: 0 | GG7: 1 | GH7: CS_RESOLUTION | GI7: Resolution Description | GJ7: 2025-10-07T12:34:01.000Z | GM7: 1 | GN7: 0 | GO7: 0 | GP7: 1 | GQ7: 1 | GR7: 0 | GS7: 1 | GT7: 0 | GU7: 1 | GV7: 0 | GW7: 1 | GX7: 0 | GY7: 1 | GZ7: 0 | HA7: US153N74 | HB7: NAMER | HC7: NAMER West | HD7: US | HE7: US153 | HF7: US153M | HG7: NAMER | HH7: NAMER West | HI7: US | HJ7: US153 | HK7: US153N | HL7: Fairview Heights | HM7: MEIJER INC | HN7: 36805 | HP7: IL | HQ7: NCR | HR7: NCR | HS7: NCR
A8: 8702 | B8: 7618403340 | C8: 34 | D8: CORE ELECTRONICS | E8: US West | F8: 0 | G8: 2026-07-06T17:22:14.000Z | H8: 2026-07-06T17:22:14.000Z | I8: 0 | J8: 7360-4010-9090 | K8: SSCO R6C Full Function, No Bag, XR7 Plus | L8: 156586345 | M8: 57-60595294 | N8: US153 | O8: AUTOMATIC | P8: CORE_ELECTRONICS | Q8: 34D9 | R8: 2026-07-03T16:45:00.000Z | S8: 2026-07-03T21:45:00.000Z | T8: 41477129116 | V8: BLOOMINGTON | W8: 46209 | X8: 2026-07-06T12:09:00.000Z | Y8: 2026-07-06T17:09:00.000Z | AA8: 0 | AB8: US | AC8: UNITED STATES | AD8: 7820C4W2 | AE8: 7 days/w, 08 AM-8 PM, 4 HR, Response,12 HR. Resolv | AF8: 1 | AG8: 452210 | AH8: Department Stores | AI8: RET | AJ8: Retail | AK8: US153R54 | AL8: ND185172 | AM8: MEIJER/FRESH THYME #638 | AN8: MEIJER INC | AO8: 36805 | AP8: 638 | AQ8: No Intelligent Deposit | AR8: 66538792 | AS8: S1 | AU8: 2026-07-03T16:06:53.000Z | AV8: 2026-07-03T21:06:53.000Z | AX8: Undefined | AY8: ES | AZ8: US153R54 | BA8: Daugherty Nicholas | BB8: 1 | BC8: 0 | BD8: 0 | BE8: 57-60595294 | BF8: 0 | BG8: 0 | BH8: 1900-01-01T00:00:00.000Z | BI8: 0 | BJ8: 1900-01-01T00:00:00.000Z | BK8: 1 | BL8: 1 | BM8: 0 | BN8: MNT | BO8: 156586345 | BP8: 2026-07-06T17:22:14.000Z | BR8: 42791770 | BT8: 0 | BU8: 2026-08-07T13:58:37.000Z | BY8: 16 | CA8: 32 | CE8: 0 | CI8: 11 | CJ8: Customer Contracted Reasons | CM8: 4010 | CO8: 7360 | CP8: 0.2833 | CQ8: 0.2833 | CR8: 2.8667 | CS8: 0 | CT8: 2026-07-03T21:06:54.000Z | CU8: 2026-07-03T16:06:54.000Z | CV8: 7360-4010-9090 | CW8: SSCO R6C Full Function, No Bag, XR7 Plus | CX8: 57-60595294 | CY8: 1 | CZ8: 1 | DA8: 7360-4010-9090 | DB8: TTW WU | DC8: 61704 | DD8: 32.05 | DE8: REACTIVE | DG8: Fastlane | DH8: Retail | DK8: ft185038 | DL8: WCS - North America | DM8: 0 | DN8: 0 | DO8: 11 | DP8: REPLACE DEF PART | DQ8: 16 | DR8: 1923 | DS8: 4083 | DT8: 0.65 | DU8: 4 | DV8: 1 | DW8: 2 | DX8: MNT | DY8: 57-60595294 | DZ8: 0 | EA8: 0 | EB8: 1 | EC8: 1 | ED8: 1 | EE8: 1 | EF8: Scanned | EG8: closed | EH8: MNT 2 | EI8: MNT 2 | EJ8: IL | EK8: 9090 | EL8: 1 | EM8: US153R | EN8: 2.8667 | EO8: 68.05 | EP8: 99991120 | EQ8: Self check out | ER8: HW | ES8: Hardware | ET8: SCO | EU8: SCO | EV8: Scanned | EX8: US153 | EY8: US153R | EZ8: Peoria IL | FA8: C | FB8: 1 | FC8: 2 | FD8: 46214 | FE8: 2026/7 | FF8: 11 | FG8: CE IS NOW US153R54 | FH8: 2026-07-06T09:01:13.000Z | FI8: 1 | FJ8: Successfully swapped out defective UPS for new. Tested and confirmed functional. SCO brought back in to full operation. Confirmed with MoD. No further action taken. Closing call. | FK8: 2026-07-06T12:06:45.000Z | FL8: 1 | FM8: New Item :7360-4010-9090 New Serial Number :57-60595294 Old Item :7360-4010-9090 Old Serial Number :57-60595294 | FN8: 2026-07-06T12:10:53.000Z | FO8: 1 | FP8: Battery Backup is faulty [Generated by Portal Login: repa14 Contact: Patrick Reeves 3092411908 ftfmsupport@rdspos.com] | FQ8: 2026-07-03T16:06:54.000Z | FR8: 1 | FS8: CE IS NOW US153R54 | FT8: 2026-07-03T16:08:02.000Z | FU8: 1 | FV8: CE WAS US153R54 | FW8: 2026-07-03T16:13:31.000Z | FX8: 1 | FY8: E | FZ8: Battery Backup is faulty [Generated by Portal Login: repa14 Contact: Patrick Reeves 3092411908 ftfmsupport@rdspos.com]-CE IS NOW US153R54-CE WAS US153R54-CE IS NOW US153R51-CE IS NOW US153R51-CE arrived onsite and spoke with Riley who called in the issue. Multiple times over the last week she has come into work at 6am and the SCO would be off and the UPS beeping, requiring her to power off UPS and then power back on. Indicative of failing UPS. Ordering Replacement UPS.-LOM order processing, Part has been Ordered , Remedy Id 000000015076011 - (Next Day) by Agent FSC Order-Oracle Order Shipped for Remedy Id: U018955066, Order/Receipt # 182393426, Ordered Part 4970534153, Part Description - UPS (N70-800) LV 100V/120V 800VA with USB communication Port and EMC Improvements, Shipment/Receipt #2119598720, Part has been Shipped, Qty 1, Priority OVERNIGHT, Shipping Method UPS-Air-Next Day Air Saver, BOL/Job 1ZH92Y051303109480, Source Location PTC AVL-CE IS NOW US153R54-Successfully swapped out defective UPS for new. Tested and confirmed functional. SCO brought back in to full operation. Confirmed with MoD. No further action taken. Closing call.-New Item :7360-4010-9090 New Serial Number :57-60595294 Old Item :7360-4010-9090 Old Serial Number :57-60595294 | GA8: Successfully swapped out defective UPS for new. Tested and confirmed functional. SCO brought back in to full operation. Confirmed with MoD. No further action taken. Closing call. | GB8: 1 | GD8: 0 | GF8: 0 | GG8: 1 | GH8: CS_RESOLUTION | GI8: Resolution Description | GJ8: 2026-07-06T12:06:45.000Z | GM8: 1 | GN8: 0 | GO8: 0 | GP8: 1 | GQ8: 1 | GR8: 0 | GS8: 1 | GT8: 0 | GU8: 1 | GV8: 0 | GW8: 1 | GX8: 0 | GY8: 1 | GZ8: 0 | HA8: US153R54 | HB8: NAMER | HC8: NAMER West | HD8: US | HE8: US153 | HF8: US153R | HG8: NAMER | HH8: NAMER West | HI8: US | HJ8: US153 | HK8: US153R | HL8: BLOOMINGTON | HM8: MEIJER INC | HN8: 36805 | HP8: IL | HQ8: NCR | HR8: NCR | HS8: NCR
A9: 8702 | B9: 7530306800 | C9: NR | D9: NOTE RECYCLER | E9: US West | F9: 0 | G9: 2025-10-31T01:15:40.000Z | H9: 2025-10-31T01:15:40.000Z | I9: 0 | J9: 7360-4010-9090 | K9: SSCO R6C Full Function, No Bag, XR7 Plus | L9: 142427776 | M9: 57-58264238 | N9: US153 | O9: AUTOMATIC | P9: NOTE_RECYCLER | Q9: NR5Z | R9: 2025-10-30T19:43:00.000Z | S9: 2025-10-31T00:43:00.000Z | T9: 41477086390 | V9: ST. LOUIS | W9: 45960 | X9: 2025-10-30T19:59:00.000Z | Y9: 2025-10-31T00:59:00.000Z | AA9: 0 | AB9: US | AC9: UNITED STATES | AD9: 7820C4ES | AE9: 7 days,8am to 8pm, 4hrs Resp,12 hrs Resol | AF9: 1 | AG9: 452210 | AH9: Department Stores | AI9: RET | AJ9: Retail | AK9: US153N79 | AL9: BS185333 | AM9: Meijer #448 Fresh Thyme Market | AN9: MEIJER INC | AO9: 36805 | AP9: 448 | AQ9: No Intelligent Deposit | AR9: 66180700 | AS9: S1 | AU9: 2025-10-30T13:09:42.000Z | AV9: 2025-10-30T18:09:42.000Z | AX9: Undefined | AY9: ES | AZ9: US153N79 | BA9: Schnur Blake | BB9: 0 | BC9: 0 | BD9: 1 | BE9: 57-58264238 | BF9: 0 | BG9: 0 | BH9: 1900-01-01T00:00:00.000Z | BI9: 0 | BJ9: 1900-01-01T00:00:00.000Z | BK9: 1 | BL9: 1 | BM9: 0 | BN9: MNT | BO9: 142427776 | BP9: 2025-10-31T01:15:40.000Z | BQ9: 38.633357 | BR9: 42511030 | BS9: -90.238448 | BT9: 0 | CM9: 4010 | CO9: 7360 | CP9: 0.2667 | CQ9: 0.2667 | CR9: 0.2667 | CS9: 26 | CT9: 2025-10-30T18:09:43.000Z | CU9: 2025-10-30T13:09:43.000Z | CV9: 7360-4010-9090 | CW9: SSCO R6C Full Function, No Bag, XR7 Plus | CX9: 57-58264238 | CY9: 1 | CZ9: 1 | DA9: 7360-4010-9090 | DB9: TTW WU | DC9: 63110 | DD9: 6.8333 | DE9: REACTIVE | DG9: Fastlane | DH9: Retail | DI9: G552-1000-5001 | DL9: WCS - North America | DM9: 0 | DN9: 0 | DO9: 11 | DP9: REPLACE DEF PART | DQ9: 16 | DR9: 410 | DS9: 410 | DT9: 6.5667 | DU9: 4 | DW9: 2 | DX9: MNT | DY9: 57-58264238 | DZ9: 1 | EA9: 1 | EB9: 1 | EC9: 0 | ED9: 0 | EE9: 1 | EF9: Scanned | EG9: closed | EH9: MNT 2 | EI9: MNT 2 | EJ9: MO | EK9: 9090 | EL9: 0 | EM9: US153N | EN9: 0.2667 | EO9: 6.8333333 | EP9: 99991120 | EQ9: Self check out | ER9: HW | ES9: Hardware | ET9: SCO | EU9: SCO | EV9: Scanned | EX9: US133 | EY9: US133A | EZ9: St Louis MO | FA9: B | FB9: 1 | FC9: 1 | FD9: 45962 | FE9: 2025/10 | FF9: 7 | FG9: CEM3904117:jamming | FH9: 2025-10-30T19:56:01.000Z | FI9: 1 | FJ9: arrived onsite, verified issue, signed in, loaded into pml, replaced top mod due to intermittently jamming | FK9: 2025-10-30T19:59:34.000Z | FL9: 1 | FM9: New Item :7360-4010-9090 New Serial Number :57-58264238 Old Item :7360-4010-9090 Old Serial Number :57-58264214 | FN9: 2025-10-30T19:59:36.000Z | FO9: 1 | FP9: Note recycler continually jamming and making a very loud strange noise on SCO11 [Generated by Portal Login: most14 Contact: Staci Mowder 3096133038 ftfmsupport@rdspos.com] | FQ9: 2025-10-30T13:09:43.000Z | FR9: 1 | FS9: CE IS NOW US153N64 | FT9: 2025-10-30T13:35:22.000Z | FU9: 1 | FV9: CE WAS US153N64 | FW9: 2025-10-30T19:36:41.000Z | FX9: 1 | FY9: E | FZ9: Note recycler continually jamming and making a very loud strange noise on SCO11 [Generated by Portal Login: most14 Contact: Staci Mowder 3096133038 ftfmsupport@rdspos.com]-CE IS NOW US153N64-CE WAS US153N64-CE IS NOW US153N79-CEM3904117:jamming-arrived onsite, verified issue, signed in, loaded into pml, replaced top mod due to intermittently jamming-New Item :7360-4010-9090 New Serial Number :57-58264238 Old Item :7360-4010-9090 Old Serial Number :57-58264214 | GA9: arrived onsite, verified issue, signed in, loaded into pml, replaced top mod due to intermittently jamming | GB9: 1 | GD9: 0 | GF9: 0 | GG9: 1 | GH9: CS_RESOLUTION | GI9: Resolution Description | GJ9: 2025-10-30T19:59:34.000Z | GM9: 1 | GN9: 1 | GO9: 0 | GP9: 1 | GQ9: 1 | GR9: 0 | GS9: 1 | GT9: 0 | GU9: 1 | GV9: 0 | GW9: 1 | GX9: 0 | GY9: 1 | GZ9: 0 | HA9: US153N79 | HB9: NAMER | HC9: NAMER West | HD9: US | HE9: US153 | HF9: US153M | HG9: NAMER | HH9: NAMER West | HI9: US | HJ9: US153 | HK9: US153N | HL9: ST. LOUIS | HM9: MEIJER INC | HN9: 36805 | HP9: MO | HQ9: NCR | HR9: NCR | HS9: NCR
A10: 8702 | B10: 7610001329 | C10: 8P | D10: COIN RECYCLER | E10: US West | F10: 1 | G10: 2026-04-17T18:54:38.000Z | H10: 2026-04-17T18:54:38.000Z | I10: 0 | J10: 7360-4010-9090 | K10: SSCO R6C Full Function, No Bag, XR7 Plus | L10: 153406521 | M10: 57-60590106 | N10: US153 | O10: AUTOMATIC | P10: COIN_RECYCLER | Q10: 8PCV | R10: 2026-04-10T17:13:00.000Z | S10: 2026-04-10T22:13:00.000Z | T10: 41477088992 | V10: VADNAIS HEIGHTS | W10: 46129 | X10: 2026-04-17T13:38:00.000Z | Y10: 2026-04-17T18:38:00.000Z | Z10: DEBRIS FOUND | AA10: 0 | AB10: US | AC10: UNITED STATES | AD10: 7820ZNES | AE10: 7 Days/Wk, 8-8, NBD Fix (Restoral) | AF10: 1 | AG10: 452210 | AH10: Department Stores | AI10: RET | AJ10: Retail | AK10: US153R24 | AL10: OO185035 | AM10: MEIJER/FRESH THYME #545 | AN10: MEIJER INC | AO10: 36805 | AP10: 545 | AQ10: No Intelligent Deposit | AR10: 66423633 | AS10: S1 | AU10: 2026-04-10T15:34:01.000Z | AV10: 2026-04-10T20:34:01.000Z | AX10: Undefined | AY10: ES | AZ10: US153R24 | BA10: Ogunnowo Olufemi | BB10: 0 | BC10: 1 | BD10: 0 | BE10: 57-60590106 | BF10: 0 | BG10: 0 | BH10: 1900-01-01T00:00:00.000Z | BI10: 0 | BJ10: 1900-01-01T00:00:00.000Z | BK10: 1 | BL10: 1 | BM10: 0 | BN10: MNT | BO10: 153406521 | BP10: 2026-04-17T18:54:38.000Z | BR10: 42791461 | BT10: 1 | BU10: 2026-05-04T17:38:28.000Z | BY10: 16 | CA10: 82 | CI10: 11 | CJ10: Customer Contracted Reasons | CM10: 4010 | CO10: 7360 | CP10: 5.55 | CQ10: 5.55 | CR10: 6.15 | CS10: 0 | CT10: 2026-04-10T20:34:01.000Z | CU10: 2026-04-10T15:34:01.000Z | CV10: 7360-4010-9090 | CW10: SSCO R6C Full Function, No Bag, XR7 Plus | CX10: 57-60590106 | CY10: 1 | CZ10: 1 | DA10: 7360-4010-9090 | DB10: TTW WU | DC10: 55127 | DD10: 82.0667 | DE10: REACTIVE | DG10: Fastlane | DH10: Retail | DJ10: Store545 | DK10: ft185038 | DL10: WCS - North America | DM10: 0 | DN10: 0 | DO10: 11 | DP10: REPLACE DEF PART | DQ10: 0 | DR10: 4924 | DS10: 9964 | DT10: 1.65 | DU10: 0 | DV10: 1 | DW10: 2 | DX10: MNT | DY10: 57-60590106 | DZ10: 1 | EA10: 1 | EB10: 1 | EC10: 1 | ED10: 1 | EE10: 1 | EF10: Manual | EG10: closed | EH10: MNT 2 | EI10: MNT 2 | EJ10: MN | EK10: 9090 | EL10: 1 | EM10: US153R | EN10: 6.15 | EO10: 166.06667 | EP10: 99991120 | EQ10: Self check out | ER10: HW | ES10: Hardware | ET10: SCO | EU10: SCO | EV10: Manual | EX10: US153 | EY10: US153J | EZ10: Minneapolis MN | FA10: A | FB10: 1 | FC10: 4 | FD10: 46130 | FE10: 2026/4 | FF10: 18 | FG10: CEM4148145:Validator icon indicator kept blinking | FH10: 2026-04-17T13:40:34.000Z | FI10: 1 | FJ10: SNFI has it that no closed SR for past 13 weeks. Icon indicator on the coin recycler kept blinking, the validator was replaced. Manager Calie tested and verified SCO made successful transactions in cards and cards. Task closed. | FK10: 2026-04-17T13:40:34.000Z | FL10: 1 | FM10: New Item :7360-4010-9090 New Serial Number :57-60590106 Old Item :7360-4010-9090 Old Serial Number :57-60590106 | FN10: 2026-04-17T13:40:36.000Z | FO10: 1 | FP10: Debis Flap Stuck. Error Code: 16-6-0--99-131184 [Generated by Portal Login: coas14 Contact: Ashley Cooper 3092131564 ftfmsupport@rdspos.com] | FQ10: 2026-04-10T15:34:01.000Z | FR10: 1 | FS10: CE IS NOW US153R24 | FT10: 2026-04-10T15:37:29.000Z | FU10: 1 | FV10: The active cashbox is jammed. Jammed coins that have clogged the white wheel could not be removed in its entirety as a few coins suspected to be dollar coin could not be purged. Active cashbox to be replaced, order made, and task suspended. | FW10: 2026-04-10T18:38:55.000Z | FX10: 1 | FY10: E | FZ10: Debis Flap Stuck. Error Code: 16-6-0--99-131184 [Generated by Portal Login: coas14 Contact: Ashley Cooper 3092131564 ftfmsupport@rdspos.com]-CE IS NOW US153R24-The active cashbox is jammed. Jammed coins that have clogged the white wheel could not be removed in its entirety as a few coins suspected to be dollar coin could not be purged. Active cashbox to be replaced, order made, and task suspended.-LOM order processing, Part has been Ordered , Remedy Id 000000015018199 - (Next Day) by Agent VIP HOLD-Escalation Request: Penalty Acct. Breaching SLA. Need to complete the SR asap once part is delivered [Added by: Vannie Kristoffer Tabares Portal Login: ncr.com Phone Number: 4106969 Email Address: vanniekristoffer.tabares@ncrvoyix.com Contact By: GIM]-Oracle Order Shipped for Remedy Id: U018902099, Order/Receipt # 182201050, Ordered Part 4970533870, Part Description - CR5000 Active Cashbox Type A (non-dissipative tracks) (Service Part), Shipment/Receipt #2118058467, Part has been Shipped, Qty 1, Priority OVERNIGHT, Shipping Method UPS-Air-Next Day Air Saver, BOL/Job 1ZH92Y061300693076, Source Location UFF USFCAE1G-Escalation Update: CE ETA 14:00.-CEM4148129:shut down validator-Part fail to function, it did not work, shutting down the validator and entire coin recycler.-The part did not work, for it shut down validator, order for another part and task suspended.-LOM order processing, Part has been Ordered , Remedy Id 000000015020703 - (Next Day) by Agent AUTO VIP-Oracle Order Shipped for Remedy Id: U018904494, Order/Receipt # 182207725, Ordered Part 4970533870, Part Description - CR5000 Active Cashbox Type A (non-dissipative tracks) (Service Part), Shipment/Receipt #2118088803, Part has been Shipped, Qty 1, Priority OVERNIGHT, Shipping Method UPS-Air-Next Day Air Saver, BOL/Job 1ZH92Y061300695789, Source Location UFF USFDFW8G-The active cashbox P/N 4970529815 installed on the SCO now functions properly. The reported malfunction of the active cashbox was due to coinbox motor suffering from overheating due to slack holding screws causing it to vibrate Ã nd heat up as it works. The screws were made to be firm, and existing cashbox reused as substituting cashbox of P/N 4970533870 ia an invalid substitute in this case The reason for the suspension is the state of icon indicators.The icon indicator of validator blinks red. a swap of Validator from working lane confirmed validator is defective. Validator ordered.-LOM order processing, Part has been Ordered , Remedy Id 000000015022256 - (Pick Up)MN, Arden Hillsby Agent Auto CE pickup-Oracle Order Shipped for Remedy Id: U018905783, Order/Receipt # 182212531, Ordered Part 4970526620, Part Description - Crane Xchange Validator Type A (Service Part), Shipment/Receipt #2118116553, Part has been Shipped, Qty 1, Priority NFO, Shipping Method CE Pickup After Hours, BOL/Job NA, Source Location UFF USFMSP1G-CEM4148145:Validator icon indicator kept blinking-SNFI has it that no closed SR for past 13 weeks. Icon indicator on the coin recycler kept blinking, the validator was replaced. Manager Calie tested and verified SCO made successful transactions in cards and cards. Task closed.-New Item :7360-4010-9090 New Serial Number :57-60590106 Old Item :7360-4010-9090 Old Serial Number :57-60590106 | GA10: SNFI has it that no closed SR for past 13 weeks. Icon indicator on the coin recycler kept blinking, the validator was replaced. Manager Calie tested and verified SCO made successful transactions in cards and cards. Task closed. | GB10: 1 | GD10: 0 | GF10: 0 | GG10: 1 | GH10: CS_RESOLUTION | GI10: Resolution Description | GJ10: 2026-04-17T13:40:34.000Z | GM10: 1 | GN10: 0 | GO10: 0 | GP10: 1 | GQ10: 1 | GR10: 0 | GS10: 1 | GT10: 0 | GU10: 1 | GV10: 0 | GW10: 1 | GX10: 0 | GY10: 1 | GZ10: 0 | HA10: US153R24 | HB10: NAMER | HC10: NAMER West | HD10: US | HE10: US153 | HF10: US153R | HG10: NAMER | HH10: NAMER West | HI10: US | HJ10: US153 | HK10: US153R | HL10: VADNAIS HEIGHTS | HM10: MEIJER INC | HN10: 36805 | HO10: 1 | HP10: MN | HQ10: NCR | HR10: NCR | HS10: NCR
A11: 8702 | B11: 7526100324 | C11: 82 | D11: SCANNER/SCAN-SCALE | E11: US Southeast | F11: 0 | G11: 2025-09-25T17:05:25.000Z | H11: 2025-09-25T17:05:25.000Z | I11: 0 | J11: 7360-4010-9090 | K11: SSCO R6C Full Function, No Bag, XR7 Plus | L11: 153402680 | M11: 57-60588438 | N11: US133 | O11: AUTOMATIC | P11: BARCODE_READER | Q11: 827H | R11: 2025-09-25T12:44:00.000Z | S11: 2025-09-25T16:44:00.000Z | T11: 41477125989 | V11: COLUMBUS | W11: 45925 | X11: 2025-09-25T12:50:00.000Z | Y11: 2025-09-25T16:50:00.000Z | Z11: CHG | AA11: 0 | AB11: US | AC11: UNITED STATES | AD11: 7820C4ES | AE11: 7 days,8am to 8pm, 4hrs Resp,12 hrs Resol | AF11: 1 | AG11: 452210 | AH11: Department Stores | AI11: RET | AJ11: Retail | AK11: US133C17 | AL11: JM185792 | AM11: MEIJER/FRESH THYME #926 | AN11: MEIJER INC | AO11: 36805 | AP11: 926 | AQ11: No Intelligent Deposit | AR11: 66129883 | AS11: S1 | AU11: 2025-09-18T16:54:02.000Z | AV11: 2025-09-18T20:54:02.000Z | AW11: 19KB | AX11: 19KB-THE CONSUMER USED THE ATM INAPPROPRIATELY AND CAUSED THE ATM TO BE OUT OF SERVICE | AY11: ES | AZ11: US133C17 | BA11: Mumaw Jayden | BB11: 0 | BC11: 0 | BD11: 0 | BE11: 57-60588438 | BF11: 0 | BG11: 0 | BH11: 1900-01-01T00:00:00.000Z | BI11: 0 | BJ11: 1900-01-01T00:00:00.000Z | BK11: 1 | BL11: 0 | BM11: 0 | BN11: MNT | BO11: 153402680 | BP11: 2025-09-25T17:05:25.000Z | BR11: 42793651 | BT11: 1 | BU11: 2025-10-13T18:23:43.000Z | CI11: 11 | CJ11: Customer Contracted Reasons | CM11: 4010 | CO11: 7360 | CP11: 0.1 | CQ11: 0.1 | CR11: 0.2667 | CS11: 138 | CT11: 2025-09-18T20:54:03.000Z | CU11: 2025-09-18T16:54:03.000Z | CV11: 7360-4010-9090 | CW11: SSCO R6C Full Function, No Bag, XR7 Plus | CX11: 57-60588438 | CY11: 0 | CZ11: 0 | DA11: 7360-4010-9090 | DB11: TTW WU | DC11: 43240 | DD11: 79.9333 | DE11: REACTIVE | DG11: Fastlane | DH11: Retail | DI11: G370-2599-0000 | DK11: as251244 | DL11: WCS - North America | DM11: 0 | DN11: 0 | DO11: 53 | DP11: NO FAULT FOUND | DQ11: 16 | DR11: 4796 | DS11: 9836 | DT11: 79.8333 | DU11: 4 | DV11: 1 | DW11: 2 | DX11: CHGC | DY11: 57-60588438 | DZ11: 0 | EA11: 0 | EB11: 0 | EC11: 0 | ED11: 0 | EE11: 0 | EF11: Manual | EG11: closed | EH11: CHGC 2 | EI11: CHGC 2 | EJ11: OH | EK11: 9090 | EL11: 0 | EM11: US133C | EN11: 0.2667 | EO11: 163.93333 | EP11: 99991120 | EQ11: Self check out | ER11: HW | ES11: Hardware | ET11: SCO | EU11: SCO | EV11: Manual | EX11: US113 | EY11: US113R | EZ11: Columbus OH | FA11: B | FB11: 1 | FC11: 1 | FD11: 45927 | FE11: 2025/9 | FF11: 10 | FG11: Paul and rival spoke to Amy informed her that I do have a ticket for softball 16 and there was a customer using self. Checkout 16, but the issue was for bad speakers and the sell checkout speakers are fine. Did a some tests with Amy to verify it and no issue was found. | FH11: 2025-09-25T12:52:12.000Z | FI11: 1 | FJ11: No fault was found upon arrival self.Checkout sixteen speakers are working just fine tested with amy to confirm | FK11: 2025-09-25T12:52:13.000Z | FL11: 1 | FM11: New Item :7360-4010-9090 New Serial Number :57-60588438 Old Item :7360-4010-9090 Old Serial Number :57-60588438 | FN11: 2025-09-25T12:52:13.000Z | FO11: 1 | FP11: Speakers on SCO16 sounds muffled [Generated by Portal Login: most14 Contact: Staci Mowder 3096133038 ftfmsupport@rdspos.com] | FQ11: 2025-09-18T16:54:04.000Z | FR11: 1 | FS11: CE IS NOW US133C24 | FT11: 2025-09-18T19:12:25.000Z | FU11: 1 | FV11: CE WAS US133C24 | FW11: 2025-09-23T08:48:44.000Z | FX11: 1 | FY11: E | FZ11: Speakers on SCO16 sounds muffled [Generated by Portal Login: most14 Contact: Staci Mowder 3096133038 ftfmsupport@rdspos.com]-CE IS NOW US133C24-CE WAS US133C24-CE IS NOW US133J31-CE WAS US133J31-CE IS NOW US133C17-site address is incorrect. it should be 849 Polaris pkway Westerville, Ohio. not Columbus ohio-Paul and rival spoke to Amy informed her that I do have a ticket for softball 16 and there was a customer using self. Checkout 16, but the issue was for bad speakers and the sell checkout speakers are fine. Did a some tests with Amy to verify it and no issue was found.-No fault was found upon arrival self.Checkout sixteen speakers are working just fine tested with amy to confirm-New Item :7360-4010-9090 New Serial Number :57-60588438 Old Item :7360-4010-9090 Old Serial Number :57-60588438 | GA11: Paul and rival spoke to Amy informed her that I do have a ticket for softball 16 and there was a customer using self. Checkout 16, but the issue was for bad speakers and the sell checkout speakers are fine. Did a some tests with Amy to verify it and no issue was found. | GB11: 1 | GD11: 0 | GF11: 0 | GG11: 1 | GH11: CS_RESOLUTION | GI11: Resolution Description | GJ11: 2025-09-25T12:52:12.000Z | GM11: 1 | GN11: 1 | GO11: 0 | GP11: 1 | GQ11: 1 | GR11: 0 | GS11: 1 | GT11: 0 | GU11: 1 | GV11: 0 | GW11: 1 | GX11: 0 | GY11: 1 | GZ11: 0 | HA11: US133C17 | HB11: NAMER | HC11: NAMER South | HD11: US | HE11: US133 | HF11: US133A | HG11: NAMER | HH11: NAMER South | HI11: US | HJ11: US133 | HK11: US133B | HL11: COLUMBUS | HM11: MEIJER INC | HN11: 36805 | HO11: 1 | HP11: OH | HQ11: NCR | HR11: NCR | HS11: NCR
A12: 8702 | B12: 7621012398 | C12: PR | D12: PRINTER | E12: US Southeast | F12: 0 | G12: 2026-07-29T19:21:29.000Z | H12: 2026-07-29T19:21:29.000Z | I12: 0 | J12: 7360-4010-9090 | K12: SSCO R6C Full Function, No Bag, XR7 Plus | L12: 153195484 | M12: 57-60588422 | N12: US133 | O12: AUTOMATIC | P12: PRINTER_RECEIPT | Q12: PR7C | R12: 2026-07-29T14:44:00.000Z | S12: 2026-07-29T18:44:00.000Z | T12: 41477056288 | V12: Indianapolis | W12: 46232 | X12: 2026-07-29T15:08:00.000Z | Y12: 2026-07-29T19:08:00.000Z | AA12: 0 | AB12: US | AC12: UNITED STATES | AD12: 7820C4W2 | AE12: 7 days/w, 08 AM-8 PM, 4 HR, Response,12 HR. Resolv | AF12: 1 | AG12: 452210 | AH12: Department Stores | AI12: RET | AJ12: Retail | AK12: US133E72 | AL12: MM185619 | AM12: MEIJER/FRESH THYME #526 | AN12: MEIJER INC | AO12: 36805 | AP12: 526 | AQ12: No Intelligent Deposit | AR12: 66572083 | AS12: S1 | AU12: 2026-07-29T13:51:56.000Z | AV12: 2026-07-29T17:51:56.000Z | AW12: 19NP | AX12: 19NP-DAMAGE OF ATM BY REPLENISHER OR USER OF ATM | AY12: ES | AZ12: US133E72 | BA12: McAtee Megan | BB12: 0 | BC12: 0 | BD12: 0 | BE12: 57-60588422 | BF12: 0 | BG12: 0 | BH12: 1900-01-01T00:00:00.000Z | BI12: 0 | BJ12: 1900-01-01T00:00:00.000Z | BK12: 1 | BL12: 0 | BM12: 0 | BN12: MNT | BO12: 153195484 | BP12: 2026-07-29T19:21:29.000Z | BQ12: 39.913493 | BR12: 42791437 | BS12: -86.201989 | BT12: 2 | BU12: 2026-08-07T13:58:37.000Z | BY12: 16 | CA12: 1 | CE12: 1 | CI12: 11 | CJ12: Customer Contracted Reasons | CM12: 4010 | CO12: 7360 | CP12: 0.4 | CQ12: 0.4 | CR12: 0.75 | CS12: 3 | CT12: 2026-07-29T17:51:57.000Z | CU12: 2026-07-29T13:51:57.000Z | CV12: 7360-4010-9090 | CW12: SSCO R6C Full Function, No Bag, XR7 Plus | CX12: 57-60588422 | CY12: 0 | CZ12: 0 | DA12: 7360-4010-9090 | DB12: TTW WU | DC12: 46260 | DD12: 1.2833 | DE12: REACTIVE | DG12: Fastlane | DH12: Retail | DI12: 7746-F242 | DK12: ft185038 | DL12: WCS - North America | DM12: 0 | DN12: 0 | DO12: 12 | DP12: RESEAT PART/MODULE | DQ12: 16 | DR12: 77 | DS12: 77 | DT12: 0.8833 | DU12: 4 | DV12: 1 | DW12: 2 | DX12: CHGC | DY12: 57-60588422 | DZ12: 0 | EA12: 0 | EB12: 0 | EC12: 0 | ED12: 0 | EE12: 0 | EF12: Scanned | EG12: closed | EH12: CHGC 2 | EI12: CHGC 2 | EJ12: IN | EK12: 9090 | EL12: 0 | EM12: US133E | EN12: 0.75 | EO12: 1.2833333 | EP12: 99991120 | EQ12: Self check out | ER12: HW | ES12: Hardware | ET12: SCO | EU12: SCO | EV12: Scanned | EX12: US133 | EY12: US133D | EZ12: Indianapolis IN | FA12: B | FB12: 1 | FC12: 1 | FD12: 46235 | FE12: 2026/7 | FF12: 6 | FG12: the tray sensor for the printer came unplugged from the printer control board. was able to disassemble the printer enough to be able to plug the cable back in. reassembled and tested. tested good. unit is now fully operational. informed sight that if they have more problems with that printer to re-call it back in and we'll replace the printer. | FH12: 2026-07-29T15:09:27.000Z | FI12: 1 | FJ12: the tray sensor for the printer came unplugged from the printer control board. was able to disassemble the printer enough to be able to plug the cable back in. reassembled and tested. tested good. unit is now fully operational. informed sight that if they have more problems with that printer to re-call it back in and we'll replace the printer. | FK12: 2026-07-29T15:09:27.000Z | FL12: 1 | FM12: New Item :7360-4010-9090 New Serial Number :57-60588422 Old Item :7360-4010-9090 Old Serial Number :57-60591352 | FN12: 2026-07-29T15:09:29.000Z | FO12: 1 | FP12: Printer error, says they need paper but new roll does not clear the error. The red and yellow wires are not plugged into the board anymore and unable to plug in Also missing the top plate for the printer cover. [Generated by Portal Login: coas14 Contact: Ashley Cooper 3092131564 ftfmsupport@rdspos.com] | FQ12: 2026-07-29T13:51:57.000Z | FR12: 1 | FS12: CE IS NOW US133E72 | FT12: 2026-07-29T13:54:29.000Z | FU12: 1 | FV12: Ernesto | FW12: 2026-07-29T15:09:27.000Z | FX12: 1 | FY12: E | FZ12: Printer error, says they need paper but new roll does not clear the error. The red and yellow wires are not plugged into the board anymore and unable to plug in Also missing the top plate for the printer cover. [Generated by Portal Login: coas14 Contact: Ashley Cooper 3092131564 ftfmsupport@rdspos.com]-CE IS NOW US133E72-Ernesto-the tray sensor for the printer came unplugged from the printer control board. was able to disassemble the printer enough to be able to plug the cable back in. reassembled and tested. tested good. unit is now fully operational. informed sight that if they have more problems with that printer to re-call it back in and we'll replace the printer.-the tray sensor for the printer came unplugged from the printer control board. was able to disassemble the printer enough to be able to plug the cable back in. reassembled and tested. tested good. unit is now fully operational. informed sight that if they have more problems with that printer to re-call it back in and we'll replace the printer.-New Item :7360-4010-9090 New Serial Number :57-60588422 Old Item :7360-4010-9090 Old Serial Number :57-60591352 | GA12: the tray sensor for the printer came unplugged from the printer control board. was able to disassemble the printer enough to be able to plug the cable back in. reassembled and tested. tested good. unit is now fully operational. informed sight that if they have more problems with that printer to re-call it back in and we'll replace the printer. | GB12: 1 | GD12: 0 | GF12: 0 | GG12: 1 | GH12: CS_RESOLUTION | GI12: Resolution Description | GJ12: 2026-07-29T15:09:27.000Z | GM12: 1 | GN12: 1 | GO12: 0 | GP12: 1 | GQ12: 1 | GR12: 0 | GS12: 1 | GT12: 0 | GU12: 1 | GV12: 0 | GW12: 1 | GX12: 0 | GY12: 1 | GZ12: 0 | HA12: US133E72 | HB12: NAMER | HC12: NAMER South | HD12: US | HE12: US133 | HF12: US133D | HG12: NAMER | HH12: NAMER South | HI12: US | HJ12: US133 | HK12: US133E | HL12: Indianapolis | HM12: MEIJER INC | HN12: 36805 | HP12: IN | HQ12: NCR | HR12: NCR | HS12: NCR
A13: 8702 | B13: 7619803959 | C13: PR | D13: PRINTER | E13: US West | F13: 0 | G13: 2026-07-18T22:06:10.000Z | H13: 2026-07-18T22:06:10.000Z | I13: 0 | J13: 7360-4010-9090 | K13: SSCO R6C Full Function, No Bag, XR7 Plus | L13: 153524539 | M13: 57-60591341 | N13: US153 | O13: AUTOMATIC | P13: PRINTER_RECEIPT | Q13: PR7C | R13: 2026-07-18T17:39:00.000Z | S13: 2026-07-18T21:39:00.000Z | T13: 41477094299 | V13: Lafayette | W13: 46221 | X13: 2026-07-18T17:52:00.000Z | Y13: 2026-07-18T21:52:00.000Z | AA13: 0 | AB13: US | AC13: UNITED STATES | AD13: 7820C4W2 | AE13: 7 days/w, 08 AM-8 PM, 4 HR, Response,12 HR. Resolv | AF13: 1 | AG13: 452210 | AH13: Department Stores | AI13: RET | AJ13: Retail | AK13: US153R61 | AL13: TB185225 | AM13: MEIJER/FRESH THYME #523 | AN13: MEIJER INC | AO13: 36805 | AP13: 523 | AQ13: No Intelligent Deposit | AR13: 66556418 | AS13: S1 | AU13: 2026-07-17T14:52:17.000Z | AV13: 2026-07-17T18:52:17.000Z | AX13: Undefined | AY13: ES | AZ13: US153R61 | BA13: Bolde Thomas | BB13: 0 | BC13: 0 | BD13: 0 | BE13: 57-60591341 | BF13: 0 | BG13: 0 | BH13: 1900-01-01T00:00:00.000Z | BI13: 0 | BJ13: 1900-01-01T00:00:00.000Z | BK13: 1 | BL13: 1 | BM13: 0 | BN13: MNT | BO13: 153524539 | BP13: 2026-07-18T22:06:10.000Z | BR13: 42791433 | BT13: 2 | BU13: 2026-08-07T13:58:37.000Z | BY13: 16 | CA13: 15 | CE13: 1 | CI13: 11 | CJ13: Customer Contracted Reasons | CM13: 4010 | CO13: 7360 | CP13: 0.2167 | CQ13: 0.2167 | CR13: 1.7167 | CS13: 3 | CT13: 2026-07-17T18:52:17.000Z | CU13: 2026-07-17T14:52:17.000Z | CV13: 7360-4010-9090 | CW13: SSCO R6C Full Function, No Bag, XR7 Plus | CX13: 57-60591341 | CY13: 0 | CZ13: 0 | DA13: 7360-4010-9090 | DB13: TTW WU | DC13: 47905 | DD13: 15 | DE13: REACTIVE | DG13: Fastlane | DH13: Retail | DI13: H400-0003-0000 | DK13: ft185038 | DL13: WCS - North America | DM13: 0 | DN13: 0 | DO13: 3 | DP13: CLEAR MEDIA/DEBRIS | DQ13: 16 | DR13: 900 | DS13: 1620 | DT13: 14.7833 | DU13: 4 | DV13: 1 | DW13: 2 | DX13: MNT | DY13: 57-60591341 | DZ13: 1 | EA13: 1 | EB13: 1 | EC13: 0 | ED13: 0 | EE13: 1 | EF13: Scanned | EG13: closed | EH13: MNT 2 | EI13: MNT 2 | EJ13: IN | EK13: 9090 | EL13: 0 | EM13: US153R | EN13: 1.7167 | EO13: 27 | EP13: 99991120 | EQ13: Self check out | ER13: HW | ES13: Hardware | ET13: SCO | EU13: SCO | EV13: Scanned | EX13: US153 | EY13: US153R | EZ13: Lafayette IN | FA13: D | FB13: 1 | FC13: 1 | FD13: 46221 | FE13: 2026/7 | FF13: 4 | FI13: 0 | FL13: 0 | FM13: New Item :7360-4010-9090 New Serial Number :57-60591341 Old Item :7360-4010-9090 Old Serial Number :57-60591341 | FN13: 2026-07-18T17:54:12.000Z | FO13: 1 | FP13: Receipts on SCO12 printing very lightly and are not legible. [Generated by Portal Login: most14 Contact: Staci Mowder 2694689716 FTFMSupport@rdspos.com] | FQ13: 2026-07-17T14:52:18.000Z | FR13: 1 | FS13: CE IS NOW US153R61 | FT13: 2026-07-17T14:55:49.000Z | FU13: 1 | FV13: Receipt printer had a small sliver of paper jammed between print head and cutting blade. Removed piece of paper and tested with MOD Maurice. Confirmed printer print quality is back to normal. Tested SCO and left in service with no issues present | FW13: 2026-07-18T17:54:10.000Z | FX13: 1 | FY13: E | FZ13: Receipts on SCO12 printing very lightly and are not legible. [Generated by Portal Login: most14 Contact: Staci Mowder 2694689716 FTFMSupport@rdspos.com]-CE IS NOW US153R61-Receipt printer had a small sliver of paper jammed between print head and cutting blade. Removed piece of paper and tested with MOD Maurice. Confirmed printer print quality is back to normal. Tested SCO and left in service with no issues present-New Item :7360-4010-9090 New Serial Number :57-60591341 Old Item :7360-4010-9090 Old Serial Number :57-60591341 | GA13: Receipt printer had a small sliver of paper jammed between print head and cutting blade. Removed piece of paper and tested with MOD Maurice. Confirmed printer print quality is back to normal. Tested SCO and left in service with no issues present | GB13: 1 | GD13: 0 | GF13: 0 | GG13: 1 | GH13: CS_RESOLUTION | GI13: Resolution Description | GJ13: 2026-07-18T17:54:10.000Z | GM13: 1 | GN13: 1 | GO13: 0 | GP13: 1 | GQ13: 1 | GR13: 0 | GS13: 1 | GT13: 0 | GU13: 1 | GV13: 0 | GW13: 1 | GX13: 0 | GY13: 1 | GZ13: 0 | HA13: US153R61 | HB13: NAMER | HC13: NAMER West | HD13: US | HE13: US153 | HF13: US153R | HG13: NAMER | HH13: NAMER West | HI13: US | HJ13: US153 | HK13: US153R | HL13: Lafayette | HM13: MEIJER INC | HN13: 36805 | HP13: IN | HQ13: NCR | HR13: NCR | HS13: NCR
A14: 8702 | B14: 7526401175 | C14: 8P | D14: COIN RECYCLER | E14: US Southeast | F14: 1 | G14: 2025-09-22T19:56:46.000Z | H14: 2025-09-22T19:56:46.000Z | I14: 0 | J14: 7360-4010-9090 | K14: SSCO R6C Full Function, No Bag, XR7 Plus | L14: 152858781 | M14: 57-60587770 | N14: US133 | O14: AUTOMATIC | P14: COIN_RECYCLER | Q14: 8PCZ | R14: 2025-09-22T12:24:00.000Z | S14: 2025-09-22T16:24:00.000Z | T14: 41477095626 | V14: MAYFIELD HEIGHTS | W14: 45922 | X14: 2025-09-22T15:40:00.000Z | Y14: 2025-09-22T19:40:00.000Z | AA14: 0 | AB14: US | AC14: UNITED STATES | AD14: 7820C4ES | AE14: 7 days,8am to 8pm, 4hrs Resp,12 hrs Resol | AF14: 1 | AG14: 452210 | AH14: Department Stores | AI14: RET | AJ14: Retail | AK14: US133C75 | AL14: MB185576 | AM14: MEIJER/FRESH THYME #925 | AN14: MEIJER INC | AO14: 36805 | AP14: 925 | AQ14: No Intelligent Deposit | AR14: 66125696 | AS14: S1 | AU14: 2025-09-21T15:08:03.000Z | AV14: 2025-09-21T19:08:03.000Z | AX14: Undefined | AY14: ES | AZ14: US133C75 | BA14: Brannon Marquis | BB14: 0 | BC14: 1 | BD14: 0 | BE14: 57-60587770 | BF14: 0 | BG14: 0 | BH14: 1900-01-01T00:00:00.000Z | BI14: 0 | BJ14: 1900-01-01T00:00:00.000Z | BK14: 1 | BL14: 1 | BM14: 0 | BN14: MNT | BO14: 152858781 | BP14: 2025-09-22T19:56:46.000Z | BQ14: 41.518337 | BR14: 42793649 | BS14: -81.449531 | BT14: 0 | CM14: 4010 | CO14: 7360 | CP14: 1.0167 | CQ14: 1.0167 | CR14: 2.0167 | CS14: 0 | CT14: 2025-09-21T19:08:06.000Z | CU14: 2025-09-21T15:08:06.000Z | CV14: 7360-4010-9090 | CW14: SSCO R6C Full Function, No Bag, XR7 Plus | CX14: 57-60587770 | CY14: 1 | CZ14: 1 | DA14: 7360-4010-9090 | DB14: TTW WU | DC14: 44124 | DD14: 12.5333 | DE14: REACTIVE | DG14: Fastlane | DH14: Retail | DI14: 6684-3000-6206 | DL14: WCS - North America | DM14: 0 | DN14: 0 | DO14: 11 | DP14: REPLACE DEF PART | DQ14: 16 | DR14: 752 | DS14: 1472 | DT14: 9.2667 | DU14: 4 | DW14: 2 | DX14: MNT | DY14: 57-60587770 | DZ14: 1 | EA14: 1 | EB14: 1 | EC14: 0 | ED14: 0 | EE14: 1 | EF14: Scanned | EG14: closed | EH14: MNT 2 | EI14: MNT 2 | EJ14: OH | EK14: 9090 | EL14: 1 | EM14: US133C | EN14: 2.0167 | EO14: 24.533333 | EP14: 99991120 | EQ14: Self check out | ER14: HW | ES14: Hardware | ET14: SCO | EU14: SCO | EV14: Scanned | EX14: US113 | EY14: US113R | EZ14: Cleveland OH | FA14: A | FB14: 1 | FC14: 2 | FD14: 45927 | FE14: 2025/9 | FF14: 11 | FG14: sco 16 replace active coin box. open PML and ran add. verify that coins can be dispense and accepted multiple times. verify with the team lead that sco 16 is working properly | FH14: 2025-09-22T15:42:14.000Z | FI14: 1 | FJ14: New Item :7360-4010-9090 New Serial Number :57-60587770 Old Item :7360-4010-9090 Old Serial Number :57-60587755 | FK14: 2025-09-22T15:42:16.000Z | FL14: 1 | FM14: Oracle Order Shipped for Remedy Id: U018757658, Order/Receipt # 181715126, Ordered Part 4970533870, Part Description - CR5000 Active Cashbox Type A (non-dissipative tracks) (Service Part), Shipment/Receipt #2110884625, Part has been Shipped, Qty 1, Priority OVERNIGHT, Shipping Method UPS-Air-Next Day Air Saver, BOL/Job 1ZJ21V721302559584, Source Location PDS DIR | FN14: 2025-09-25T22:05:00.000Z | FO14: 1 | FP14: SCO16 has a Coin recycler error -Coin box motor jammed [Generated by Portal Login: most14 Contact: Staci Mowder 3096133038 ftfmsupport@rdspos.com] | FQ14: 2025-09-21T15:08:06.000Z | FR14: 1 | FS14: CE IS NOW US133C75 | FT14: 2025-09-21T15:18:28.000Z | FU14: 1 | FV14: CE WAS US133C75 | FW14: 2025-09-22T08:09:09.000Z | FX14: 1 | FY14: E | FZ14: SCO16 has a Coin recycler error -Coin box motor jammed [Generated by Portal Login: most14 Contact: Staci Mowder 3096133038 ftfmsupport@rdspos.com]-CE IS NOW US133C75-CE WAS US133C75-CE IS NOW US133C73-metal piece inside active cashbox is bent out of place needs replaced part showing in c75 ppk-CE IS NOW US133C75-LOM order processing, Part has been Ordered , Remedy Id 000000014869320 - (Next Day) by Agent Auto VIP P000-CEM3941256:bad-sco 16 replace active coin box. open PML and ran add. verify that coins can be dispense and accepted multiple times. verify with the team lead that sco 16 is working properly-New Item :7360-4010-9090 New Serial Number :57-60587770 Old Item :7360-4010-9090 Old Serial Number :57-60587755-Oracle Order Shipped for Remedy Id: U018757658, Order/Receipt # 181715126, Ordered Part 4970533870, Part Description - CR5000 Active Cashbox Type A (non-dissipative tracks) (Service Part), Shipment/Receipt #2110884625, Part has been Shipped, Qty 1, Priority OVERNIGHT, Shipping Method UPS-Air-Next Day Air Saver, BOL/Job 1ZJ21V721302559584, Source Location PDS DIR | GA14: sco 16 replace active coin box. open PML and ran add. verify that coins can be dispense and accepted multiple times. verify with the team lead that sco 16 is working properly | GB14: 1 | GD14: 0 | GF14: 0 | GG14: 1 | GH14: CS_RESOLUTION | GI14: Resolution Description | GJ14: 2025-09-22T15:42:14.000Z | GM14: 1 | GN14: 0 | GO14: 0 | GP14: 1 | GQ14: 1 | GR14: 0 | GS14: 1 | GT14: 0 | GU14: 1 | GV14: 0 | GW14: 1 | GX14: 0 | GY14: 1 | GZ14: 0 | HA14: US133C75 | HB14: NAMER | HC14: NAMER South | HD14: US | HE14: US133 | HF14: US133A | HG14: NAMER | HH14: NAMER South | HI14: US | HJ14: US133 | HK14: US133B | HL14: MAYFIELD HEIGHTS | HM14: MEIJER INC | HN14: 36805 | HP14: OH | HQ14: NCR | HR14: NCR | HS14: NCR
