Workbook

Sheet Summary & Assumptions
B2: FRESH THYME FARMERS MARKET — Power Services Revenue Forecast
B3: Contract 1473438 • Customer #9299639 • Billed quarterly (Advance Invoice) • Prepared for Account Executive review
B5: FORECAST ASSUMPTIONS (edit the yellow cells — everything recalculates)
B7: CPI uplift — Base case (CPI + 2, current cycle) | C7: 0.055
B8: CPI uplift — Low scenario | C8: 0.03
B9: CPI uplift — High scenario | C9: 0.07
B10: Contract escalation formula | C10: CPI + 2%
B11: Note | C11: BOC confirmed this cycle: 'CPI 2+' formula resulted in a total 5.5% increase (applied uniformly to every line, 2025→2026). 5.5% is the base case for FY2027.
B14: ANNUAL CONTRACT VALUE — Actuals & Forecast
C15: FY2025 (Oct25–Sep26) | D15: FY2026 (Oct26–Sep27) APPROVED | E15: FY2027 Forecast LOW | F15: FY2027 Forecast BASE | G15: FY2027 Forecast HIGH
B16: Total Annual Revenue | C16: ='FY2025'!C3 | D16: ='FY2026'!C3 | E16: ='FY2027 Forecast'!F3 | F16: ='FY2027 Forecast'!G3 | G16: ='FY2027 Forecast'!H3
B17: Quarterly Invoice (÷ 4) | C17: =C16/4 | D17: =D16/4 | E17: =E16/4 | F17: =F16/4 | G17: =G16/4
B18: YoY $ Increase | D18: =D16-C16 | E18: =E16-D16 | F18: =F16-D16 | G18: =G16-D16
B19: YoY % Increase | D19: =D16/C16-1 | E19: =E16/D16-1 | F19: =F16/D16-1 | G19: =G16/D16-1
B21: Reading it: FY2026 is the prebill you just approved. FY2027 = FY2026 × (1 + CPI uplift), line by line. Base case uses 5.5%.

Sheet FY2025
A1: FY2025 — Prebill Detail by Service Line
A3: GRAND TOTAL (annual) | C3: =C17
A5: Service / Product Line | B5: Lanes | C5: Annual $ (this yr) | D5: Quarterly $ | E5: Per-Lane $
A6: Power Transportation Inbound/Outbound w/ Optimization (Large) | B6: 1 | C6: 14105.79 | D6: =C6/4 | E6: =IF(B6=0,0,C6/B6)
A7: Invoice Reconciliation - Stores (Small) | B7: 1 | C7: 32083.46 | D7: =C7/4 | E7: =IF(B7=0,0,C7/B7)
A8: Retalix Store/HQ POS/HQ POS EXCHANGE/POS CONNECT | B8: 70 | C8: 40308.8 | D8: =C8/4 | E8: =IF(B8=0,0,C8/B8)
A9: Power HQ (large format), Per store for retailer with 26 to 100 stores | B9: 70 | C9: 145375.3 | D9: =C9/4 | E9: =IF(B9=0,0,C9/B9)
A10: Power Webstore (large format), Per store for retailer with 26 to 100 stores | B10: 70 | C10: 40308.8 | D10: =C10/4 | E10: =IF(B10=0,0,C10/B10)
A11: Power Portal (large format), Per store for retailer with 26 to 100 stores | B11: 70 | C11: 0 | D11: =C11/4 | E11: =IF(B11=0,0,C11/B11)
A12: Power DAX (large format), Per store for retailer with 26 to 100 stores | B12: 70 | C12: 55463.1 | D12: =C12/4 | E12: =IF(B12=0,0,C12/B12)
A13: Power Inventory (large format), Per store for retailer with 26 to 100 stores | B13: 70 | C13: 50411.9 | D13: =C13/4 | E13: =IF(B13=0,0,C13/B13)
A14: Power+ Purchasing (initial site) (Large) | B14: 1 | C14: 40554.14 | D14: =C14/4 | E14: =IF(B14=0,0,C14/B14)
A15: Power+ WMS (initial site) (Large) | B15: 1 | C15: 28564.2 | D15: =C15/4 | E15: =IF(B15=0,0,C15/B15)
A16: Power Dock (initial site) (Large) | B16: 1 | C16: 5994.97 | D16: =C16/4 | E16: =IF(B16=0,0,C16/B16)
A17: TOTAL | B17: =SUM(B6:B16) | C17: =SUM(C6:C16) | D17: =SUM(D6:D16) | E17: =SUM(E6:E16)

Sheet FY2026
A1: FY2026 — Prebill Detail by Service Line
A3: GRAND TOTAL (annual) | C3: =C17
A5: Service / Product Line | B5: Lanes | C5: Annual $ (this yr) | D5: Prior Yr $ | E5: YoY $ | F5: YoY % | G5: Quarterly $ | H5: Per-Lane $
A6: Power Transportation Inbound/Outbound w/ Optimization (Large) | B6: 1 | C6: 14881.61 | D6: 14105.79 | E6: =C6-D6 | F6: =IF(D6=0,0,C6/D6-1) | G6: =C6/4 | H6: =IF(B6=0,0,C6/B6)
A7: Invoice Reconciliation - Stores (Small) | B7: 1 | C7: 33848.05 | D7: 32083.46 | E7: =C7-D7 | F7: =IF(D7=0,0,C7/D7-1) | G7: =C7/4 | H7: =IF(B7=0,0,C7/B7)
A8: Retalix Store/HQ POS/HQ POS EXCHANGE/POS CONNECT | B8: 70 | C8: 42525.7 | D8: 40308.8 | E8: =C8-D8 | F8: =IF(D8=0,0,C8/D8-1) | G8: =C8/4 | H8: =IF(B8=0,0,C8/B8)
A9: Power HQ (large format), Per store for retailer with 26 to 100 stores | B9: 70 | C9: 153370.7 | D9: 145375.3 | E9: =C9-D9 | F9: =IF(D9=0,0,C9/D9-1) | G9: =C9/4 | H9: =IF(B9=0,0,C9/B9)
A10: Power Webstore (large format), Per store for retailer with 26 to 100 stores | B10: 70 | C10: 42525.7 | D10: 40308.8 | E10: =C10-D10 | F10: =IF(D10=0,0,C10/D10-1) | G10: =C10/4 | H10: =IF(B10=0,0,C10/B10)
A11: Power Portal (large format), Per store for retailer with 26 to 100 stores | B11: 70 | C11: 0 | D11: 0 | E11: =C11-D11 | F11: =IF(D11=0,0,C11/D11-1) | G11: =C11/4 | H11: =IF(B11=0,0,C11/B11)
A12: Power DAX (large format), Per store for retailer with 26 to 100 stores | B12: 70 | C12: 58513.7 | D12: 55463.1 | E12: =C12-D12 | F12: =IF(D12=0,0,C12/D12-1) | G12: =C12/4 | H12: =IF(B12=0,0,C12/B12)
A13: Power Inventory (large format), Per store for retailer with 26 to 100 stores | B13: 70 | C13: 53184.6 | D13: 50411.9 | E13: =C13-D13 | F13: =IF(D13=0,0,C13/D13-1) | G13: =C13/4 | H13: =IF(B13=0,0,C13/B13)
A14: Power+ Purchasing (initial site) (Large) | B14: 1 | C14: 42784.62 | D14: 40554.14 | E14: =C14-D14 | F14: =IF(D14=0,0,C14/D14-1) | G14: =C14/4 | H14: =IF(B14=0,0,C14/B14)
A15: Power+ WMS (initial site) (Large) | B15: 1 | C15: 30135.23 | D15: 28564.2 | E15: =C15-D15 | F15: =IF(D15=0,0,C15/D15-1) | G15: =C15/4 | H15: =IF(B15=0,0,C15/B15)
A16: Power Dock (initial site) (Large) | B16: 1 | C16: 6324.69 | D16: 5994.97 | E16: =C16-D16 | F16: =IF(D16=0,0,C16/D16-1) | G16: =C16/4 | H16: =IF(B16=0,0,C16/B16)
A17: TOTAL | B17: =SUM(B6:B16) | C17: =SUM(C6:C16) | D17: =SUM(D6:D16) | E17: =SUM(E6:E16) | F17: =IF(D17=0,0,C17/D17-1) | G17: =SUM(G6:G16) | H17: =SUM(H6:H16)

Sheet FY2027 Forecast
A1: FY2027 FORECAST (Oct 2027 – Sep 2028) — FY2026 × (1 + CPI uplift), by line
A3: GRAND TOTAL (annual) | C3: =C17 | F3: =F17 | G3: =G17 | H3: =H17
A4: Quarterly (Base ÷4) | G4: =G3/4
A5: Service / Product Line | B5: Lanes | C5: FY2026 Base $ | D5: CPI applied | F5: Forecast LOW | G5: Forecast BASE | H5: Forecast HIGH
A6: Power Transportation Inbound/Outbound w/ Optimization (Large) | B6: 1 | C6: ='FY2026'!C6 | D6: ='Summary & Assumptions'!$C$7 | F6: =C6*(1+'Summary & Assumptions'!$C$8) | G6: =C6*(1+'Summary & Assumptions'!$C$7) | H6: =C6*(1+'Summary & Assumptions'!$C$9)
A7: Invoice Reconciliation - Stores (Small) | B7: 1 | C7: ='FY2026'!C7 | D7: ='Summary & Assumptions'!$C$7 | F7: =C7*(1+'Summary & Assumptions'!$C$8) | G7: =C7*(1+'Summary & Assumptions'!$C$7) | H7: =C7*(1+'Summary & Assumptions'!$C$9)
A8: Retalix Store/HQ POS/HQ POS EXCHANGE/POS CONNECT | B8: 70 | C8: ='FY2026'!C8 | D8: ='Summary & Assumptions'!$C$7 | F8: =C8*(1+'Summary & Assumptions'!$C$8) | G8: =C8*(1+'Summary & Assumptions'!$C$7) | H8: =C8*(1+'Summary & Assumptions'!$C$9)
A9: Power HQ (large format), Per store for retailer with 26 to 100 stores | B9: 70 | C9: ='FY2026'!C9 | D9: ='Summary & Assumptions'!$C$7 | F9: =C9*(1+'Summary & Assumptions'!$C$8) | G9: =C9*(1+'Summary & Assumptions'!$C$7) | H9: =C9*(1+'Summary & Assumptions'!$C$9)
A10: Power Webstore (large format), Per store for retailer with 26 to 100 stores | B10: 70 | C10: ='FY2026'!C10 | D10: ='Summary & Assumptions'!$C$7 | F10: =C10*(1+'Summary & Assumptions'!$C$8) | G10: =C10*(1+'Summary & Assumptions'!$C$7) | H10: =C10*(1+'Summary & Assumptions'!$C$9)
A11: Power Portal (large format), Per store for retailer with 26 to 100 stores | B11: 70 | C11: ='FY2026'!C11 | D11: ='Summary & Assumptions'!$C$7 | F11: =C11*(1+'Summary & Assumptions'!$C$8) | G11: =C11*(1+'Summary & Assumptions'!$C$7) | H11: =C11*(1+'Summary & Assumptions'!$C$9)
A12: Power DAX (large format), Per store for retailer with 26 to 100 stores | B12: 70 | C12: ='FY2026'!C12 | D12: ='Summary & Assumptions'!$C$7 | F12: =C12*(1+'Summary & Assumptions'!$C$8) | G12: =C12*(1+'Summary & Assumptions'!$C$7) | H12: =C12*(1+'Summary & Assumptions'!$C$9)
A13: Power Inventory (large format), Per store for retailer with 26 to 100 stores | B13: 70 | C13: ='FY2026'!C13 | D13: ='Summary & Assumptions'!$C$7 | F13: =C13*(1+'Summary & Assumptions'!$C$8) | G13: =C13*(1+'Summary & Assumptions'!$C$7) | H13: =C13*(1+'Summary & Assumptions'!$C$9)
A14: Power+ Purchasing (initial site) (Large) | B14: 1 | C14: ='FY2026'!C14 | D14: ='Summary & Assumptions'!$C$7 | F14: =C14*(1+'Summary & Assumptions'!$C$8) | G14: =C14*(1+'Summary & Assumptions'!$C$7) | H14: =C14*(1+'Summary & Assumptions'!$C$9)
A15: Power+ WMS (initial site) (Large) | B15: 1 | C15: ='FY2026'!C15 | D15: ='Summary & Assumptions'!$C$7 | F15: =C15*(1+'Summary & Assumptions'!$C$8) | G15: =C15*(1+'Summary & Assumptions'!$C$7) | H15: =C15*(1+'Summary & Assumptions'!$C$9)
A16: Power Dock (initial site) (Large) | B16: 1 | C16: ='FY2026'!C16 | D16: ='Summary & Assumptions'!$C$7 | F16: =C16*(1+'Summary & Assumptions'!$C$8) | G16: =C16*(1+'Summary & Assumptions'!$C$7) | H16: =C16*(1+'Summary & Assumptions'!$C$9)
A17: TOTAL | B17: =SUM(B6:B16) | C17: =SUM(C6:C16) | D17: ='Summary & Assumptions'!$C$7 | F17: =SUM(F6:F16) | G17: =SUM(G6:G16) | H17: =SUM(H6:H16)

Sheet Trend & Charts
A1: 3-YEAR REVENUE TREND
A3: Fiscal Year | B3: Annual Revenue (Base)
A4: FY2025 | B4: ='FY2025'!C3
A5: FY2026 (approved) | B5: ='FY2026'!C3
A6: FY2027 (base fcst) | B6: ='FY2027 Forecast'!G3
A9: By Service Line (annual $)
A10: Service / Product Line | B10: FY2025 | C10: FY2026 | D10: FY2027 Base
A11: Power Transportation Inbound/Outbound w/ Optimization (Large) | B11: ='FY2025'!C6 | C11: ='FY2026'!C6 | D11: ='FY2027 Forecast'!G6
A12: Invoice Reconciliation - Stores (Small) | B12: ='FY2025'!C7 | C12: ='FY2026'!C7 | D12: ='FY2027 Forecast'!G7
A13: Retalix Store/HQ POS/HQ POS EXCHANGE/POS CONNECT | B13: ='FY2025'!C8 | C13: ='FY2026'!C8 | D13: ='FY2027 Forecast'!G8
A14: Power HQ (large format), Per store for retailer with 26 to 100 stores | B14: ='FY2025'!C9 | C14: ='FY2026'!C9 | D14: ='FY2027 Forecast'!G9
A15: Power Webstore (large format), Per store for retailer with 26 to 100 stores | B15: ='FY2025'!C10 | C15: ='FY2026'!C10 | D15: ='FY2027 Forecast'!G10
A16: Power Portal (large format), Per store for retailer with 26 to 100 stores | B16: ='FY2025'!C11 | C16: ='FY2026'!C11 | D16: ='FY2027 Forecast'!G11
A17: Power DAX (large format), Per store for retailer with 26 to 100 stores | B17: ='FY2025'!C12 | C17: ='FY2026'!C12 | D17: ='FY2027 Forecast'!G12
A18: Power Inventory (large format), Per store for retailer with 26 to 100 stores | B18: ='FY2025'!C13 | C18: ='FY2026'!C13 | D18: ='FY2027 Forecast'!G13
A19: Power+ Purchasing (initial site) (Large) | B19: ='FY2025'!C14 | C19: ='FY2026'!C14 | D19: ='FY2027 Forecast'!G14
A20: Power+ WMS (initial site) (Large) | B20: ='FY2025'!C15 | C20: ='FY2026'!C15 | D20: ='FY2027 Forecast'!G15
A21: Power Dock (initial site) (Large) | B21: ='FY2025'!C16 | C21: ='FY2026'!C16 | D21: ='FY2027 Forecast'!G16
A28: FY2027 Scenario Range
A29: Scenario | B29: Annual $
A30: Low | B30: ='FY2027 Forecast'!F3
A31: Base | B31: ='FY2027 Forecast'!G3
A32: High | B32: ='FY2027 Forecast'!H3
